Workbook

Sheet README
A1: Insurance Comparison Platform - Reference Data Workbook
A3: Purpose | B3: Structured reference data from research through October 1, 2026 (California auto and home; Texas, Florida, New York, Illinois, Pennsylvania, Georgia, North Carolina and Virginia auto; Texas, Florida, New York, Illinois, Pennsylvania, Georgia, North Carolina and Virginia home verified from primary sources; California home credit-use rules still open) for the U.S. auto and home insurance education/comparison project.
A4: As-of date | B4: 46296
A5: Important | B5: This is reference data, not insurer quotes or advice. Most entries come from secondary sources and must be checked against state DOI, statute or carrier filings before use on a live site.
A6: How to edit | B6: Edit any cell in the data tabs. Add new rows at the bottom, keep the standard columns filled, and set Verification Status from the dropdown.
A7: Standard columns | B7: Every data tab ends with: Source, Source URL, Date Collected, Geographic Scope, Data Type, Verification Status, Last Updated, Notes.
A9: Verification Status legend
A10: Primary source | B10: From a regulator, government body or the carrier's own published terms. Still confirm it is current.
A11: Secondary - unverified | B11: From a comparison site, publisher or blog. Treat as a lead to verify, not a fact to publish.
A12: Conflicting | B12: Sources disagree. See Conflicts Log.
A13: Not researched | B13: Placeholder row; nothing researched yet.
A15: Status count by tab (live formulas)
A16: Tab | B16: Primary source | C16: Secondary - unverified | D16: Conflicting | E16: Not researched | F16: Total rows
A17: State Min Limits | B17: =COUNTIF('State Min Limits'!$N$2:$N$500,"Primary source") | C17: =COUNTIF('State Min Limits'!$N$2:$N$500,"Secondary - unverified") | D17: =COUNTIF('State Min Limits'!$N$2:$N$500,"Conflicting") | E17: =COUNTIF('State Min Limits'!$N$2:$N$500,"Not researched") | F17: =SUM(B17:E17)
A18: Rating Factors | B18: =COUNTIF('Rating Factors'!$L$2:$L$500,"Primary source") | C18: =COUNTIF('Rating Factors'!$L$2:$L$500,"Secondary - unverified") | D18: =COUNTIF('Rating Factors'!$L$2:$L$500,"Conflicting") | E18: =COUNTIF('Rating Factors'!$L$2:$L$500,"Not researched") | F18: =SUM(B18:E18)
A19: Discounts | B19: =COUNTIF(Discounts!$K$2:$K$500,"Primary source") | C19: =COUNTIF(Discounts!$K$2:$K$500,"Secondary - unverified") | D19: =COUNTIF(Discounts!$K$2:$K$500,"Conflicting") | E19: =COUNTIF(Discounts!$K$2:$K$500,"Not researched") | F19: =SUM(B19:E19)
A20: Telematics | B20: =COUNTIF(Telematics!$M$2:$M$500,"Primary source") | C20: =COUNTIF(Telematics!$M$2:$M$500,"Secondary - unverified") | D20: =COUNTIF(Telematics!$M$2:$M$500,"Conflicting") | E20: =COUNTIF(Telematics!$M$2:$M$500,"Not researched") | F20: =SUM(B20:E20)
A21: Coverage Details | B21: =COUNTIF('Coverage Details'!$J$2:$J$500,"Primary source") | C21: =COUNTIF('Coverage Details'!$J$2:$J$500,"Secondary - unverified") | D21: =COUNTIF('Coverage Details'!$J$2:$J$500,"Conflicting") | E21: =COUNTIF('Coverage Details'!$J$2:$J$500,"Not researched") | F21: =SUM(B21:E21)
A22: Price Benchmarks | B22: =COUNTIF('Price Benchmarks'!$K$2:$K$500,"Primary source") | C22: =COUNTIF('Price Benchmarks'!$K$2:$K$500,"Secondary - unverified") | D22: =COUNTIF('Price Benchmarks'!$K$2:$K$500,"Conflicting") | E22: =COUNTIF('Price Benchmarks'!$K$2:$K$500,"Not researched") | F22: =SUM(B22:E22)
A23: Regulatory Watch | B23: =COUNTIF('Regulatory Watch'!$J$2:$J$500,"Primary source") | C23: =COUNTIF('Regulatory Watch'!$J$2:$J$500,"Secondary - unverified") | D23: =COUNTIF('Regulatory Watch'!$J$2:$J$500,"Conflicting") | E23: =COUNTIF('Regulatory Watch'!$J$2:$J$500,"Not researched") | F23: =SUM(B23:E23)
A24: CA Auto Verified | B24: =COUNTIF('CA Auto Verified'!$J$2:$J$500,"Primary source") | C24: =COUNTIF('CA Auto Verified'!$J$2:$J$500,"Secondary - unverified") | D24: =COUNTIF('CA Auto Verified'!$J$2:$J$500,"Conflicting") | E24: =COUNTIF('CA Auto Verified'!$J$2:$J$500,"Not researched") | F24: =SUM(B24:E24)
A25: CA Home Verified | B25: =COUNTIF('CA Home Verified'!$J$2:$J$500,"Primary source") | C25: =COUNTIF('CA Home Verified'!$J$2:$J$500,"Secondary - unverified") | D25: =COUNTIF('CA Home Verified'!$J$2:$J$500,"Conflicting") | E25: =COUNTIF('CA Home Verified'!$J$2:$J$500,"Not researched") | F25: =SUM(B25:E25)
A26: TX Auto Verified | B26: =COUNTIF('TX Auto Verified'!$J$2:$J$500,"Primary source") | C26: =COUNTIF('TX Auto Verified'!$J$2:$J$500,"Secondary - unverified") | D26: =COUNTIF('TX Auto Verified'!$J$2:$J$500,"Conflicting") | E26: =COUNTIF('TX Auto Verified'!$J$2:$J$500,"Not researched") | F26: =SUM(B26:E26)
A27: FL Auto Verified | B27: =COUNTIF('FL Auto Verified'!$J$2:$J$500,"Primary source") | C27: =COUNTIF('FL Auto Verified'!$J$2:$J$500,"Secondary - unverified") | D27: =COUNTIF('FL Auto Verified'!$J$2:$J$500,"Conflicting") | E27: =COUNTIF('FL Auto Verified'!$J$2:$J$500,"Not researched") | F27: =SUM(B27:E27)
A28: NY Auto Verified | B28: =COUNTIF('NY Auto Verified'!$J$2:$J$500,"Primary source") | C28: =COUNTIF('NY Auto Verified'!$J$2:$J$500,"Secondary - unverified") | D28: =COUNTIF('NY Auto Verified'!$J$2:$J$500,"Conflicting") | E28: =COUNTIF('NY Auto Verified'!$J$2:$J$500,"Not researched") | F28: =SUM(B28:E28)
A29: TX Home Verified | B29: =COUNTIF('TX Home Verified'!$J$2:$J$500,"Primary source") | C29: =COUNTIF('TX Home Verified'!$J$2:$J$500,"Secondary - unverified") | D29: =COUNTIF('TX Home Verified'!$J$2:$J$500,"Conflicting") | E29: =COUNTIF('TX Home Verified'!$J$2:$J$500,"Not researched") | F29: =SUM(B29:E29)
A30: FL Home Verified | B30: =COUNTIF('FL Home Verified'!$J$2:$J$500,"Primary source") | C30: =COUNTIF('FL Home Verified'!$J$2:$J$500,"Secondary - unverified") | D30: =COUNTIF('FL Home Verified'!$J$2:$J$500,"Conflicting") | E30: =COUNTIF('FL Home Verified'!$J$2:$J$500,"Not researched") | F30: =SUM(B30:E30)
A31: NY Home Verified | B31: =COUNTIF('NY Home Verified'!$J$2:$J$500,"Primary source") | C31: =COUNTIF('NY Home Verified'!$J$2:$J$500,"Secondary - unverified") | D31: =COUNTIF('NY Home Verified'!$J$2:$J$500,"Conflicting") | E31: =COUNTIF('NY Home Verified'!$J$2:$J$500,"Not researched") | F31: =SUM(B31:E31)
A32: IL Auto Verified | B32: =COUNTIF('IL Auto Verified'!$J$2:$J$500,"Primary source") | C32: =COUNTIF('IL Auto Verified'!$J$2:$J$500,"Secondary - unverified") | D32: =COUNTIF('IL Auto Verified'!$J$2:$J$500,"Conflicting") | E32: =COUNTIF('IL Auto Verified'!$J$2:$J$500,"Not researched") | F32: =SUM(B32:E32)
A33: IL Home Verified | B33: =COUNTIF('IL Home Verified'!$J$2:$J$500,"Primary source") | C33: =COUNTIF('IL Home Verified'!$J$2:$J$500,"Secondary - unverified") | D33: =COUNTIF('IL Home Verified'!$J$2:$J$500,"Conflicting") | E33: =COUNTIF('IL Home Verified'!$J$2:$J$500,"Not researched") | F33: =SUM(B33:E33)
A34: PA Auto Verified | B34: =COUNTIF('PA Auto Verified'!$J$2:$J$500,"Primary source") | C34: =COUNTIF('PA Auto Verified'!$J$2:$J$500,"Secondary - unverified") | D34: =COUNTIF('PA Auto Verified'!$J$2:$J$500,"Conflicting") | E34: =COUNTIF('PA Auto Verified'!$J$2:$J$500,"Not researched") | F34: =SUM(B34:E34)
A35: PA Home Verified | B35: =COUNTIF('PA Home Verified'!$J$2:$J$500,"Primary source") | C35: =COUNTIF('PA Home Verified'!$J$2:$J$500,"Secondary - unverified") | D35: =COUNTIF('PA Home Verified'!$J$2:$J$500,"Conflicting") | E35: =COUNTIF('PA Home Verified'!$J$2:$J$500,"Not researched") | F35: =SUM(B35:E35)
A36: GA Auto Verified | B36: =COUNTIF('GA Auto Verified'!$J$2:$J$500,"Primary source") | C36: =COUNTIF('GA Auto Verified'!$J$2:$J$500,"Secondary - unverified") | D36: =COUNTIF('GA Auto Verified'!$J$2:$J$500,"Conflicting") | E36: =COUNTIF('GA Auto Verified'!$J$2:$J$500,"Not researched") | F36: =SUM(B36:E36)
A37: GA Home Verified | B37: =COUNTIF('GA Home Verified'!$J$2:$J$500,"Primary source") | C37: =COUNTIF('GA Home Verified'!$J$2:$J$500,"Secondary - unverified") | D37: =COUNTIF('GA Home Verified'!$J$2:$J$500,"Conflicting") | E37: =COUNTIF('GA Home Verified'!$J$2:$J$500,"Not researched") | F37: =SUM(B37:E37)
A38: NC Auto Verified | B38: =COUNTIF('NC Auto Verified'!$J$2:$J$500,"Primary source") | C38: =COUNTIF('NC Auto Verified'!$J$2:$J$500,"Secondary - unverified") | D38: =COUNTIF('NC Auto Verified'!$J$2:$J$500,"Conflicting") | E38: =COUNTIF('NC Auto Verified'!$J$2:$J$500,"Not researched") | F38: =SUM(B38:E38)
A39: NC Home Verified | B39: =COUNTIF('NC Home Verified'!$J$2:$J$500,"Primary source") | C39: =COUNTIF('NC Home Verified'!$J$2:$J$500,"Secondary - unverified") | D39: =COUNTIF('NC Home Verified'!$J$2:$J$500,"Conflicting") | E39: =COUNTIF('NC Home Verified'!$J$2:$J$500,"Not researched") | F39: =SUM(B39:E39)
A40: VA Auto Verified | B40: =COUNTIF('VA Auto Verified'!$J$2:$J$500,"Primary source") | C40: =COUNTIF('VA Auto Verified'!$J$2:$J$500,"Secondary - unverified") | D40: =COUNTIF('VA Auto Verified'!$J$2:$J$500,"Conflicting") | E40: =COUNTIF('VA Auto Verified'!$J$2:$J$500,"Not researched") | F40: =SUM(B40:E40)
A41: VA Home Verified | B41: =COUNTIF('VA Home Verified'!$J$2:$J$500,"Primary source") | C41: =COUNTIF('VA Home Verified'!$J$2:$J$500,"Secondary - unverified") | D41: =COUNTIF('VA Home Verified'!$J$2:$J$500,"Conflicting") | E41: =COUNTIF('VA Home Verified'!$J$2:$J$500,"Not researched") | F41: =SUM(B41:E41)
A42: All tabs | B42: =SUM(B17:B41) | C42: =SUM(C17:C41) | D42: =SUM(D17:D41) | E42: =SUM(E17:E41) | F42: =SUM(F17:F41)
A43: TX Home Verified | B43: Texas home facts from TDI, TWIA and secondary sources.
A44: FL Home Verified | B44: Florida home facts: hurricane deductibles, Citizens and flood rules.
A45: TX Auto Verified | B45: Texas auto facts from the TDI guide.
A46: FL Auto Verified | B46: Florida auto facts from FLHSMV and Florida Statutes.
A47: NY Auto Verified | B47: New York auto facts from the DFS consumer guide.
A48: CA Home Verified | B48: California home insurance facts traced to CDI, CEA and FAIR Plan sources and CDI press releases.
A49: CA Auto Verified | B49: California auto facts traced to primary sources (CDI, DMV, statutes and regulations).
A50: State Min Limits | B50: Minimum auto liability limits by state (50 states + DC); most rows still to research.
A51: Rating Factors | B51: Credit, gender and age rules by state for states researched.
A52: Discounts | B52: Discount availability by state and carrier.
A53: Telematics | B53: Usage-based programs by carrier.
A54: Coverage Details | B54: Flood, earthquake, umbrella and other coverage facts.
... A73: VA Home Verified | B73: Virginia home facts from the Virginia Property Insurance Association (VPIA / FAIR Plan).

Sheet CA Auto Verified
A1: Topic | B1: Fact | C1: Value | D1: Legal Citation | E1: Source | F1: Source URL | G1: Date Collected | H1: Geographic Scope | I1: Data Type | J1: Verification Status | K1: Last Updated | L1: Notes
A2: Minimum liability | B2: Bodily injury per person | C2: $30,000 | D2: Ins. Code 11580.1(b) (per DMV) | E2: CA DMV - Auto Insurance Requirements (modified Jul 10, 2025) | F2: https://www.dmv.ca.gov/portal/vehicle-registration/insurance-requirements/ | G2: 46295 | H2: California | I2: Regulator-published | J2: Primary source | K2: 46295 | L2: CDI Form 101 states the same limits.
A3: Minimum liability | B3: Bodily injury per accident | C3: $60,000 | D3: Ins. Code 11580.1(b) (per DMV) | E3: CA DMV - Auto Insurance Requirements (modified Jul 10, 2025) | F3: https://www.dmv.ca.gov/portal/vehicle-registration/insurance-requirements/ | G3: 46295 | H3: California | I3: Regulator-published | J3: Primary source | K3: 46295
A4: Minimum liability | B4: Property damage | C4: $15,000 | D4: Ins. Code 11580.1(b) (per DMV) | E4: CA DMV - Auto Insurance Requirements (modified Jul 10, 2025) | F4: https://www.dmv.ca.gov/portal/vehicle-registration/insurance-requirements/ | G4: 46295 | H4: California | I4: Regulator-published | J4: Primary source | K4: 46295
A5: Minimum liability | B5: Timing of increase | C5: Increased limits begin 2025 under SB 1107 | D5: SB 1107 (2022) | E5: CA Dept of Insurance - Low Cost Auto consumer alert (Jul 23, 2024) | F5: https://www.insurance.ca.gov/0400-news/0102-alerts/2024/California-s-Low-Cost-Auto-Insurance.cfm | G5: 46295 | H5: California | I5: Regulator-published | J5: Primary source | K5: 46295 | L5: CDI alert says liability limits increase beginning 2025.
A6: Minimum liability | B6: Existing policies adjust at renewal | C6: Policies renew at the new limits | D6: Per law-firm summary of CDI position | E6: CarInsurance.com - Minimum liability by state (Apr 2026) | F6: https://www.carinsurance.com/Articles/minimum-liability-car-insurance-requirements-by-state.aspx | G6: 46295 | H6: California | I6: Reference data (secondary source) | J6: Secondary - unverified | K6: 46295 | L6: Verify with CDI.
A7: Minimum liability | B7: Scheduled second increase | C7: On Jan 1, 2035 minimums rise by $20,000 (per person), $40,000 (per accident) and $10,000 (property damage): 50/100/25 | D7: SB 1107 (2022) text | E7: SB 1107 (2021-22) enrolled bill text - Vehicles: insurance (leginfo) | F7: https://leginfo.legislature.ca.gov/faces/billNavClient.xhtml?bill_id=202120220SB1107 | G7: 46295 | H7: California | I7: Statute / regulation text | J7: Primary source | K7: 46295 | L7: Confirmed in the bill text on leginfo. Agency and law-firm sites report the same 50/100/25.
A8: Financial responsibility | B8: Alternatives to insurance (DMV) | C8: Cash deposit $75,000; surety bond $75,000; DMV self-insurance certificate | D8: DMV page (Jul 2025); SB 1107 | E8: CA DMV - Auto Insurance Requirements (modified Jul 10, 2025) | F8: https://www.dmv.ca.gov/portal/vehicle-registration/insurance-requirements/ | G8: 46295 | H8: California | I8: Regulator-published | J8: Primary source | K8: 46295 | L8: Resolved: SB 1107 raised the deposit to $75,000 (and by $50,000 more on Jan 1, 2035). CDI Form 101's $35,000 figure is out of date.
A9: Financial responsibility | B9: Collision/comprehensive | C9: Do not satisfy financial responsibility | D9: DMV page | E9: CA DMV - Auto Insurance Requirements (modified Jul 10, 2025) | F9: https://www.dmv.ca.gov/portal/vehicle-registration/insurance-requirements/ | G9: 46295 | H9: California | I9: Regulator-published | J9: Primary source | K9: 46295 | L9: Liability is the only required coverage.
A10: Financial responsibility | B10: When proof must be shown | C10: On request by law enforcement, at registration renewal, after a collision | D10: DMV page | E10: CA DMV - Auto Insurance Requirements (modified Jul 10, 2025) | F10: https://www.dmv.ca.gov/portal/vehicle-registration/insurance-requirements/ | G10: 46295 | H10: California | I10: Regulator-published | J10: Primary source | K10: 46295 | L10: Registration is suspended if DMV does not receive proof.
A11: Financial responsibility | B11: Insurers report to DMV | C11: Electronic reporting required | D11: Veh. Code 16058 (per DMV) | E11: CA DMV - Auto Insurance Requirements (modified Jul 10, 2025) | F11: https://www.dmv.ca.gov/portal/vehicle-registration/insurance-requirements/ | G11: 46295 | H11: California | I11: Regulator-published | J11: Primary source | K11: 46295
A12: Other coverages | B12: Uninsured/underinsured motorist | C12: Must be offered; can be declined by signed waiver; UMBI limits equal liability limits | D12: CDI Form 101 | E12: CA Dept of Insurance - Introduction to Auto Insurance (Form 101, rev. Feb 5, 2025) | F12: https://www.insurance.ca.gov/01-consumers/105-type/95-guides/01-auto/auto101.cfm | G12: 46295 | H12: California | I12: Regulator-published | J12: Primary source | K12: 46295
A13: Other coverages | B13: UM property damage limit | C13: $3,500 (only if uninsured driver identified) | D13: CDI Form 101 | E13: CA Dept of Insurance - Introduction to Auto Insurance (Form 101, rev. Feb 5, 2025) | F13: https://www.insurance.ca.gov/01-consumers/105-type/95-guides/01-auto/auto101.cfm | G13: 46295 | H13: California | I13: Regulator-published | J13: Primary source | K13: 46295
A14: Other coverages | B14: Medical payments | C14: Optional; minimum limit you can buy is $1,000 per person | D14: CDI Form 101 | E14: CA Dept of Insurance - Introduction to Auto Insurance (Form 101, rev. Feb 5, 2025) | F14: https://www.insurance.ca.gov/01-consumers/105-type/95-guides/01-auto/auto101.cfm | G14: 46295 | H14: California | I14: Regulator-published | J14: Primary source | K14: 46295
A15: Fault and claims | B15: Fault rule | C15: Comparative negligence | D15: CDI Form 101 | E15: CA Dept of Insurance - Introduction to Auto Insurance (Form 101, rev. Feb 5, 2025) | F15: https://www.insurance.ca.gov/01-consumers/105-type/95-guides/01-auto/auto101.cfm | G15: 46295 | H15: California | I15: Regulator-published | J15: Primary source | K15: 46295
A16: Fault and claims | B16: Surcharge after an accident | C16: None if not at fault; can apply at renewal if at least 51% at fault | D16: CDI Form 101 | E16: CA Dept of Insurance - Introduction to Auto Insurance (Form 101, rev. Feb 5, 2025) | F16: https://www.insurance.ca.gov/01-consumers/105-type/95-guides/01-auto/auto101.cfm | G16: 46295 | H16: California | I16: Regulator-published | J16: Primary source | K16: 46295
A17: Fault and claims | B17: Reasons a policy can be cancelled or non-renewed | C17: Fraud/material misrepresentation; non-payment; substantial increase in hazard | D17: CDI Form 101 | E17: CA Dept of Insurance - Introduction to Auto Insurance (Form 101, rev. Feb 5, 2025) | F17: https://www.insurance.ca.gov/01-consumers/105-type/95-guides/01-auto/auto101.cfm | G17: 46295 | H17: California | I17: Regulator-published | J17: Primary source | K17: 46295
A18: Rating factors | B18: Mandatory factors (in order of importance) | C18: 1) driving safety record 2) annual miles 3) years of driving experience | D18: Ins. Code 1861.02(a); 10 CCR 2632.5(c) | E18: 10 CCR section 2632.5 - Rating Factors (text via Cornell LII) | F18: https://www.law.cornell.edu/regulations/california/10-CCR-2632.5 | G18: 46295 | H18: California | I18: Statute / regulation text | J18: Primary source | K18: 46295 | L18: Factors after the third must be on the Commissioner's approved list.
A19: Rating factors | B19: Optional factors currently listed | C19: Vehicle type; performance; type of use; percent use; multi-vehicle household; academic standing; driver training; vehicle characteristics; marital status; persistency; non-smoker; secondary driver characteristics; multi-policy; relative claims frequency; relative claims severity | D19: 10 CCR 2632.5(d) | E19: 10 CCR section 2632.5 - Rating Factors (text via Cornell LII) | F19: https://www.law.cornell.edu/regulations/california/10-CCR-2632.5 | G19: 46295 | H19: California | I19: Statute / regulation text | J19: Primary source | K19: 46295 | L19: Advisory Notice 2005-02 counted 16 optional factors; one was repealed effective Jan 1, 2019 (reported as gender). Confirm.
A20: Rating factors | B20: Location | C20: Only through claims frequency and severity bands, each max 20 categories, based on ZIP code or census tract where vehicle is garaged | D20: 10 CCR 2632.5(d)(14)-(15) | E20: 10 CCR section 2632.5 - Rating Factors (text via Cornell LII) | F20: https://www.law.cornell.edu/regulations/california/10-CCR-2632.5 | G20: 46295 | H20: California | I20: Statute / regulation text | J20: Primary source | K20: 46295
A21: Rating factors | B21: Credit history, gender, age | C21: Not on the mandatory or optional lists | D21: 10 CCR 2632.5 | E21: 10 CCR section 2632.5 - Rating Factors (text via Cornell LII) | F21: https://www.law.cornell.edu/regulations/california/10-CCR-2632.5 | G21: 46295 | H21: California | I21: Statute / regulation text | J21: Primary source | K21: 46295 | L21: Derived from the regulation text: age matters only via years licensed. Confirm with counsel before publishing as a legal statement.
A22: Rating factors | B22: Driving record verification | C22: Insurer must verify the motor vehicle report at application and at least every 36 months; DUI convictions treated as highest surchargeable violation | D22: 10 CCR 2632.5(c)(1) | E22: 10 CCR section 2632.5 - Rating Factors (text via Cornell LII) | F22: https://www.law.cornell.edu/regulations/california/10-CCR-2632.5 | G22: 46295 | H22: California | I22: Statute / regulation text | J22: Primary source | K22: 46295
A23: Mileage and telematics | B23: How mileage is set | C23: Estimated annual miles, with insurer allowed to request supporting information; verified-actual-mileage programs also allowed | D23: 10 CCR 2632.5(c)(2) | E23: 10 CCR section 2632.5 - Rating Factors (text via Cornell LII) | F23: https://www.law.cornell.edu/regulations/california/10-CCR-2632.5 | G23: 46295 | H23: California | I23: Statute / regulation text | J23: Primary source | K23: 46295
A24: Mileage and telematics | B24: Device restrictions | C24: Insurer may use a device only to collect actual miles driven and may not collect or store vehicle location (exceptions for roadside, theft, map, travel services) | D24: 10 CCR 2632.5(c)(2)(F)(i)5 | E24: 10 CCR section 2632.5 - Rating Factors (text via Cornell LII) | F24: https://www.law.cornell.edu/regulations/california/10-CCR-2632.5 | G24: 46295 | H24: California | I24: Statute / regulation text | J24: Primary source | K24: 46295 | L24: This may explain why behavior-based programs like Snapshot and Drivewise are not offered in CA. That link is my inference.
A25: Discounts | B25: Good driver discount | C25: Rate at least 20% lower than a comparable non-good driver | D25: Ins. Code 1861.02; 10 CCR 2632.12; CDI Form 101 | E25: 10 CCR section 2632.12 - Good Driver Discount (text via Cornell LII) | F25: https://www.law.cornell.edu/regulations/california/10-CCR-2632.12 | G25: 46295 | H25: California | I25: Statute / regulation text | J25: Primary source | K25: 46295 | L25: See statute row below for eligibility.
A26: Discounts | B26: Good driver eligibility (statute) | C26: Licensed for the previous three years, and in that period: no more than one violation point (an at-fault property-damage accident counts as one point), no more than one non-confidential dismissal that would have carried more than one point, and not principally at fault in an accident causing injury or death | D26: Ins. Code 1861.025(a)-(b) | E26: CA Insurance Code section 1861.025 - Good Driver Discount eligibility (Justia) | F26: https://law.justia.com/codes/california/code-ins/division-1/part-2/chapter-9/article-10/section-1861-025/ | G26: 46295 | H26: California | I26: Statute / regulation text | J26: Primary source | K26: 46295 | L26: CDI's consumer page mentions only the point limit. Further criteria in later subdivisions were not visible in the text I read; have counsel confirm before publishing eligibility rules.
A27: Discounts | B27: Six-month vs annual policy | C27: Six-month premium must be one-half of the annual premium; no paid-in-full discount | D27: CDI Advisory Notice 2005-02 | E27: CDI Rate Regulation Advisory Notice 2005-02 (May 2, 2005) | F27: https://www.insurance.ca.gov/0250-insurers/0300-insurers/0200-bulletins/bulletin-notices-commiss-opinion/upload/Advisory-Notice-2005-02.pdf | G27: 46295 | H27: California | I27: Regulator-published | J27: Primary source | K27: 46295 | L27: Dated May 2, 2005; confirm not superseded. Matters for your policy-term comparison feature.
A28: Discounts | B28: Mature driver (55+) with DMV-approved course | C28: Every admitted insurer must provide a reduction; insurer sets the percentage | D28: Ins. Code 11628.3; 13 CCR 346.00 | E28: CA Insurance Code section 11628.3 - Mature driver (text via FindLaw) | F28: https://codes.findlaw.com/ca/insurance-code/ins-sect-11628-3/ | G28: 46295 | H28: California | I28: Statute / regulation text | J28: Primary source | K28: 46295 | L28: FindLaw may lag the latest law.
A29: Programs | B29: Low Cost Auto (CLCA) | C29: Limits 10/20/3; income at or below 250% of federal poverty level; vehicle worth $25,000 or less; age 16+ | D29: CDI Form 101 | E29: CA Dept of Insurance - Introduction to Auto Insurance (Form 101, rev. Feb 5, 2025) | F29: https://www.insurance.ca.gov/01-consumers/105-type/95-guides/01-auto/auto101.cfm | G29: 46295 | H29: California | I29: Regulator-published | J29: Primary source | K29: 46295 | L29: CLCA limits unchanged by SB 1107 (CDI alert).
A30: Programs | B30: High-risk drivers (CAARP) | C30: Assigned to an insurer; all licensed insurers must accept; same premiums across companies | D30: CDI Form 101 | E30: CA Dept of Insurance - Introduction to Auto Insurance (Form 101, rev. Feb 5, 2025) | F30: https://www.insurance.ca.gov/01-consumers/105-type/95-guides/01-auto/auto101.cfm | G30: 46295 | H30: California | I30: Regulator-published | J30: Primary source | K30: 46295
A31: Agents and brokers | B31: Licensing and pay | C31: All agents and brokers must be state licensed; agents paid by insurers; brokers may charge a broker fee | D31: CDI Form 101 | E31: CA Dept of Insurance - Introduction to Auto Insurance (Form 101, rev. Feb 5, 2025) | F31: https://www.insurance.ca.gov/01-consumers/105-type/95-guides/01-auto/auto101.cfm | G31: 46295 | H31: California | I31: Regulator-published | J31: Primary source | K31: 46295 | L31: Relevant to your referral and lead-generation model.
A32: Quotes | B32: What CDI calls a quote | C32: An estimate of premium; get quotes in writing and compare | D32: CDI Form 101 | E32: CA Dept of Insurance - Introduction to Auto Insurance (Form 101, rev. Feb 5, 2025) | F32: https://www.insurance.ca.gov/01-consumers/105-type/95-guides/01-auto/auto101.cfm | G32: 46295 | H32: California | I32: Regulator-published | J32: Primary source | K32: 46295 | L32: Supports your 'estimate vs actual quote' labels.

Sheet CA Home Verified
A1: Topic | B1: Fact | C1: Value | D1: Legal Citation | E1: Source | F1: Source URL | G1: Date Collected | H1: Geographic Scope | I1: Data Type | J1: Verification Status | K1: Last Updated | L1: Notes
A2: Requirement | B2: Is homeowners insurance required? | C2: No. Lenders require enough coverage; lenders require flood insurance in federally mapped high-risk flood zones | D2: CDI Homeowners flyer (Dec 2024) | E2: CA Dept of Insurance - Homeowners Insurance flyer (Dec 2024) | F2: https://www.insurance.ca.gov/01-consumers/105-type/95-guides/upload/Homeowners-Insurance-Updated-121924.pdf | G2: 46295 | H2: California | I2: Regulator-published | J2: Primary source | K2: 46295
A3: Coverage | B3: Coverage A - Dwelling | C3: Protects the house and attached structures from covered perils | D3: CDI Form 401 | E3: CA Dept of Insurance - Residential Insurance: Homeowners and Renters (Form 401, rev. Jan 2026) | F3: https://www.insurance.ca.gov/01-consumers/105-type/95-guides/03-res/res-ins-guide.cfm | G3: 46295 | H3: California | I3: Regulator-published | J3: Primary source | K3: 46295
A4: Coverage | B4: Coverage B - Other structures | C4: Normally limited to 10% of Coverage A; more available for extra premium | D4: CDI Form 401 | E4: CA Dept of Insurance - Residential Insurance: Homeowners and Renters (Form 401, rev. Jan 2026) | F4: https://www.insurance.ca.gov/01-consumers/105-type/95-guides/03-res/res-ins-guide.cfm | G4: 46295 | H4: California | I4: Regulator-published | J4: Primary source | K4: 46295
A5: Coverage | B5: Coverage C - Personal property | C5: Contents limit generally about 50% of dwelling (a guideline only); special limits on jewelry, antiques, furs, collectibles, fine art, firearms, silverware, money | D5: CDI Form 401 | E5: CA Dept of Insurance - Residential Insurance: Homeowners and Renters (Form 401, rev. Jan 2026) | F5: https://www.insurance.ca.gov/01-consumers/105-type/95-guides/03-res/res-ins-guide.cfm | G5: 46295 | H5: California | I5: Regulator-published | J5: Primary source | K5: 46295 | L5: Special limits sit inside the overall contents limit, not on top of it; scheduling items separately is the fix.
A6: Coverage | B6: Coverage D - Loss of use | C6: Normally limited to 20% of Coverage A (renters: 20% of C; condo: 40% of C) | D6: CDI Form 401 | E6: CA Dept of Insurance - Residential Insurance: Homeowners and Renters (Form 401, rev. Jan 2026) | F6: https://www.insurance.ca.gov/01-consumers/105-type/95-guides/03-res/res-ins-guide.cfm | G6: 46295 | H6: California | I6: Regulator-published | J6: Primary source | K6: 46295
A7: Coverage | B7: Coverage E and F | C7: E: personal liability. F: medical payments to others (not for household members) | D7: CDI Form 401 | E7: CA Dept of Insurance - Residential Insurance: Homeowners and Renters (Form 401, rev. Jan 2026) | F7: https://www.insurance.ca.gov/01-consumers/105-type/95-guides/03-res/res-ins-guide.cfm | G7: 46295 | H7: California | I7: Regulator-published | J7: Primary source | K7: 46295
A8: Coverage | B8: Perils generally NOT covered | C8: Flood, earthquake, earth movement, termites and pests, seepage/leaks, vacancy of 60+ days, mold, wear and tear, war, neglect, nuclear hazard | D8: CDI Form 401 | E8: CA Dept of Insurance - Residential Insurance: Homeowners and Renters (Form 401, rev. Jan 2026) | F8: https://www.insurance.ca.gov/01-consumers/105-type/95-guides/03-res/res-ins-guide.cfm | G8: 46295 | H8: California | I8: Regulator-published | J8: Primary source | K8: 46295 | L8: Read the actual policy exclusions.
A9: Limits | B9: How to set the dwelling limit | C9: Should equal the cost to rebuild, not purchase price or market value; land is not covered | D9: CDI Form 401 | E9: CA Dept of Insurance - Residential Insurance: Homeowners and Renters (Form 401, rev. Jan 2026) | F9: https://www.insurance.ca.gov/01-consumers/105-type/95-guides/03-res/res-ins-guide.cfm | G9: 46295 | H9: California | I9: Regulator-published | J9: Primary source | K9: 46295
A10: Limits | B10: Replacement cost estimates | C10: If an insurer or broker gives a replacement cost estimate, a copy must be given to the applicant or insured who buys the coverage | D10: CDI Form 401 | E10: CA Dept of Insurance - Residential Insurance: Homeowners and Renters (Form 401, rev. Jan 2026) | F10: https://www.insurance.ca.gov/01-consumers/105-type/95-guides/03-res/res-ins-guide.cfm | G10: 46295 | H10: California | I10: Regulator-published | J10: Primary source | K10: 46295 | L10: Relevant if your site ever shows a rebuild-cost estimate.
A11: Limits | B11: 'Guaranteed replacement cost' label | C11: May be used only if the policy pays to fully rebuild regardless of the limit; other forms pay the limit plus a percentage; SB 1855 renamed 'Extended' to 'Limited Replacement Cost' in disclosures | D11: CDI Form 401 | E11: CA Dept of Insurance - Residential Insurance: Homeowners and Renters (Form 401, rev. Jan 2026) | F11: https://www.insurance.ca.gov/01-consumers/105-type/95-guides/03-res/res-ins-guide.cfm | G11: 46295 | H11: California | I11: Regulator-published | J11: Primary source | K11: 46295
A12: Limits | B12: Building code upgrade (ordinance or law) | C12: Some policies lack it; available by endorsement | D12: CDI Form 401 | E12: CA Dept of Insurance - Residential Insurance: Homeowners and Renters (Form 401, rev. Jan 2026) | F12: https://www.insurance.ca.gov/01-consumers/105-type/95-guides/03-res/res-ins-guide.cfm | G12: 46295 | H12: California | I12: Regulator-published | J12: Primary source | K12: 46295
A13: Limits | B13: Actual cash value (ACV) | C13: Total loss: lesser of policy limit or fair market value. Partial loss: repair cost minus depreciation, or the limit | D13: CDI Form 401 glossary | E13: CA Dept of Insurance - Residential Insurance: Homeowners and Renters (Form 401, rev. Jan 2026) | F13: https://www.insurance.ca.gov/01-consumers/105-type/95-guides/03-res/res-ins-guide.cfm | G13: 46295 | H13: California | I13: Regulator-published | J13: Primary source | K13: 46295
A14: Discounts | B14: Discounts named by CDI | C14: Burglar alarms and fire protection devices such as smoke detectors, alarms and sprinklers; higher deductible can significantly cut premium | D14: CDI Form 401 | E14: CA Dept of Insurance - Residential Insurance: Homeowners and Renters (Form 401, rev. Jan 2026) | F14: https://www.insurance.ca.gov/01-consumers/105-type/95-guides/03-res/res-ins-guide.cfm | G14: 46295 | H14: California | I14: Regulator-published | J14: Primary source | K14: 46295
A15: Discounts | B15: Safer from Wildfires | C15: Every action under the framework qualifies for an insurance discount (structure, surroundings, community) | D15: 10 CCR 2644.9 (CDI page) | E15: CA Dept of Insurance - Safer from Wildfires | F15: https://www.insurance.ca.gov/01-consumers/200-wrr/Safer-from-Wildfires.cfm | G15: 46295 | H15: California | I15: Regulator-published | J15: Primary source | K15: 46295 | L15: Secondary sites often cite this as 'Insurance Code 2644.9'; it is a Title 10 regulation.
A16: Discounts | B16: Disclosure and appeal of wildfire risk score | C16: Insurers must disclose available discounts and the policyholder's risk score, and allow an appeal | D16: 10 CCR 2644.9 (per research paper) | E16: Resources for the Future - Insurance discounts for wildfire mitigation (WP 25-30) | F16: https://media.rff.org/documents/WP_25-30.pdf | G16: 46295 | H16: California | I16: Reference data (secondary source) | J16: Secondary - unverified | K16: 46295 | L16: Confirm in the regulation text.
A17: Rates | B17: Who approves rates | C17: Each insurer calculates its own rates, subject to CDI approval | D17: CDI residential one-pager | E17: CA Dept of Insurance - Residential Insurance: Homeowners and Renters (Form 401, rev. Jan 2026) | F17: https://www.insurance.ca.gov/01-consumers/105-type/95-guides/03-res/res-ins-guide.cfm | G17: 46295 | H17: California | I17: Regulator-published | J17: Primary source | K17: 46295 | L17: Snippet of the one-pager was truncated; confirm wording.
A18: Rights | B18: Cancellation | C18: After 60 days, only for nonpayment, fraud, material misrepresentation, or physical changes that increase hazard; 20 days' notice (10 for nonpayment or fraud) | D18: CDI Form 401 | E18: CA Dept of Insurance - Residential Insurance: Homeowners and Renters (Form 401, rev. Jan 2026) | F18: https://www.insurance.ca.gov/01-consumers/105-type/95-guides/03-res/res-ins-guide.cfm | G18: 46295 | H18: California | I18: Regulator-published | J18: Primary source | K18: 46295
A19: Rights | B19: Nonrenewal | C19: Written notice at least 75 days before expiration with the reason; if late, the existing policy stays in effect 75 days from notice | D19: CDI Form 401 | E19: CA Dept of Insurance - Residential Insurance: Homeowners and Renters (Form 401, rev. Jan 2026) | F19: https://www.insurance.ca.gov/01-consumers/105-type/95-guides/03-res/res-ins-guide.cfm | G19: 46295 | H19: California | I19: Regulator-published | J19: Primary source | K19: 46295
A20: Rights | B20: Premium verification | C20: Insurer has 60 days to verify rating and underwriting of a new policy and notify of errors | D20: CDI Form 401 | E20: CA Dept of Insurance - Residential Insurance: Homeowners and Renters (Form 401, rev. Jan 2026) | F20: https://www.insurance.ca.gov/01-consumers/105-type/95-guides/03-res/res-ins-guide.cfm | G20: 46295 | H20: California | I20: Regulator-published | J20: Primary source | K20: 46295
A21: Rights | B21: Time to rebuild (AB 2199) | C21: At least 12 months (plus 6-month extensions for good cause); 24 months after a declared emergency; may rebuild elsewhere | D21: CDI Form 401 | E21: CA Dept of Insurance - Residential Insurance: Homeowners and Renters (Form 401, rev. Jan 2026) | F21: https://www.insurance.ca.gov/01-consumers/105-type/95-guides/03-res/res-ins-guide.cfm | G21: 46295 | H21: California | I21: Regulator-published | J21: Primary source | K21: 46295
A22: Rights | B22: Total loss protections (AB 2962) | C22: Insurer must consult at renewal; cannot cancel mid-rebuild except for fraud; must renew at least once after a declared-disaster total loss not caused by negligence | D22: CDI Form 401 | E22: CA Dept of Insurance - Residential Insurance: Homeowners and Renters (Form 401, rev. Jan 2026) | F22: https://www.insurance.ca.gov/01-consumers/105-type/95-guides/03-res/res-ins-guide.cfm | G22: 46295 | H22: California | I22: Regulator-published | J22: Primary source | K22: 46295
A23: Rights | B23: Wildfire non-renewal moratorium | C23: Bars non-renewal of residential policies for one year after a declared wildfire (SB 824); SB 547 extends this to commercial policies from Jan 1, 2026 | D23: CDI press release Dec 30, 2025 | E23: CDI press release - New laws take effect January 1, 2026 (Dec 30, 2025) | F23: https://www.insurance.ca.gov/0400-news/0100-press-releases/2025/release079-2025.cfm | G23: 46295 | H23: California | I23: Regulator-published | J23: Primary source | K23: 46295 | L23: Zones covered are set by CDI; check the current list.
A24: Rights | B24: Contents payout without inventory (SB 495) | C24: Wildfire total loss: 60% of contents limit, capped at $350,000, without a detailed list; at least 100 days for proof of loss after a declared emergency | D24: CDI press release Dec 30, 2025 (effective Jan 1, 2026) | E24: CDI press release - New laws take effect January 1, 2026 (Dec 30, 2025) | F24: https://www.insurance.ca.gov/0400-news/0100-press-releases/2025/release079-2025.cfm | G24: 46295 | H24: California | I24: Regulator-published | J24: Primary source | K24: 46295
A25: New laws (2026) | B25: AB 1, AB 226, AB 888, SB 429 | C25: AB 1: regular review of Safer from Wildfires. AB 226: FAIR Plan may use catastrophe bonds and credit lines if authorized. AB 888: grants for fire-safe roofs and Zone Zero. SB 429: grants for a public wildfire model | D25: CDI press release Dec 30, 2025 (effective Jan 1, 2026) | E25: CDI press release - New laws take effect January 1, 2026 (Dec 30, 2025) | F25: https://www.insurance.ca.gov/0400-news/0100-press-releases/2025/release079-2025.cfm | G25: 46295 | H25: California | I25: Regulator-published | J25: Primary source | K25: 46295
A26: Earthquake | B26: Must insurers offer it? | C26: Yes. No residential property policy may be issued or renewed unless the insured is offered earthquake coverage; it may be written by the insurer, another insurer, or the CEA | D26: Ins. Code 10081; CDI Form 401 | E26: CA Dept of Insurance - Earthquake Insurance | F26: https://www.insurance.ca.gov/01-consumers/105-type/95-guides/03-res/eq-ins.cfm | G26: 46295 | H26: California | I26: Regulator-published | J26: Primary source | K26: 46295
A27: Earthquake | B27: Re-offer schedule | C27: If declined, the insurer must re-offer earthquake coverage every other year at continuation, renewal or reinstatement; the offer may be made before, at, or within 60 days after issuance or renewal | D27: Ins. Code 10083(a)-(b) | E27: CA Insurance Code section 10083 - Earthquake offer timing (Justia) | F27: https://law.justia.com/codes/california/code-ins/division-2/part-1/chapter-8-5/section-10083/ | G27: 46295 | H27: California | I27: Statute / regulation text | J27: Primary source | K27: 46295 | L27: Confirms the every-other-year rule that earlier came only from agency sites.
A28: Earthquake | B28: Fire after earthquake | C28: Homeowners and renters policies must cover fire damage caused by or following an earthquake | D28: CDI earthquake page | E28: CA Dept of Insurance - Earthquake Insurance | F28: https://www.insurance.ca.gov/01-consumers/105-type/95-guides/03-res/eq-ins.cfm | G28: 46295 | H28: California | I28: Regulator-published | J28: Primary source | K28: 46295
A29: Earthquake | B29: What earthquake insurance does not cover | C29: Vehicles; flood, sewer/drain backup, tsunami | D29: CDI earthquake page | E29: CA Dept of Insurance - Earthquake Insurance | F29: https://www.insurance.ca.gov/01-consumers/105-type/95-guides/03-res/eq-ins.cfm | G29: 46295 | H29: California | I29: Regulator-published | J29: Primary source | K29: 46295
A30: Earthquake | B30: Claim reporting | C30: Insurer can deny claims not reported within one year | D30: CDI earthquake brochure | E30: CA Dept of Insurance - Earthquake Insurance | F30: https://www.insurance.ca.gov/01-consumers/105-type/95-guides/03-res/eq-ins.cfm | G30: 46295 | H30: California | I30: Regulator-published | J30: Primary source | K30: 46295 | L30: From a truncated brochure snippet; confirm.
A31: Earthquake | B31: CEA deductible options | C31: 5%, 10%, 15%, 20%, 25% of dwelling coverage; homes over $1M dwelling limit or pre-1980 raised-foundation homes without verified retrofit only get 15%-25% | D31: CEA homeowners page | E31: California Earthquake Authority - Homeowners policies | F31: https://www.earthquakeauthority.com/california-earthquake-insurance-policies/homeowners | G31: 46295 | H31: California | I31: Regulator-published | J31: Primary source | K31: 46295 | L31: Premium and take-up figures remain secondary; see Coverage Details.
A32: Earthquake | B32: CEA retrofit discount and loss of use | C32: Discount up to 25% for retrofit; loss of use never has a deductible | D32: CEA homeowners page | E32: California Earthquake Authority - Homeowners policies | F32: https://www.earthquakeauthority.com/california-earthquake-insurance-policies/homeowners | G32: 46295 | H32: California | I32: Regulator-published | J32: Primary source | K32: 46295
A33: Flood | B33: Is flood covered? | C33: Generally excluded from homeowners and renters policies; NFIP (FEMA) offers it; CDI does not regulate the NFIP | D33: CDI Form 401; CDI flood page | E33: CA Dept of Insurance - Flood Insurance Resources | F33: https://www.insurance.ca.gov/01-consumers/140-catastrophes/FloodFacts.cfm | G33: 46295 | H33: California | I33: Regulator-published | J33: Primary source | K33: 46295
A34: Flood | B34: NFIP maximums, single-family | C34: $250,000 structure; $100,000 contents; renters up to $100,000 contents | D34: CDI Form 401 | E34: CA Dept of Insurance - Residential Insurance: Homeowners and Renters (Form 401, rev. Jan 2026) | F34: https://www.insurance.ca.gov/01-consumers/105-type/95-guides/03-res/res-ins-guide.cfm | G34: 46295 | H34: California | I34: Regulator-published | J34: Primary source | K34: 46295 | L34: Federal program authorization status must be checked live; see Coverage Details.
A35: Flood | B35: FAIR Plan and storms | C35: FAIR Plan does not cover storm-related damage unless the owner buys a supplemental 'difference in conditions' (DIC) policy from another insurer | D35: CDI flood page | E35: CA Dept of Insurance - Flood Insurance Resources | F35: https://www.insurance.ca.gov/01-consumers/140-catastrophes/FloodFacts.cfm | G35: 46295 | H35: California | I35: Regulator-published | J35: Primary source | K35: 46295
A36: FAIR Plan | B36: What it is | C36: Association of all licensed property insurers; insurer of last resort | D36: CDI Form 401; FAIR Plan site | E36: CA Dept of Insurance - Residential Insurance: Homeowners and Renters (Form 401, rev. Jan 2026) | F36: https://www.insurance.ca.gov/01-consumers/105-type/95-guides/03-res/res-ins-guide.cfm | G36: 46295 | H36: California | I36: Regulator-published | J36: Primary source | K36: 46295
A37: FAIR Plan | B37: What it covers | C37: Standard fire policy for structure and contents; basic property policy with limits; no liability or other perils such as burglary | D37: CDI Form 401 | E37: CA Dept of Insurance - Residential Insurance: Homeowners and Renters (Form 401, rev. Jan 2026) | F37: https://www.insurance.ca.gov/01-consumers/105-type/95-guides/03-res/res-ins-guide.cfm | G37: 46295 | H37: California | I37: Regulator-published | J37: Primary source | K37: 46295 | L37: CDI suggests a DIC or supplemental policy from a private insurer.
A38: FAIR Plan | B38: Broker fees | C38: Broker may not charge a fee for a FAIR Plan submission | D38: CDI Form 401 | E38: CA Dept of Insurance - Residential Insurance: Homeowners and Renters (Form 401, rev. Jan 2026) | F38: https://www.insurance.ca.gov/01-consumers/105-type/95-guides/03-res/res-ins-guide.cfm | G38: 46295 | H38: California | I38: Regulator-published | J38: Primary source | K38: 46295
A39: FAIR Plan | B39: Dwelling limit | C39: $3 million per property | D39: CDI press release 2019 (effective Apr 1, 2020); Assembly Insurance Committee | E39: CDI press release 089-19 - FAIR Plan coverage options | F39: https://www.insurance.ca.gov/0400-news/0100-press-releases/2019/release089-19.cfm | G39: 46295 | H39: California | I39: Regulator-published | J39: Primary source | K39: 46295 | L39: Confirm current limit on the FAIR Plan site.
A40: FAIR Plan | B40: 2026 rate change | C40: CDI approved a 29.1% average dwelling increase (FAIR Plan asked for 35.8%), effective Oct 15, 2026 per news reports | D40: News reports, not the CDI decision | E40: KQED - FAIR Plan announces 29.1% rate hike (Aug 2026) | F40: https://www.kqed.org/news/12094860/california-fair-plan-announces-29-1-rate-hike-for-homeowners-this-fall | G40: 46295 | H40: California | I40: Reference data (secondary source) | J40: Secondary - unverified | K40: 46295 | L40: Replaces the earlier 'sought 35.8%' note. Verify in the CDI order.
A41: FAIR Plan | B41: Size | C41: Exposure $768 billion in June 2026 (KQED); policies 668,600 at end-2025 (InsuranceNewsNet) | D41: News reports | E41: InsuranceNewsNet - FAIR Plan rates going up 29.1% (May 2026) | F41: https://insurancenewsnet.com/oarticle/california-fair-plan-rates-going-up-29-1-in-late-2026 | G41: 46295 | H41: California | I41: Reference data (secondary source) | J41: Secondary - unverified | K41: 46295 | L41: Earlier note: about 697,000 policies in June (CalMatters). Different dates, not a true conflict; a third source's '550,000+' looks stale.
A42: Availability | B42: Sustainable Insurance Strategy | C42: Insurers that use catastrophe models or reinsurance costs in rates must commit to write at least 85% of their statewide market share in wildfire-distressed areas; larger insurers within two years of a rate filing being adopted | D42: CDI SIS page; CDI press release 023-2024 | E42: CA Dept of Insurance - Sustainable Insurance Strategy updates | F42: https://www.insurance.ca.gov/01-consumers/180-climate-change/SustainableInsuranceStrategy.cfm | G42: 46295 | H42: California | I42: Regulator-published | J42: Primary source | K42: 46295 | L42: CDI monitors this through rate filings. Actual new policies written are not published by CDI in what I found.
A43: Availability | B43: Home Insurance Finder tool | C43: CDI tool to identify insurers writing in high-risk regions | D43: CDI Form 401 | E43: CA Dept of Insurance - Residential Insurance: Homeowners and Renters (Form 401, rev. Jan 2026) | F43: https://www.insurance.ca.gov/01-consumers/105-type/95-guides/03-res/res-ins-guide.cfm | G43: 46295 | H43: California | I43: Regulator-published | J43: Primary source | K43: 46295 | L43: Possible data source to link to from your site; check terms.
A44: Availability | B44: Surplus lines | C44: Insurers in this market are not backed by the California Insurance Guarantee Association | D44: CDI Form 401 | E44: CA Dept of Insurance - Residential Insurance: Homeowners and Renters (Form 401, rev. Jan 2026) | F44: https://www.insurance.ca.gov/01-consumers/105-type/95-guides/03-res/res-ins-guide.cfm | G44: 46295 | H44: California | I44: Regulator-published | J44: Primary source | K44: 46295
A45: Brokers | B45: Broker fee rules | C45: Advance consent after disclosure, signed Broker Fee Agreement, broker not appointed by the insurer, broker bond on file, fee disclosed at initial quote | D45: CDI Form 401 | E45: CA Dept of Insurance - Residential Insurance: Homeowners and Renters (Form 401, rev. Jan 2026) | F45: https://www.insurance.ca.gov/01-consumers/105-type/95-guides/03-res/res-ins-guide.cfm | G45: 46295 | H45: California | I45: Regulator-published | J45: Primary source | K45: 46295 | L45: Fees are not set by law and may be negotiable.

Sheet TX Auto Verified
A1: Topic | B1: Fact | C1: Value | D1: Legal Citation | E1: Source | F1: Source URL | G1: Date Collected | H1: Geographic Scope | I1: Data Type | J1: Verification Status | K1: Last Updated | L1: Notes
A2: Minimum liability | B2: Bodily injury and property damage | C2: 30/60/25: $30,000 per person, $60,000 per accident, $25,000 property damage | D2: TDI guide (Transportation Code 601.072 per secondary sources) | E2: Texas Dept of Insurance - Auto insurance guide (CB020) | F2: https://www.tdi.texas.gov/pubs/consumer/cb020.html | G2: 46295 | H2: Texas | I2: Regulator-published | J2: Primary source | K2: 46295 | L2: TDI: collision and comprehensive are required only by lenders.
A3: Other coverages | B3: Personal injury protection (PIP) | C3: Included on auto policies; the insured must reject it in writing | D3: TDI guide | E3: Texas Dept of Insurance - Auto insurance guide (CB020) | F3: https://www.tdi.texas.gov/pubs/consumer/cb020.html | G3: 46295 | H3: Texas | I3: Regulator-published | J3: Primary source | K3: 46295 | L3: PIP dollar amount not stated by TDI.
A4: Other coverages | B4: PIP amount | C4: Insurers must offer $2,500 | D4: Law-firm blog | E4: Ashmore Law Firm - Car insurance: do you have enough? | F4: https://www.ashmorelaw.com/blog/car-insurance-do-you-have-enough-.cfm | G4: 46295 | H4: Texas | I4: Reference data (secondary source) | J4: Secondary - unverified | K4: 46295 | L4: Confirm in Insurance Code chapter 1952.
A5: Other coverages | B5: Uninsured/underinsured motorist | C5: Insurers must offer it; rejection must be in writing | D5: TDI guide | E5: Texas Dept of Insurance - Auto insurance guide (CB020) | F5: https://www.tdi.texas.gov/pubs/consumer/cb020.html | G5: 46295 | H5: Texas | I5: Regulator-published | J5: Primary source | K5: 46295
A6: Other coverages | B6: Medical payments | C6: Optional; pays medical bills for you and passengers | D6: TDI guide | E6: Texas Dept of Insurance - Auto insurance guide (CB020) | F6: https://www.tdi.texas.gov/pubs/consumer/cb020.html | G6: 46295 | H6: Texas | I6: Regulator-published | J6: Primary source | K6: 46295
A7: Rates | B7: Rate approval | C7: No prior approval; TDI can order refunds if rates are too high; rates must be fair, reasonable and adequate | D7: TDI guide | E7: Texas Dept of Insurance - Auto insurance guide (CB020) | F7: https://www.tdi.texas.gov/pubs/consumer/cb020.html | G7: 46295 | H7: Texas | I7: Regulator-published | J7: Primary source | K7: 46295
A8: Rating | B8: Prohibited factors | C8: Race, color, religion, national origin may not be used to deny or charge more | D8: TDI guide | E8: Texas Dept of Insurance - Auto insurance guide (CB020) | F8: https://www.tdi.texas.gov/pubs/consumer/cb020.html | G8: 46295 | H8: Texas | I8: Regulator-published | J8: Primary source | K8: 46295
A9: Rating | B9: Age, gender, marital status, location, disability | C9: Allowed only if the company can show a greater risk of loss | D9: TDI guide | E9: Texas Dept of Insurance - Auto insurance guide (CB020) | F9: https://www.tdi.texas.gov/pubs/consumer/cb020.html | G9: 46295 | H9: Texas | I9: Regulator-published | J9: Primary source | K9: 46295
A10: Rating | B10: Credit score | C10: May be used, but not as the only reason to turn you down or charge more; HelpInsure.com shows which companies use it | D10: TDI guide | E10: Texas Dept of Insurance - Auto insurance guide (CB020) | F10: https://www.tdi.texas.gov/pubs/consumer/cb020.html | G10: 46295 | H10: Texas | I10: Regulator-published | J10: Primary source | K10: 46295
A11: Rating | B11: Other factors TDI names | C11: Driving record and claims history (CLUE), where the car is kept, vehicle type, how the car is used, credit score | D11: TDI guide | E11: Texas Dept of Insurance - Auto insurance guide (CB020) | F11: https://www.tdi.texas.gov/pubs/consumer/cb020.html | G11: 46295 | H11: Texas | I11: Regulator-published | J11: Primary source | K11: 46295
A12: Discounts | B12: Discounts | C12: Each company decides what to offer and the amount | D12: TDI guide | E12: Texas Dept of Insurance - Auto insurance guide (CB020) | F12: https://www.tdi.texas.gov/pubs/consumer/cb020.html | G12: 46295 | H12: Texas | I12: Regulator-published | J12: Primary source | K12: 46295 | L12: Examples TDI lists: airbags/ABS/antitheft, defensive driving or driver education, multi-car, multi-policy, no claims.
A13: Policy changes | B13: Cancellation | C13: 10 days' notice; any reason in first 60 days; afterwards only nonpayment, fraudulent claim, or suspended license/registration; unearned premium refunded within 15 days | D13: TDI guide | E13: Texas Dept of Insurance - Auto insurance guide (CB020) | F13: https://www.tdi.texas.gov/pubs/consumer/cb020.html | G13: 46295 | H13: Texas | I13: Regulator-published | J13: Primary source | K13: 46295
A14: Policy changes | B14: Nonrenewal | C14: Written reason; 60 days' notice if bought or renewed in 2024 (30 days for 2023 or earlier); only after 12 months in effect; no nonrenewal for age or certain claims (weather, hitting an animal, not-at-fault, flying objects) | D14: TDI guide | E14: Texas Dept of Insurance - Auto insurance guide (CB020) | F14: https://www.tdi.texas.gov/pubs/consumer/cb020.html | G14: 46295 | H14: Texas | I14: Regulator-published | J14: Conflicting | K14: 46295 | L14: Wording is date-specific; confirm the current notice period with TDI.
A15: Programs | B15: Texas Automobile Insurance Plan (TAIPA) | C15: Available after two insurers decline; liability, PIP and UM/UIM only; no collision, comprehensive or higher limits; cheaper policy must be offered after 3 clean years | D15: TDI guide | E15: Texas Dept of Insurance - Auto insurance guide (CB020) | F15: https://www.tdi.texas.gov/pubs/consumer/cb020.html | G15: 46295 | H15: Texas | I15: Regulator-published | J15: Primary source | K15: 46295
A16: Claims | B16: Deadlines | C16: Acknowledge within 15 days; accept or reject within 15 business days of receiving information (45 days if more time needed); pay within 5 business days of agreeing | D16: TDI guide | E16: Texas Dept of Insurance - Auto insurance guide (CB020) | F16: https://www.tdi.texas.gov/pubs/consumer/cb020.html | G16: 46295 | H16: Texas | I16: Regulator-published | J16: Primary source | K16: 46295 | L16: Prompt-pay rules do not apply when another driver's insurer pays.
A17: Claims | B17: Settlement basis | C17: Actual cash value; parts of like kind and quality; insurer cannot require preferred shops | D17: TDI guide | E17: Texas Dept of Insurance - Auto insurance guide (CB020) | F17: https://www.tdi.texas.gov/pubs/consumer/cb020.html | G17: 46295 | H17: Texas | I17: Regulator-published | J17: Primary source | K17: 46295
A18: Claims | B18: Disputes | C18: Appraisal, TDI complaint (in writing), or court (Justice Court for claims under $10,000) | D18: TDI guide | E18: Texas Dept of Insurance - Auto insurance guide (CB020) | F18: https://www.tdi.texas.gov/pubs/consumer/cb020.html | G18: 46295 | H18: Texas | I18: Regulator-published | J18: Primary source | K18: 46295
A19: Consumer rights | B19: Auto Consumer Bill of Rights | C19: Insurer must give a copy when you get or renew a policy | D19: TDI guide | E19: Texas Dept of Insurance - Auto insurance guide (CB020) | F19: https://www.tdi.texas.gov/pubs/consumer/cb020.html | G19: 46295 | H19: Texas | I19: Regulator-published | J19: Primary source | K19: 46295

Sheet FL Auto Verified
A1: Topic | B1: Fact | C1: Value | D1: Legal Citation | E1: Source | F1: Source URL | G1: Date Collected | H1: Geographic Scope | I1: Data Type | J1: Verification Status | K1: Last Updated | L1: Notes
A2: Requirement | B2: Coverage required to register | C2: PIP $10,000 and property damage liability $10,000 for vehicles with at least four wheels | D2: FLHSMV; s. 627.736 and 324.022 per secondary sources | E2: Florida DHSMV - Florida Insurance Requirements | F2: https://www.flhsmv.gov/insurance/ | G2: 46295 | H2: Florida | I2: Regulator-published | J2: Primary source | K2: 46295
A3: Requirement | B3: PIP benefit | C3: Pays 80% of necessary and reasonable medical expenses up to $10,000, regardless of fault | D3: FLHSMV | E3: Florida DHSMV - Florida Insurance Requirements | F3: https://www.flhsmv.gov/insurance/ | G3: 46295 | H3: Florida | I3: Regulator-published | J3: Primary source | K3: 46295
A4: Requirement | B4: Bodily injury liability | C4: Not required for most private passenger vehicles; taxis must carry $125,000/$250,000/$50,000 | D4: FLHSMV | E4: Florida DHSMV - Florida Insurance Requirements | F4: https://www.flhsmv.gov/insurance/ | G4: 46295 | H4: Florida | I4: Regulator-published | J4: Primary source | K4: 46295
A5: Requirement | B5: Continuous coverage | C5: Required even if the vehicle is not driven; surrender the plate before cancelling insurance | D5: FLHSMV | E5: Florida DHSMV - Florida Insurance Requirements | F5: https://www.flhsmv.gov/insurance/ | G5: 46295 | H5: Florida | I5: Regulator-published | J5: Primary source | K5: 46295
A6: Penalties | B6: Lapse consequences | C6: Driving privilege and plate can be suspended up to 3 years; reinstatement fee up to $500; no hardship license | D6: FLHSMV | E6: Florida DHSMV - Florida Insurance Requirements | F6: https://www.flhsmv.gov/insurance/ | G6: 46295 | H6: Florida | I6: Regulator-published | J6: Primary source | K6: 46295
A7: Financial responsibility | B7: After a crash | C7: Proof of ability to pay damages: $10,000 for one person, $20,000 for two or more (bodily injury), plus property damage | D7: Ch. 324 (2022 text) | E7: Florida Statutes Chapter 324 - Financial Responsibility (2022 text) | F7: https://www.flsenate.gov/Laws/Statutes/2022/Chapter324/All | G7: 46295 | H7: Florida | I7: Statute / regulation text | J7: Primary source | K7: 46295 | L7: Confirm current text; SR-22 is the filing that certifies BIL and PDL after a suspension (FLHSMV).
A8: Financial responsibility | B8: DUI convictions | C8: BI liability of $100,000/$300,000 and $50,000 PD required | D8: s. 324.023 (per law-firm sources) | E8: Viles & Beckman - Did Florida repeal no-fault? (Jul 2026) | F8: https://www.vilesandbeckman.com/blog/did-florida-repeal-no-fault-insurance-the-pip-myths-and-the-facts-for-2026/ | G8: 46295 | H8: Florida | I8: Reference data (secondary source) | J8: Secondary - unverified | K8: 46295 | L8: Not confirmed from statute text.
A9: No-fault | B9: Serious-injury threshold, 14-day rule, 60% wage loss, $5,000 death benefit | C9: Reported by law firms; PIP requires treatment within 14 days; lawsuits for pain and suffering require a defined serious injury | D9: s. 627.736, 627.737 (per law-firm sources) | E9: Viles & Beckman - Did Florida repeal no-fault? (Jul 2026) | F9: https://www.vilesandbeckman.com/blog/did-florida-repeal-no-fault-insurance-the-pip-myths-and-the-facts-for-2026/ | G9: 46295 | H9: Florida | I9: Reference data (secondary source) | J9: Secondary - unverified | K9: 46295 | L9: Read the statute before publishing.
A10: Legislation | B10: PIP repeal | C10: SB 522 and HB 769 died in committee on Mar 13, 2026; PIP remains required | D10: Florida Legislature (per law-firm sources) | E10: Viles & Beckman - Did Florida repeal no-fault? (Jul 2026) | F10: https://www.vilesandbeckman.com/blog/did-florida-repeal-no-fault-insurance-the-pip-myths-and-the-facts-for-2026/ | G10: 46295 | H10: Florida | I10: Reference data (secondary source) | J10: Secondary - unverified | K10: 46295 | L10: Next session convenes Mar 2, 2027; verify at flsenate.gov.
A11: Policy changes | B11: Cancellation | C11: At least 45 days' notice (10 days for nonpayment); notice must explain appeal right to the Office of Insurance Regulation (appeal at least 20 days before effective date) | D11: s. 627.728 | E11: Florida Statutes 627.728 - Cancellations; nonrenewals (2025, via Justia) | F11: https://law.justia.com/codes/florida/title-xxxvii/chapter-627/part-xi/section-627-728/ | G11: 46295 | H11: Florida | I11: Statute / regulation text | J11: Primary source | K11: 46295 | L11: Nonrenewal rules for private passenger auto not captured; s. 626.9201 sits in the surplus lines part of the code.
A12: Rating | B12: Credit | C12: Statute regulates and limits use of credit reports and scores in personal lines motor vehicle and residential insurance; insurer must disclose the request and use DFS-prescribed language; certain inquiries and medical collections may not be used; appeal rights for events such as divorce, spouse's death, temporary job loss | D12: s. 626.9741 | E12: Florida Statutes 626.9741 - Credit reports and scores by insurers | F12: https://www.flsenate.gov/Laws/Statutes/2025/0626.9741 | G12: 46295 | H12: Florida | I12: Statute / regulation text | J12: Primary source | K12: 46295 | L12: Seen in snippets and older-year text; fetch was rate-limited. Confirm full text.
A13: Discounts | B13: Statutory discounts | C13: Sections 627.06501 (driver improvement course, discount up to 10% presumed appropriate), 627.0652 (safety course, 3-year reduction), 627.0653 (specified equipment) | D13: Fla. Stat. 627.06501, 627.0652, 627.0653 | E13: Florida Statutes Chapter 627 (2025) - table of contents | F13: https://www.flsenate.gov/Laws/Statutes/2025/Chapter627/All | G13: 46295 | H13: Florida | I13: Statute / regulation text | J13: Secondary - unverified | K13: 46295 | L13: Section titles confirmed in the 2025 table of contents; course text is from 2003 and 2012 versions.
A14: Rates | B14: Rate filing rules | C14: Section 627.0651 governs making and use of rates for motor vehicle insurance | D14: s. 627.0651 | E14: Florida Statutes Chapter 627 (2025) - table of contents | F14: https://www.flsenate.gov/Laws/Statutes/2025/Chapter627/All | G14: 46295 | H14: Florida | I14: Statute / regulation text | J14: Not researched | K14: 46295 | L14: Only the title was seen; not researched.

Sheet NY Auto Verified
A1: Topic | B1: Fact | C1: Value | D1: Legal Citation | E1: Source | F1: Source URL | G1: Date Collected | H1: Geographic Scope | I1: Data Type | J1: Verification Status | K1: Last Updated | L1: Notes
A2: Minimum liability | B2: Bodily injury | C2: $25,000 per person (non-death) or $50,000 (death); $50,000 for two or more (non-death) or $100,000 (death) | D2: NY Vehicle and Traffic Law (per DFS) | E2: NY Dept of Financial Services - Auto Insurance Information for Consumers | F2: https://www.dfs.ny.gov/consumers/auto_insurance/Auto_resource_center | G2: 46295 | H2: New York | I2: Regulator-published | J2: Primary source | K2: 46295
A3: Minimum liability | B3: Property damage | C3: $10,000 per accident (25/50/10) | D3: DFS | E3: NY Dept of Financial Services - Auto Insurance Information for Consumers | F3: https://www.dfs.ny.gov/consumers/auto_insurance/Auto_resource_center | G3: 46295 | H3: New York | I3: Regulator-published | J3: Primary source | K3: 46295
A4: No-fault | B4: Basic PIP | C4: $50,000 per person: medical, 80% of lost earnings up to $2,000 a month for up to 3 years, $25 a day for up to a year for other expenses, $2,000 death benefit | D4: DFS | E4: NY Dept of Financial Services - Auto Insurance Information for Consumers | F4: https://www.dfs.ny.gov/consumers/auto_insurance/Auto_resource_center | G4: 46295 | H4: New York | I4: Regulator-published | J4: Primary source | K4: 46295
A5: No-fault | B5: Lawsuits | C5: Non-economic damages only for a 'serious injury' as defined in the Insurance Law | D5: DFS | E5: NY Dept of Financial Services - Auto Insurance Information for Consumers | F5: https://www.dfs.ny.gov/consumers/auto_insurance/Auto_resource_center | G5: 46295 | H5: New York | I5: Regulator-published | J5: Primary source | K5: 46295
A6: No-fault | B6: Who is ineligible | C6: Impaired or intoxicated driver, intentional self-injury, ATV/motorcycle riders, felony, known stolen vehicle, owner of an uninsured vehicle | D6: DFS | E6: NY Dept of Financial Services - Auto Insurance Information for Consumers | F6: https://www.dfs.ny.gov/consumers/auto_insurance/Auto_resource_center | G6: 46295 | H6: New York | I6: Regulator-published | J6: Primary source | K6: 46295
A7: No-fault | B7: Claim timing | C7: Written notice within 30 days; application sent within 5 business days; payment within 30 days; 2% monthly interest if late | D7: DFS | E7: NY Dept of Financial Services - Auto Insurance Information for Consumers | F7: https://www.dfs.ny.gov/consumers/auto_insurance/Auto_resource_center | G7: 46295 | H7: New York | I7: Regulator-published | J7: Primary source | K7: 46295
A8: Uninsured motorists | B8: Required UM | C8: Same minimum bodily injury limits; applies to NY accidents; out-of-state by endorsement | D8: DFS | E8: NY Dept of Financial Services - Auto Insurance Information for Consumers | F8: https://www.dfs.ny.gov/consumers/auto_insurance/Auto_resource_center | G8: 46295 | H8: New York | I8: Regulator-published | J8: Primary source | K8: 46295
A9: Uninsured motorists | B9: SUM | C9: Included at bodily injury limits unless declined by signed waiver; insurer notifies annually; up to BI limits; insurer must offer $250,000/$500,000 if BI is that high | D9: DFS FAQ | E9: NY DFS FAQ - How much auto insurance must I carry? | F9: https://www.dfs.ny.gov/faqs/consumer-auto/how-much-auto-insurance-must-i-carry | G9: 46295 | H9: New York | I9: Regulator-published | J9: Primary source | K9: 46295
A10: Optional | B10: Additional PIP, OBEL, spousal liability | C10: Additional PIP to $100,000+; OBEL adds $25,000; supplemental spousal liability included unless declined | D10: DFS | E10: NY Dept of Financial Services - Auto Insurance Information for Consumers | F10: https://www.dfs.ny.gov/consumers/auto_insurance/Auto_resource_center | G10: 46295 | H10: New York | I10: Regulator-published | J10: Primary source | K10: 46295
A11: Enforcement | B11: DMV tracking | C11: Insurers report starts, renewals and cancellations; lapses can suspend registration and license | D11: DFS (IIES) | E11: NY Dept of Financial Services - Auto Insurance Information for Consumers | F11: https://www.dfs.ny.gov/consumers/auto_insurance/Auto_resource_center | G11: 46295 | H11: New York | I11: Regulator-published | J11: Primary source | K11: 46295
A12: Rating | B12: Classifications | C12: Age, sex, marital status, territory, annual mileage, vehicle use and driving experience; inexperienced-operator surcharge if licensed under 3 years | D12: DFS | E12: NY Dept of Financial Services - Auto Insurance Information for Consumers | F12: https://www.dfs.ny.gov/consumers/auto_insurance/Auto_resource_center | G12: 46295 | H12: New York | I12: Regulator-published | J12: Primary source | K12: 46295
A13: Rating | B13: Discrimination limits | C13: Insurance Law forbids refusing or terminating a policy because of race, creed, color, national origin, disability, sex, marital status or advanced age; cannot reject solely for geography; 39-month no-vehicle rule | D13: DFS | E13: NY Dept of Financial Services - Auto Insurance Information for Consumers | F13: https://www.dfs.ny.gov/consumers/auto_insurance/Auto_resource_center | G13: 46295 | H13: New York | I13: Regulator-published | J13: Primary source | K13: 46295 | L13: Reconcile with the classification list: rating classes are allowed, refusal or termination on these grounds is not.
A14: Rating | B14: Credit | C14: May be used but not as sole basis for rejection; insurer must disclose use and notify of higher premium; review at least every 3 years; may not terminate or raise renewal premium based on credit | D14: DFS | E14: NY Dept of Financial Services - Auto Insurance Information for Consumers | F14: https://www.dfs.ny.gov/consumers/auto_insurance/Auto_resource_center | G14: 46295 | H14: New York | I14: Regulator-published | J14: Primary source | K14: 46295
A15: Rating | B15: Surcharges | C15: First at-fault accident can add up to 40% under many plans; typical 3-year period; specified exceptions; total capped at 3 times base premium; applies only to liability, no-fault and collision | D15: DFS | E15: NY Dept of Financial Services - Auto Insurance Information for Consumers | F15: https://www.dfs.ny.gov/consumers/auto_insurance/Auto_resource_center | G15: 46295 | H15: New York | I15: Regulator-published | J15: Primary source | K15: 46295
A16: Discounts | B16: Accident prevention course | C16: Insurers must apply a discount to liability, collision and no-fault for 3 years; up to 4 points removed from license record | D16: DFS | E16: NY Dept of Financial Services - Auto Insurance Information for Consumers | F16: https://www.dfs.ny.gov/consumers/auto_insurance/Auto_resource_center | G16: 46295 | H16: New York | I16: Regulator-published | J16: Primary source | K16: 46295
A17: Discounts | B17: Equipment and anti-theft | C17: Discounts for ABS, daytime running lamps, air bags or automatic belts, anti-theft devices, electronic tracking and window etching | D17: DFS | E17: NY Dept of Financial Services - Auto Insurance Information for Consumers | F17: https://www.dfs.ny.gov/consumers/auto_insurance/Auto_resource_center | G17: 46295 | H17: New York | I17: Regulator-published | J17: Primary source | K17: 46295 | L17: Amount of required discounts must appear on the declarations page.
A18: Discounts | B18: Telematics | C18: Optional; may be based on miles, time of day, acceleration, braking and GPS location | D18: DFS | E18: NY Dept of Financial Services - Auto Insurance Information for Consumers | F18: https://www.dfs.ny.gov/consumers/auto_insurance/Auto_resource_center | G18: 46295 | H18: New York | I18: Regulator-published | J18: Primary source | K18: 46295
A19: Policy changes | B19: Cancellation | C19: First 60 days for any lawful reason; afterwards only license suspension/revocation, nonpayment or fraud; 20 days' notice (15 for nonpayment) stating reason | D19: DFS | E19: NY Dept of Financial Services - Auto Insurance Information for Consumers | F19: https://www.dfs.ny.gov/consumers/auto_insurance/Auto_resource_center | G19: 46295 | H19: New York | I19: Regulator-published | J19: Primary source | K19: 46295
A20: Policy changes | B20: Nonrenewal | C20: 45 to 60 days' advance written notice with reasons; no nonrenewal solely because the driver is 60 | D20: DFS | E20: NY Dept of Financial Services - Auto Insurance Information for Consumers | F20: https://www.dfs.ny.gov/consumers/auto_insurance/Auto_resource_center | G20: 46295 | H20: New York | I20: Regulator-published | J20: Primary source | K20: 46295
A21: Programs | B21: Auto Plan (NYAIP) | C21: For those declined in the voluntary market; same premium whichever insurer is assigned; insurer must keep you 3 years before nonrenewal | D21: DFS | E21: NY Dept of Financial Services - Auto Insurance Information for Consumers | F21: https://www.dfs.ny.gov/consumers/auto_insurance/Auto_resource_center | G21: 46295 | H21: New York | I21: Regulator-published | J21: Primary source | K21: 46295
A22: Claims | B22: Physical damage timelines (Reg. 64) | C22: Inspect and make good-faith offer within 6 business days; pay within 5 business days of agreement; written reason if unsettled after 30 days | D22: DFS | E22: NY Dept of Financial Services - Auto Insurance Information for Consumers | F22: https://www.dfs.ny.gov/consumers/auto_insurance/Auto_resource_center | G22: 46295 | H22: New York | I22: Regulator-published | J22: Primary source | K22: 46295
A23: Fees | B23: Motor vehicle law enforcement fee | C23: $10 per vehicle per year ($5 for six-month policy) | D23: DFS | E23: NY Dept of Financial Services - Auto Insurance Information for Consumers | F23: https://www.dfs.ny.gov/consumers/auto_insurance/Auto_resource_center | G23: 46295 | H23: New York | I23: Regulator-published | J23: Primary source | K23: 46295

Sheet TX Home Verified
A1: Topic | B1: Fact | C1: Value | D1: Legal Citation | E1: Source | F1: Source URL | G1: Date Collected | H1: Geographic Scope | I1: Data Type | J1: Verification Status | K1: Last Updated | L1: Notes
A2: Coverage | B2: Standard coverages | C2: Most Texas home policies include six coverages; dwelling coverage pays if the house is damaged or destroyed by a covered peril | D2: TDI home guide (CB025) | E2: Texas Dept of Insurance - Home insurance guide (CB025) | F2: https://www.tdi.texas.gov/pubs/consumer/cb025.html | G2: 46295 | H2: Texas | I2: Regulator-published | J2: Primary source | K2: 46295
A3: Settlement | B3: Replacement cost vs actual cash value | C3: Replacement cost pays current repair or rebuild cost; actual cash value pays replacement cost minus depreciation and costs less | D3: TDI home insurance page | E3: Texas Dept of Insurance - Home insurance guide (CB025) | F3: https://www.tdi.texas.gov/pubs/consumer/cb025.html | G3: 46295 | H3: Texas | I3: Regulator-published | J3: Primary source | K3: 46295
A4: Liability | B4: Personal liability | C4: Home policies include liability protection with a limited amount; a separate umbrella policy can add more | D4: TDI home guide | E4: Texas Dept of Insurance - Home insurance guide (CB025) | F4: https://www.tdi.texas.gov/pubs/consumer/cb025.html | G4: 46295 | H4: Texas | I4: Regulator-published | J4: Primary source | K4: 46295
A5: Flood | B5: Is flood covered? | C5: No. A separate flood policy is needed, from an insurer or the National Flood Insurance Program | D5: TDI flood page | E5: Texas Dept of Insurance - Home insurance guide (CB025) | F5: https://www.tdi.texas.gov/pubs/consumer/cb025.html | G5: 46295 | H5: Texas | I5: Regulator-published | J5: Primary source | K5: 46295
A6: Flood | B6: Waiting period | C6: NFIP policies take effect 30 days after purchase unless bought for a new home purchase | D6: TDI blog | E6: Texas Dept of Insurance - Home and property blog | F6: https://tdi.texas.gov/blog/category/home-property.html | G6: 46295 | H6: Texas | I6: Regulator-published | J6: Primary source | K6: 46295
A7: Wind | B7: Coastal homes | C7: Home policy may not cover wind and hail on the Texas coast or in Harris County on Galveston Bay; TWIA sells wind and hail coverage | D7: TDI home guide | E7: Texas Dept of Insurance - Home insurance guide (CB025) | F7: https://www.tdi.texas.gov/pubs/consumer/cb025.html | G7: 46295 | H7: Texas | I7: Regulator-published | J7: Primary source | K7: 46295
A8: Wind | B8: TWIA territory | C8: 14 coastal counties and parts of Harris County east of Highway 146 | D8: TDI market overview | E8: Texas Dept of Insurance - Texas homeowners insurance market overview | F8: https://www.tdi.texas.gov/general/texas-homeowners-insurance-market-overview.html | G8: 46295 | H8: Texas | I8: Regulator-published | J8: Primary source | K8: 46295
A9: Wind | B9: TWIA eligibility | C9: May require flood insurance first and an engineer or windstorm inspection; flood is required when property is in a V-type flood zone and NFIP flood is available | D9: TDI home guide; TWIA | E9: TWIA - Flood insurance requirements | F9: https://www.twia.org/flood-requirement/ | G9: 46295 | H9: Texas | I9: Regulator-published | J9: Primary source | K9: 46295 | L9: TWIA sells wind and hail only, so a flood policy and a separate home policy are usually also needed.
A10: Wind | B10: TWIA claim deadline | C10: One year from the date of damage | D10: TDI home guide | E10: Texas Dept of Insurance - Home insurance guide (CB025) | F10: https://www.tdi.texas.gov/pubs/consumer/cb025.html | G10: 46295 | H10: Texas | I10: Regulator-published | J10: Primary source | K10: 46295
A11: Wind | B11: Named storm cutoff | C11: Once a named storm enters the Gulf, most insurers including TWIA stop selling new policies or making changes | D11: TDI blog | E11: Texas Dept of Insurance - Home and property blog | F11: https://tdi.texas.gov/blog/category/home-property.html | G11: 46295 | H11: Texas | I11: Regulator-published | J11: Primary source | K11: 46295 | L11: Timing matters for any 'buy now' guidance.
A12: Wind | B12: TWIA maximum dwelling coverage | C12: About $1.8 million reported; one source says the Commissioner disapproved a proposed increase to $1,809,000 (TDI Order 2025-9540) | D12: Not confirmed | E12: Latent Insurance - TWIA coverage, limits and cost (Aug 2026) | F12: https://www.latentinsure.com/texas-homeowners-insurance/twia | G12: 46295 | H12: Texas | I12: Reference data (secondary source) | J12: Conflicting | K12: 46295 | L12: The two statements can both be true or the limit may differ; check TWIA's current limits.
A13: Residual market | B13: FAIR Plan eligibility | C13: Texas-licensed companies will not insure you, at least two turned you down, and no company offered the same level of coverage | D13: TDI home insurance page | E13: Texas Dept of Insurance - Home insurance guide (CB025) | F13: https://www.tdi.texas.gov/pubs/consumer/cb025.html | G13: 46295 | H13: Texas | I13: Regulator-published | J13: Primary source | K13: 46295
A14: Policy changes | B14: Nonrenewal notice | C14: Company must give 60 days' notice before the policy ends | D14: TDI blog | E14: Texas Dept of Insurance - Home and property blog | F14: https://tdi.texas.gov/blog/category/home-property.html | G14: 46295 | H14: Texas | I14: Regulator-published | J14: Primary source | K14: 46295 | L14: Undated blog; compare with the auto rule, which is date-specific.
A15: Claims | B15: Public adjusters | C15: Must hold a TDI license | D15: TDI home guide | E15: Texas Dept of Insurance - Home insurance guide (CB025) | F15: https://www.tdi.texas.gov/pubs/consumer/cb025.html | G15: 46295 | H15: Texas | I15: Regulator-published | J15: Primary source | K15: 46295
A16: Market | B16: Average annual homeowners premium | C16: $3,506 (preliminary 2025) | D16: TDI June 2026 market overview (as reported) | E16: Aegivra - Texas homeowners insurance guide (Jul 2026) | F16: https://aegivra.com/guides/texas-homeowners-insurance-guide | G16: 46295 | H16: Texas | I16: Reference data (secondary source) | J16: Secondary - unverified | K16: 46295 | L16: Read the TDI overview directly before using.
A17: Deductible | B17: Wind/hail deductible form | C17: Usually a percentage of Coverage A; for example 2% of a $500,000 dwelling limit is $10,000 | D17: Policy practice (not a statute) | E17: Aegivra - Texas homeowners insurance guide (Jul 2026) | F17: https://aegivra.com/guides/texas-homeowners-insurance-guide | G17: 46295 | H17: Texas | I17: Reference data (secondary source) | J17: Secondary - unverified | K17: 46295 | L17: Percentages vary by policy.

Sheet FL Home Verified
A1: Topic | B1: Fact | C1: Value | D1: Legal Citation | E1: Source | F1: Source URL | G1: Date Collected | H1: Geographic Scope | I1: Data Type | J1: Verification Status | K1: Last Updated | L1: Notes
A2: Hurricane deductible | B2: Options insurers must offer | C2: $500, 2%, 5% and 10% of the policy dwelling limit before issuing a personal residential policy (unless the percentage is under $500) | D2: Fla. Stat. 627.701(3)(a) | E2: Florida Statutes 627.701 - deductibles (via FindLaw) | F2: https://codes.findlaw.com/fl/title-xxxvii-insurance/fl-st-sect-627-701/ | G2: 46295 | H2: Florida | I2: Statute / regulation text | J2: Primary source | K2: 46295 | L2: Statute text seen via FindLaw snippet.
A3: Hurricane deductible | B3: When it applies | C3: Begins when a hurricane warning is issued for any part of Florida; applies annually if the same insurer or group covers you | D3: Fla. Stat. 627.4025 (per DFS) | E3: Florida DFS - Florida's Hurricane Deductible | F3: https://www.myfloridacfo.com/division/consumers/consumerprotections/floridashurricanedeductible | G3: 46295 | H3: Florida | I3: Regulator-published | J3: Primary source | K3: 46295 | L3: A secondary source says it ends 72 hours after the last watch or warning ends.
A4: Hurricane deductible | B4: Separate from other perils | C4: A percentage hurricane deductible is separate from the regular deductible; only the hurricane deductible applies to a hurricane loss | D4: DFS; secondary sources | E4: Florida DFS - Florida's Hurricane Deductible | F4: https://www.myfloridacfo.com/division/consumers/consumerprotections/floridashurricanedeductible | G4: 46295 | H4: Florida | I4: Regulator-published | J4: Primary source | K4: 46295 | L4: Example: 2% of a $340,000 dwelling limit is $6,800 (Coverage Classroom).
A5: Wind coverage | B5: Windstorm exclusion | C5: Authorized insurers (not surplus lines) must make a windstorm exclusion available | D5: Fla. Stat. 627.712 (per DFS) | E5: Florida DFS - Florida's Hurricane Deductible | F5: https://www.myfloridacfo.com/division/consumers/consumerprotections/floridashurricanedeductible | G5: 46295 | H5: Florida | I5: Regulator-published | J5: Primary source | K5: 46295
A6: Wind coverage | B6: Mitigation credits | C6: When the owner has taken hurricane mitigation measures, insurer must offer a reduced hurricane deductible or a discount credit | D6: Fla. Stat. 627.701(9); 627.0629 | E6: Florida Statutes 627.701 - deductibles (via FindLaw) | F6: https://codes.findlaw.com/fl/title-xxxvii-insurance/fl-st-sect-627-701/ | G6: 46295 | H6: Florida | I6: Statute / regulation text | J6: Primary source | K6: 46295 | L6: Text seen is from a 2011 version; confirm current law.
A7: Wind coverage | B7: Separate roof deductible | C7: Insurers may include a separate roof deductible meeting statutory conditions; policyholder may opt out at initial issuance | D7: Fla. Stat. 627.701(10) | E7: Florida Statutes 627.701 - deductibles (via FindLaw) | F7: https://codes.findlaw.com/fl/title-xxxvii-insurance/fl-st-sect-627-701/ | G7: 46295 | H7: Florida | I7: Statute / regulation text | J7: Primary source | K7: 46295 | L7: Conditions were truncated in the snippet; read the statute.
A8: Flood | B8: Is flood covered? | C8: No. Homeowners policies exclude flood and Citizens may not insure flood | D8: Fla. Stat. 627.715 (per secondary source) | E8: Coverage Classroom - Hurricane insurance in Florida | F8: https://coverageclassroom.com/learn/hurricane-insurance-florida-guide | G8: 46295 | H8: Florida | I8: Reference data (secondary source) | J8: Secondary - unverified | K8: 46295
A9: Citizens | B9: Flood requirement phase-in | C9: Citizens wind policies need separate flood coverage: $600,000+ dwelling from Jan 1, 2024; $500,000+ from Jan 1, 2025; $400,000+ from Jan 1, 2026; all remaining policies from Jan 1, 2027; policies without wind are excluded | D9: Fla. Stat. 627.351(6)(aa) (per secondary sources) | E9: Coverage Classroom - Citizens flood requirement phase-in | F9: https://coverageclassroom.com/learn/citizens-flood-insurance-requirement | G9: 46295 | H9: Florida | I9: Reference data (secondary source) | J9: Secondary - unverified | K9: 46295 | L9: Confirm on Citizens' site. Coverage Criteria/Lewis Insurance agree on the $400,000 level for 2026.
A10: Citizens | B10: Eligibility price test | C10: A private offer within 20% of the Citizens rate can make the risk ineligible | D10: Fla. Stat. 627.351(6) (per secondary sources) | E10: CIG Florida - Policy updates for Florida homeowners (Apr 2026) | F10: https://www.cigflorida.com/policy-updates-for-florida-homeowners/ | G10: 46295 | H10: Florida | I10: Reference data (secondary source) | J10: Secondary - unverified | K10: 46295 | L10: Three sources agree.
A11: Citizens | B11: Surcharges and assessments | C11: Policyholder surcharge up to 45% and emergency assessments up to 30% on most Florida policies after a deficit | D11: Fla. Stat. 627.351(6) (per CIG) | E11: CIG Florida - Policy updates for Florida homeowners (Apr 2026) | F11: https://www.cigflorida.com/policy-updates-for-florida-homeowners/ | G11: 46295 | H11: Florida | I11: Reference data (secondary source) | J11: Secondary - unverified | K11: 46295
A12: Citizens | B12: Size | C12: 1.93% of the statewide homeowners market and 57.33% of the wind-only market as of Mar 31, 2026 | D12: OIR data (per Coverage Classroom) | E12: Coverage Classroom - Citizens flood requirement phase-in | F12: https://coverageclassroom.com/learn/citizens-flood-insurance-requirement | G12: 46295 | H12: Florida | I12: Reference data (secondary source) | J12: Secondary - unverified | K12: 46295 | L12: Policy counts disagree: over 1.2 million (Louis Law) vs under 400,000 (Lewis Insurance, Jan 2026).
A13: Market | B13: County average premiums including wind (Mar 31, 2026) | C13: Sumter $2,105 (lowest; $1,352 without wind); Osceola $2,940 | D13: OIR July 2026 report (per Coverage Classroom) | E13: Coverage Classroom - Hurricane insurance in Florida | F13: https://coverageclassroom.com/learn/hurricane-insurance-florida-guide | G13: 46295 | H13: Florida | I13: Reference data (secondary source) | J13: Secondary - unverified | K13: 46295 | L13: Read the OIR report directly.

Sheet State Min Limits
A1: State | B1: BI Per Person ($k) | C1: BI Per Accident ($k) | D1: PD ($k) | E1: Fault System | F1: PIP / MedPay | G1: UM/UIM | H1: Change Note | I1: Source | J1: Source URL | K1: Date Collected | L1: Geographic Scope | M1: Data Type | N1: Verification Status | O1: Last Updated | P1: Notes
A2: Alabama | K2: 46295 | L2: Alabama | M2: Placeholder | N2: Not researched | O2: 46295 | P2: To research: check state DOI/DMV for current limits.
A3: Alaska | B3: 50 | C3: 100 | D3: 25 | I3: Insurance Geek - Minimum limits by state (Apr 2026) | J3: https://www.insurancegeek.com/auto-insurance/state-minimum-car-insurance-limits/ | K3: 46295 | L3: Alaska | M3: Reference data (secondary source) | N3: Secondary - unverified | O3: 46295 | P3: Described as among the highest minimums.
A4: Arizona | K4: 46295 | L4: Arizona | M4: Placeholder | N4: Not researched | O4: 46295 | P4: To research: check state DOI/DMV for current limits.
A5: Arkansas | K5: 46295 | L5: Arkansas | M5: Placeholder | N5: Not researched | O5: 46295 | P5: To research: check state DOI/DMV for current limits.
A6: California | B6: 30 | C6: 60 | D6: 15 | E6: Comparative negligence (per CDI) | F6: MedPay optional; minimum purchasable limit $1,000 per person | G6: UM/UIM must be offered; can be declined by signed waiver | H6: SB 1107: increased limits begin 2025 | I6: CA DMV - Auto Insurance Requirements (modified Jul 10, 2025) | J6: https://www.dmv.ca.gov/portal/vehicle-registration/insurance-requirements/ | K6: 46295 | L6: California | M6: Reference data (secondary source) | N6: Primary source | O6: 46295 | P6: Verified on DMV and CDI pages (Insurance Code section 11580.1(b)). Policies renew at new limits (per law-firm summaries, secondary). See CA Auto Verified tab.
A7: Colorado | K7: 46295 | L7: Colorado | M7: Placeholder | N7: Not researched | O7: 46295 | P7: To research: check state DOI/DMV for current limits.
A8: Connecticut | K8: 46295 | L8: Connecticut | M8: Placeholder | N8: Not researched | O8: 46295 | P8: To research: check state DOI/DMV for current limits.
A9: Delaware | K9: 46295 | L9: Delaware | M9: Placeholder | N9: Not researched | O9: 46295 | P9: To research: check state DOI/DMV for current limits.
A10: District of Columbia | K10: 46295 | L10: District of Columbia | M10: Placeholder | N10: Not researched | O10: 46295 | P10: To research: check state DOI/DMV for current limits.
A11: Florida | B11: None required | C11: None required | D11: 10 | E11: No-fault | F11: PIP $10,000 required (pays 80% of necessary medical expenses regardless of fault) | I11: Florida DHSMV - Florida Insurance Requirements | J11: https://www.flhsmv.gov/insurance/ | K11: 46295 | L11: Florida | M11: Reference data (secondary source) | N11: Primary source | O11: 46295 | P11: FLHSMV: PIP and PDL required to register vehicles with 4+ wheels; BI not required for most private vehicles (taxis: 125/250/50). After a crash, the Financial Responsibility Law can require BI proof of 10/20. See FL Auto Verified.
A12: Georgia | B12: 25 | C12: 50 | D12: 25 | F12: Medical Payments optional, in varying amounts | G12: Uninsured motorist coverage optional | I12: Georgia OCI - Consumer Guide for Automobile Insurance | J12: https://oci.georgia.gov/document/document/guide-auto-insurance/download | K12: 46296 | L12: Georgia | M12: Regulator-published | N12: Primary source | O12: 46296 | P12: To research: check state DOI/DMV for current limits.
A13: Hawaii | B13: 40 | C13: 80 | D13: 20 | H13: Single source says minimums rise from 20/40/10 to 40/80/20 in 2026 | I13: Beach Insurance LLC - State minimums 2026 | J13: https://beachinsurancellc.com/blog/state-minimum-car-insurance-requirements-for-2026-your-essential-guide | K13: 46295 | L13: Hawaii | M13: Reference data (secondary source) | N13: Secondary - unverified | O13: 46295 | P13: Only one source found for the 2026 change; verify with Hawaii Insurance Division.
A14: Idaho | K14: 46295 | L14: Idaho | M14: Placeholder | N14: Not researched | O14: 46295 | P14: To research: check state DOI/DMV for current limits.
A15: Illinois | B15: 25 | C15: 50 | D15: 20 | F15: Medical payments optional (no PIP/no-fault requirement) | G15: UM bodily injury required at $25,000/$50,000 (same as liability minimums); UIM mandatory when buying higher UM limits; UMPD optional, insurer must offer with a max $250 deductible | I15: Illinois Dept of Insurance - Auto Insurance Shopping Guide | J15: https://idoi.illinois.gov/consumers/consumerinsurance/auto-insurance-shopping-guide.html | K15: 46296 | L15: Illinois | M15: Regulator-published | N15: Primary source | O15: 46296 | P15: To research: check state DOI/DMV for current limits.
A16: Indiana | K16: 46295 | L16: Indiana | M16: Placeholder | N16: Not researched | O16: 46295 | P16: To research: check state DOI/DMV for current limits.
A17: Iowa | B17: 20 | C17: 40 | D17: 15 | I17: Coverage Criteria - Minimum auto insurance by state (Feb 2026) | J17: https://coveragecriteria.com/articles/minimum-auto-insurance-by-state | K17: 46295 | L17: Iowa | M17: Reference data (secondary source) | N17: Secondary - unverified | O17: 46295 | P17: Among the lowest bodily injury minimums.
A18: Kansas | K18: 46295 | L18: Kansas | M18: Placeholder | N18: Not researched | O18: 46295 | P18: To research: check state DOI/DMV for current limits.
A19: Kentucky | B19: 25 | C19: 50 | D19: 25 | F19: Basic PIP included (per source) | I19: AutoInsurance.org - Requirements by state | J19: https://www.autoinsurance.org/car-insurance-requirements/ | K19: 46295 | L19: Kentucky | M19: Reference data (secondary source) | N19: Secondary - unverified | O19: 46295
A20: Louisiana | B20: 15 | C20: 30 | D20: 25 | I20: Coverage Criteria - Minimum auto insurance by state (Feb 2026) | J20: https://coveragecriteria.com/articles/minimum-auto-insurance-by-state | K20: 46295 | L20: Louisiana | M20: Reference data (secondary source) | N20: Secondary - unverified | O20: 46295 | P20: Among the lowest bodily injury minimums.
A21: Maine | B21: 50 | C21: 100 | D21: 25 | F21: MedPay required (per Beach Insurance) | I21: Insurance Geek - Minimum limits by state (Apr 2026) | J21: https://www.insurancegeek.com/auto-insurance/state-minimum-car-insurance-limits/ | K21: 46295 | L21: Maine | M21: Reference data (secondary source) | N21: Secondary - unverified | O21: 46295
A22: Maryland | K22: 46295 | L22: Maryland | M22: Placeholder | N22: Not researched | O22: 46295 | P22: To research: check state DOI/DMV for current limits.
A23: Massachusetts | K23: 46295 | L23: Massachusetts | M23: Placeholder | N23: Not researched | O23: 46295 | P23: To research: check state DOI/DMV for current limits.
A24: Michigan | B24: 50 | C24: 100 | D24: Not captured | E24: No-fault | F24: Tiered PIP; options from $50,000 up to unlimited medical (2020 reform) | I24: Coverage Criteria - Minimum auto insurance by state (Feb 2026) | J24: https://coveragecriteria.com/articles/minimum-auto-insurance-by-state | K24: 46295 | L24: Michigan | M24: Reference data (secondary source) | N24: Secondary - unverified | O24: 46295 | P24: PD minimum not captured; complex PIP tiers; verify with DIFS.
A25: Minnesota | K25: 46295 | L25: Minnesota | M25: Placeholder | N25: Not researched | O25: 46295 | P25: To research: check state DOI/DMV for current limits.
A26: Mississippi | K26: 46295 | L26: Mississippi | M26: Placeholder | N26: Not researched | O26: 46295 | P26: To research: check state DOI/DMV for current limits.
A27: Missouri | K27: 46295 | L27: Missouri | M27: Placeholder | N27: Not researched | O27: 46295 | P27: To research: check state DOI/DMV for current limits.
A28: Montana | K28: 46295 | L28: Montana | M28: Placeholder | N28: Not researched | O28: 46295 | P28: To research: check state DOI/DMV for current limits.
A29: Nebraska | K29: 46295 | L29: Nebraska | M29: Placeholder | N29: Not researched | O29: 46295 | P29: To research: check state DOI/DMV for current limits.
A30: Nevada | K30: 46295 | L30: Nevada | M30: Placeholder | N30: Not researched | O30: 46295 | P30: To research: check state DOI/DMV for current limits.
A31: New Hampshire | B31: No mandate | C31: No mandate | D31: No mandate | I31: CNBC Select - State minimum requirements | J31: https://www.cnbc.com/select/state-minimum-car-insurance-requirements/ | K31: 46295 | L31: New Hampshire | M31: Reference data (secondary source) | N31: Secondary - unverified | O31: 46295 | P31: No blanket requirement, but proof of financial responsibility needed; 25/50/25 applies if insured.
A32: New Jersey | B32: 35 | C32: 70 | D32: 25 | G32: UM/UIM limits also rising | H32: New limits effective Jan 1, 2026 (3 sources) | I32: CarInsurance.com - Minimum liability by state (Apr 2026) | J32: https://www.carinsurance.com/Articles/minimum-liability-car-insurance-requirements-by-state.aspx | K32: 46295 | L32: New Jersey | M32: Reference data (secondary source) | N32: Conflicting | O32: 46295 | P32: Coverage Criteria (Feb 2026) still lists older two-tier structure (Basic Policy: no BI minimum, $5K PD, $15K PIP; Standard: 15/30/5 + $15K PIP). Confirm with NJ DOBI.
A33: New Mexico | K33: 46295 | L33: New Mexico | M33: Placeholder | N33: Not researched | O33: 46295 | P33: To research: check state DOI/DMV for current limits.
A34: New York | B34: 25 | C34: 50 | D34: 10 | E34: No-fault | F34: Basic no-fault $50,000 required | G34: UM required at 25/50 (NY accidents); SUM included unless declined | H34: Death limits: $50,000 per person; $100,000 for two or more | I34: NY Dept of Financial Services - Auto Insurance Information for Consumers | J34: https://www.dfs.ny.gov/consumers/auto_insurance/Auto_resource_center | K34: 46295 | L34: New York | M34: Reference data (secondary source) | N34: Primary source | O34: 46295 | P34: DFS: 25/50/10 plus $50,000 basic no-fault. See NY Auto Verified.
A35: North Carolina | B35: 50 | C35: 100 | D35: 50 | G35: UM/UIM mandated on all policies | H35: Raised from 30/60/25, effective for policies issued/renewed on or after July 1, 2025 | I35: NCDOI - Changes to the Rating of Automobile Insurance Policies | J35: https://www.ncdoi.gov/changes-rating-automobile-insurance-policies-effective-july-1-2025 | K35: 46296 | L35: North Carolina | M35: Regulator-published | N35: Primary source | O35: 46296
A36: North Dakota | K36: 46295 | L36: North Dakota | M36: Placeholder | N36: Not researched | O36: 46295 | P36: To research: check state DOI/DMV for current limits.
A37: Ohio | K37: 46295 | L37: Ohio | M37: Placeholder | N37: Not researched | O37: 46295 | P37: To research: check state DOI/DMV for current limits.
A38: Oklahoma | K38: 46295 | L38: Oklahoma | M38: Placeholder | N38: Not researched | O38: 46295 | P38: To research: check state DOI/DMV for current limits.
A39: Oregon | K39: 46295 | L39: Oregon | M39: Placeholder | N39: Not researched | O39: 46295 | P39: To research: check state DOI/DMV for current limits.
A40: Pennsylvania | B40: 15 | C40: 30 | D40: 5 | E40: Choice no-fault (full tort / limited tort election) | F40: Medical Benefits required, minimum $5,000, pays regardless of fault | G40: UM/UIM optional; stacking applies by law unless rejected | H40: Combined single limit option of $35,000 meets both BI and PD minimums | I40: Pennsylvania Insurance Department - Automobile Insurance Guide | J40: https://www.pa.gov/content/dam/copapwp-pagov/en/insurance/documents/consumer-help-center/learn-about-insurance/auto-insurance-guide.pdf | K40: 46296 | L40: Pennsylvania | M40: Regulator-published | N40: Primary source | O40: 46296 | P40: Limits not captured in this research.
A41: Rhode Island | K41: 46295 | L41: Rhode Island | M41: Placeholder | N41: Not researched | O41: 46295 | P41: To research: check state DOI/DMV for current limits.
A42: South Carolina | K42: 46295 | L42: South Carolina | M42: Placeholder | N42: Not researched | O42: 46295 | P42: To research: check state DOI/DMV for current limits.
A43: South Dakota | K43: 46295 | L43: South Dakota | M43: Placeholder | N43: Not researched | O43: 46295 | P43: To research: check state DOI/DMV for current limits.
A44: Tennessee | B44: 25 | C44: 50 | D44: 25 | I44: AutoInsurance.org - Requirements by state | J44: https://www.autoinsurance.org/car-insurance-requirements/ | K44: 46295 | L44: Tennessee | M44: Reference data (secondary source) | N44: Secondary - unverified | O44: 46295
A45: Texas | B45: 30 | C45: 60 | D45: 25 | F45: PIP included in auto policies unless rejected in writing | G45: UM/UIM must be offered; can be rejected in writing | I45: Texas Dept of Insurance - Auto insurance guide (CB020) | J45: https://www.tdi.texas.gov/pubs/consumer/cb020.html | K45: 46295 | L45: Texas | M45: Reference data (secondary source) | N45: Primary source | O45: 46295 | P45: TDI guide. Only liability is required. See TX Auto Verified.
A46: Utah | B46: 30 | C46: 65 | D46: 25 | H46: Raised in 2025 per source | I46: CarInsurance.com - Minimum liability by state (Apr 2026) | J46: https://www.carinsurance.com/Articles/minimum-liability-car-insurance-requirements-by-state.aspx | K46: 46295 | L46: Utah | M46: Reference data (secondary source) | N46: Secondary - unverified | O46: 46295
A47: Vermont | B47: 25 | C47: 50 | D47: 10 | G47: UM/UIM 50/100/10 | I47: AutoInsurance.org - Requirements by state | J47: https://www.autoinsurance.org/car-insurance-requirements/ | K47: 46295 | L47: Vermont | M47: Reference data (secondary source) | N47: Secondary - unverified | O47: 46295
A48: Virginia | B48: 50 | C48: 100 | D48: 25 | H48: New limits effective Jan 1, 2025, confirmed directly by VA DMV | I48: Virginia DMV - Insurance Requirements | J48: https://www.dmv.virginia.gov/vehicles/insurance-requirements | K48: 46296 | L48: Virginia | M48: Regulator-published | N48: Primary source | O48: 46296 | P48: The $30,000/$60,000/$20,000 figure some sources list was the prior minimum, in effect Jan 1, 2022 - Dec 31, 2024.
A49: Washington | K49: 46295 | L49: Washington | M49: Placeholder | N49: Not researched | O49: 46295 | P49: To research: check state DOI/DMV for current limits.
A50: West Virginia | K50: 46295 | L50: West Virginia | M50: Placeholder | N50: Not researched | O50: 46295 | P50: To research: check state DOI/DMV for current limits.
A51: Wisconsin | K51: 46295 | L51: Wisconsin | M51: Placeholder | N51: Not researched | O51: 46295 | P51: To research: check state DOI/DMV for current limits.
A52: Wyoming | K52: 46295 | L52: Wyoming | M52: Placeholder | N52: Not researched | O52: 46295 | P52: To research: check state DOI/DMV for current limits.

Sheet Rating Factors
A1: State | B1: Credit - Auto | C1: Credit - Home | D1: Gender | E1: Age | F1: Other Notes | G1: Source | H1: Source URL | I1: Date Collected | J1: Geographic Scope | K1: Data Type | L1: Verification Status | M1: Last Updated | N1: Notes
A2: California | B2: Not on approved factor list (10 CCR 2632.5) | C2: Banned (secondary: CNBC, Newsweek) - not yet verified from primary | D2: Not on approved factor list; regulation history shows one factor repealed effective Jan 1, 2019 | E2: Not on approved list; only years licensed (third mandatory factor) | F2: Mandatory factors in order: driving safety record, annual miles, years of driving experience. ZIP allowed only through claims frequency/severity bands (max 20 categories each); marital status is an allowed optional factor. | G2: 10 CCR section 2632.5 - Rating Factors (text via Cornell LII) | H2: https://www.law.cornell.edu/regulations/california/10-CCR-2632.5 | I2: 46295 | J2: California | K2: Regulation text | L2: Primary source | M2: 46295 | N2: Resolves the earlier conflict: The Zebra and Firstcard were each partly right. Home-credit column is still secondary. Absence from the list is derived from the regulation text; confirm with counsel.
A3: California (home) | B3: Not applicable (auto rule) | C3: Unresolved: no explicit statute found; reports say CDI does not approve homeowners rate filings that depend on credit, while older reports say some insurers used credit in underwriting | D3: Not captured | E3: Not captured | F3: A ban bill passed the Senate in 2022 (outcome not confirmed); 2004 and 2006 bills were earlier attempts. Experian (2025) says CA insurers do not use credit for homeowners rates. | G3: United Policyholders - Should states ban credit-based insurance scoring? (2013) | H3: https://uphelp.org/should-states-ban-credit-based-insurance-scoring/ | I3: 46295 | J3: California | K3: Reference data (secondary source) | L3: Conflicting | M3: 46295 | N3: Ask CDI directly and check Insurance Code and CDI rate-filing rules for homeowners.
A4: Hawaii | B4: Banned | C4: Allowed (per Newsweek); CNBC says auto ban only | D4: Not captured | E4: Not captured | F4: Credit banned for auto only, per Newsweek. | G4: Newsweek - Where your credit score can/can't raise insurance costs | H4: https://www.newsweek.com/where-your-credit-score-can-cant-raise-insurance-costs-11885672 | I4: 46295 | J4: Hawaii | K4: Reference data (secondary source) | L4: Secondary - unverified | M4: 46295 | N4: Age/gender rules not captured.
A5: Texas | B5: Allowed, but cannot be the only reason to turn down or charge more | C5: Not captured | D5: Age, gender, marital status, location, disability allowed only if the insurer can show greater risk | E5: Same as gender | F5: Race, color, religion, national origin may not be used. TDI HelpInsure.com lists which insurers use credit. | G5: Texas Dept of Insurance - Auto insurance guide (CB020) | H5: https://www.tdi.texas.gov/pubs/consumer/cb020.html | I5: 46295 | J5: Texas | K5: Regulator-published | L5: Primary source | M5: 46295 | N5: TDI guide wording; underlying statute not read.
A6: Florida | B6: Regulated by s. 626.9741: insurer must disclose use, allow appeals for certain life events, and may not use certain inquiries or medical collections | C6: Same statute covers personal residential lines | D6: Not captured | E6: Not captured | F6: Statute applies to personal lines motor vehicle and residential insurance. | G6: Florida Statutes 626.9741 - Credit reports and scores by insurers | H6: https://www.flsenate.gov/Laws/Statutes/2025/0626.9741 | I6: 46295 | J6: Florida | K6: Statute text | L6: Primary source | M6: 46295 | N6: Seen in snippets and older-year text; other rating limits (age, gender) not researched.
A7: New York | B7: Allowed; cannot be sole basis for rejection; insurer may not terminate or raise renewal premium based on credit | C7: Not captured | D7: Sex is a permitted rating classification but refusing or terminating because of sex is prohibited | E7: Age is a permitted classification; 60+ cannot be sole reason for non-renewal | F7: Classifications include age, sex, marital status, territory, mileage, use and driving experience; unlicensed under 3 years gets an inexperienced-operator surcharge; disclosure and 3-year credit review rules apply. | G7: NY Dept of Financial Services - Auto Insurance Information for Consumers | H7: https://www.dfs.ny.gov/consumers/auto_insurance/Auto_resource_center | I7: 46295 | J7: New York | K7: Regulator-published | L7: Primary source | M7: 46295 | N7: DFS page. Confirm exact statutory limits with counsel.
A8: Massachusetts | B8: Banned | C8: Banned | D8: Prohibited (per The Zebra) | E8: Prohibited (per The Zebra) | F8: Marital status also prohibited; driving experience, ZIP and insurance history allowed with limits (The Zebra). | G8: The Zebra - Car insurance rating factors by state | H8: https://www.thezebra.com/resources/research/car-insurance-rating-factors-by-state/ | I8: 46295 | J8: Massachusetts | K8: Reference data (secondary source) | L8: Secondary - unverified | M8: 46295
A9: Michigan | B9: Conflicting | C9: Cannot be used to deny/cancel/non-renew (per Experian) | D9: Non-group policies prohibited (per The Zebra) | E9: Allowed per The Zebra | F9: Most sources say auto credit is banned; The Zebra lists credit history as 'allowed with limitations'; Firstcard says limited but not fully banned. | G9: Experian - States that restrict credit-based insurance scores | H9: https://www.experian.com/blogs/ask-experian/which-states-prohibit-or-restrict-the-use-of-credit-based-insurance-scores/ | I9: 46295 | J9: Michigan | K9: Reference data (secondary source) | L9: Conflicting | M9: 46295 | N9: Resolve with Michigan DIFS / Insurance Code of 1956.
A10: Maryland | B10: Allowed with restrictions (per Firstcard) | C10: Banned (per CNBC) | D10: Not captured | E10: Not captured | F10: Experian lists Maryland among 7 states with strict credit limits. | G10: CNBC - Insurance rates based on credit history draw scrutiny | H10: https://www.cnbc.com/2026/04/26/insurance-rates-credit-history.html | I10: 46295 | J10: Maryland | K10: Reference data (secondary source) | L10: Secondary - unverified | M10: 46295
A11: Oregon | B11: Strict limits (per Experian) | C11: Strict limits (per Experian) | D11: Not captured | E11: Not captured | G11: Experian - States that restrict credit-based insurance scores | H11: https://www.experian.com/blogs/ask-experian/which-states-prohibit-or-restrict-the-use-of-credit-based-insurance-scores/ | I11: 46295 | J11: Oregon | K11: Reference data (secondary source) | L11: Secondary - unverified | M11: 46295 | N11: Details of the limits not captured.
A12: Utah | B12: Strict limits (per Experian) | C12: Strict limits (per Experian) | D12: Not captured | E12: Not captured | G12: Experian - States that restrict credit-based insurance scores | H12: https://www.experian.com/blogs/ask-experian/which-states-prohibit-or-restrict-the-use-of-credit-based-insurance-scores/ | I12: 46295 | J12: Utah | K12: Reference data (secondary source) | L12: Secondary - unverified | M12: 46295 | N12: Details of the limits not captured.
A13: Washington | B13: Allowed (ban struck down) | C13: Not captured | D13: Not captured | E13: Not captured | F13: A court struck down the state's three-year credit ban in 2021 (MoneyGeek). | G13: MoneyGeek - Insurers that don't check credit | H13: https://www.moneygeek.com/insurance/auto/which-insurance-companies-dont-check-credit-score/ | I13: 46295 | J13: Washington | K13: Reference data (secondary source) | L13: Secondary - unverified | M13: 46295 | N13: Verify current status with WA OIC.
A14: All other states | B14: Generally allowed | C14: Generally allowed | D14: Generally allowed | E14: Generally allowed | F14: Per Experian, 7 states strictly limit credit use: CA, HI, MD, MA, MI, OR, UT. Bills pending in IA, NY, OK, PA (CNBC). | G14: Experian - States that restrict credit-based insurance scores | H14: https://www.experian.com/blogs/ask-experian/which-states-prohibit-or-restrict-the-use-of-credit-based-insurance-scores/ | I14: 46295 | J14: 46 states + DC | K14: Reference data (secondary source) | L14: Secondary - unverified | M14: 46295 | N14: Do not assume any factor is allowed; check each state's statute.
A15: NY | C15: Insurer must disclose use of credit information; policyholder may request re-underwriting/re-rating based on current credit at least every 3 years; credit updates may only be used to decrease premium, never increase it | G15: NY Dept of Financial Services - Ways to Save on Homeowners Insurance | H15: https://www.dfs.ny.gov/system/files/documents/2026/02/Ways-to-Save-Homeowners-Insurance.pdf | I15: 46296 | J15: New York | K15: Regulator-published | L15: Primary source | M15: 46296 | N15: Home credit-use rule only; NY auto credit-use rule not yet researched (left blank).
A16: IL | B16: Credit-based insurance scores used for auto and home insurance may not consider race, color, national origin, religion, gender, marital status, age, income, occupation or employment history, location of residence, any interest rate being charged, child/family support obligations or rental agreements, or certain credit inquiries (account review, employment, promotional) or credit counseling participation; insurers cannot base renewal rates solely on credit information; an insurer must use a credit report or score obtained within 90 days of writing or renewing a policy to take an adverse action; consumers may request premium reconsideration after an extraordinary life circumstance such as a catastrophic event, job loss, or serious illness | C16: Credit-based insurance scores used for auto and home insurance may not consider race, color, national origin, religion, gender, marital status, age, income, occupation or employment history, location of residence, any interest rate being charged, child/family support obligations or rental agreements, or certain credit inquiries (account review, employment, promotional) or credit counseling participation; insurers cannot base renewal rates solely on credit information; an insurer must use a credit report or score obtained within 90 days of writing or renewing a policy to take an adverse action; consumers may request premium reconsideration after an extraordinary life circumstance such as a catastrophic event, job loss, or serious illness | G16: Illinois Dept of Insurance - Credit: How Insurers Use It | H16: https://idoi.illinois.gov/consumers/consumerinsurance/credit.html | I16: 46296 | J16: Illinois | K16: Regulator-published | L16: Primary source | M16: 46296 | N16: 215 ILCS 157 (Use of Credit Information in Personal Insurance Act) applies identically to auto and home.

Sheet Discounts
A1: Discount | B1: Category | C1: State / Scope | D1: Availability | E1: Reported Amount | F1: Source | G1: Source URL | H1: Date Collected | I1: Geographic Scope | J1: Data Type | K1: Verification Status | L1: Last Updated | M1: Notes
A2: Accident prevention course (defensive driving) | B2: Driver / Vehicle | C2: New York | D2: Mandated by statute | E2: Amount not stated | F2: NY Dept of Financial Services - Auto Insurance Discounts | G2: https://www.dfs.ny.gov/consumers/auto_insurance/discounts_list | H2: 46295 | I2: New York | J2: Regulator-published | K2: Primary source | L2: 46295 | M2: Must be offered by all NY companies (DFS).
A3: Electronic tracking device | B3: Driver / Vehicle | C3: New York | D3: Mandated by statute | E3: Amount not stated | F3: NY Dept of Financial Services - Auto Insurance Discounts | G3: https://www.dfs.ny.gov/consumers/auto_insurance/discounts_list | H3: 46295 | I3: New York | J3: Regulator-published | K3: Primary source | L3: 46295 | M3: Must be offered by all NY companies (DFS).
A4: Factory-installed anti-lock brakes (ABS) | B4: Driver / Vehicle | C4: New York | D4: Mandated by statute | E4: Amount not stated | F4: NY Dept of Financial Services - Auto Insurance Discounts | G4: https://www.dfs.ny.gov/consumers/auto_insurance/discounts_list | H4: 46295 | I4: New York | J4: Regulator-published | K4: Primary source | L4: 46295 | M4: Must be offered by all NY companies (DFS).
A5: Passive restraints (automatic belts / air bags) | B5: Driver / Vehicle | C5: New York | D5: Mandated by statute | E5: Amount not stated | F5: NY Dept of Financial Services - Auto Insurance Discounts | G5: https://www.dfs.ny.gov/consumers/auto_insurance/discounts_list | H5: 46295 | I5: New York | J5: Regulator-published | K5: Primary source | L5: 46295 | M5: Must be offered by all NY companies (DFS).
A6: Factory-installed daytime running lamps | B6: Driver / Vehicle | C6: New York | D6: Mandated by statute | E6: Amount not stated | F6: NY Dept of Financial Services - Auto Insurance Discounts | G6: https://www.dfs.ny.gov/consumers/auto_insurance/discounts_list | H6: 46295 | I6: New York | J6: Regulator-published | K6: Primary source | L6: 46295 | M6: Must be offered by all NY companies (DFS).
A7: Window glass etching | B7: Driver / Vehicle | C7: New York | D7: Mandated by statute | E7: Amount not stated | F7: NY Dept of Financial Services - Auto Insurance Discounts | G7: https://www.dfs.ny.gov/consumers/auto_insurance/discounts_list | H7: 46295 | I7: New York | J7: Regulator-published | K7: Primary source | L7: 46295 | M7: Must be offered by all NY companies (DFS).
A8: Accident prevention course - guaranteed amount | B8: Driver | C8: New York | D8: Mandated | E8: 10% via PIRP for approved course | F8: MoneyGeek - Defensive driver discounts | G8: https://www.moneygeek.com/insurance/auto/defensive-driver-courses/ | H8: 46295 | I8: New York | J8: Reference data (secondary source) | K8: Secondary - unverified | L8: 46295 | M8: Amount from MoneyGeek; confirm with DFS.
A9: Defensive driver discount | B9: Driver | C9: Massachusetts, Michigan, Hawaii | D9: Not offered | E9: - | F9: MoneyGeek - Defensive driver discounts | G9: https://www.moneygeek.com/insurance/auto/defensive-driver-courses/ | H9: 46295 | I9: MA, MI, HI | J9: Reference data (secondary source) | K9: Secondary - unverified | L9: 46295 | M9: Per MoneyGeek: none offered regardless of carrier.
A10: Defensive driver discount | B10: Driver | C10: North Carolina | D10: Not offered (by GEICO) | E10: - | F10: GEICO - Defensive driving discounts by state | G10: https://www.geico.com/save/discounts/defensive-driver-discounts/ | H10: 46295 | I10: North Carolina | J10: Carrier-published | K10: Primary source | L10: 46295 | M10: GEICO-specific; other carriers may differ.
A11: Defensive driver discount | B11: Driver | C11: Massachusetts, Hawaii, Michigan (GEICO) | D11: Not offered (by GEICO) | E11: - | F11: GEICO - Defensive driving discounts by state | G11: https://www.geico.com/save/discounts/defensive-driver-discounts/ | H11: 46295 | I11: MA, HI, MI | J11: Carrier-published | K11: Primary source | L11: 46295 | M11: GEICO-specific statement.
A12: Defensive driver discount | B12: Driver | C12: Idaho | D12: Carrier-optional (GEICO) | E12: Up to 10% (GEICO) | F12: GEICO - Defensive driving discounts by state | G12: https://www.geico.com/save/discounts/defensive-driver-discounts/ | H12: 46295 | I12: Idaho | J12: Carrier-published | K12: Primary source | L12: 46295 | M12: GEICO-specific.
A13: Defensive driver discount | B13: Driver | C13: Texas | D13: Carrier-optional (no state mandate) | E13: Up to 10% at most carriers for TDLR-approved course | F13: MoneyGeek - Defensive driver discounts | G13: https://www.moneygeek.com/insurance/auto/defensive-driver-courses/ | H13: 46295 | I13: Texas | J13: Reference data (secondary source) | K13: Secondary - unverified | L13: 46295
A14: Good driver discount | B14: Driver | C14: California | D14: Mandated: every insurer must offer | E14: At least 20% below comparable non-good-driver rate | F14: CA Dept of Insurance - Introduction to Auto Insurance (Form 101, rev. Feb 5, 2025) | G14: https://www.insurance.ca.gov/01-consumers/105-type/95-guides/01-auto/auto101.cfm | H14: 46295 | I14: California | J14: Regulator-published | K14: Primary source | L14: 46295 | M14: Good driver: licensed 3+ consecutive years and no more than one point (CDI). Full statutory definition is Insurance Code 1861.025 - not yet read.
A15: Driver training / defensive driving discount | B15: Driver | C15: California | D15: Insurers permitted to offer (optional factor) | E15: Insurer-determined | F15: CDI Rate Regulation Advisory Notice 2005-02 (May 2, 2005) | G15: https://www.insurance.ca.gov/0250-insurers/0300-insurers/0200-bulletins/bulletin-notices-commiss-opinion/upload/Advisory-Notice-2005-02.pdf | H15: 46295 | I15: California | J15: Regulator-published | K15: Primary source | L15: 46295 | M15: 10 CCR 2632.6 authorizes it, per Advisory Notice 2005-02.
A16: Mature driver course discount (age 55+) | B16: Driver | C16: California | D16: Mandated: every admitted insurer must provide a reduction | E16: Insurer-determined percentage | F16: CA Insurance Code section 11628.3 - Mature driver (text via FindLaw) | G16: https://codes.findlaw.com/ca/insurance-code/ins-sect-11628-3/ | H16: 46295 | I16: California | J16: Statute text | K16: Primary source | L16: 46295 | M16: Principal operators 55+ with DMV-approved course certificate (Ins. Code 11628.3; 13 CCR 346.00). Secondary sites claim 5-15% for three years - unverified.
A17: Paid-in-full discount / six-month term surcharge | B17: Policy | C17: California | D17: Not permitted | E17: - | F17: CDI Rate Regulation Advisory Notice 2005-02 (May 2, 2005) | G17: https://www.insurance.ca.gov/0250-insurers/0300-insurers/0200-bulletins/bulletin-notices-commiss-opinion/upload/Advisory-Notice-2005-02.pdf | H17: 46295 | I17: California | J17: Regulator-published | K17: Primary source | L17: 46295 | M17: Six-month premium must be half the annual premium; no paid-in-full discount. Notice dated May 2005; confirm still current.
A18: Accident prevention course | B18: Driver | C18: New York | D18: Mandated: 3-year discount on liability, collision and no-fault | E18: Amount set by insurer; must be stated on declarations | F18: NY Dept of Financial Services - Auto Insurance Information for Consumers | G18: https://www.dfs.ny.gov/consumers/auto_insurance/Auto_resource_center | H18: 46295 | I18: New York | J18: Regulator-published | K18: Primary source | L18: 46295 | M18: Also up to a four-point reduction on the license record (DMV).
A19: ABS, daytime running lamps, air bags/automatic belts | B19: Vehicle | C19: New York | D19: Required discounts on liability, collision, no-fault and med-pay as described | E19: Amount stated on declarations | F19: NY Dept of Financial Services - Auto Insurance Information for Consumers | G19: https://www.dfs.ny.gov/consumers/auto_insurance/Auto_resource_center | H19: 46295 | I19: New York | J19: Regulator-published | K19: Primary source | L19: 46295 | M19: Anti-theft, electronic tracking and window etching discounts apply to comprehensive.
A20: Telematics / usage-based | B20: Usage | C20: New York | D20: Carrier-optional; data may include miles, time of day, acceleration, braking and GPS location | E20: Insurer-determined | F20: NY Dept of Financial Services - Auto Insurance Information for Consumers | G20: https://www.dfs.ny.gov/consumers/auto_insurance/Auto_resource_center | H20: 46295 | I20: New York | J20: Regulator-published | K20: Primary source | L20: 46295 | M20: Contrast with California, which bars location collection.
A21: Discounts generally | B21: Policy | C21: Texas | D21: Each company decides what to offer and how much | E21: Not stated | F21: Texas Dept of Insurance - Auto insurance guide (CB020) | G21: https://www.tdi.texas.gov/pubs/consumer/cb020.html | H21: 46295 | I21: Texas | J21: Regulator-published | K21: Primary source | L21: 46295 | M21: TDI lists airbags, ABS, antitheft, defensive driving/driver education, multi-car, multi-policy, good record as examples.
A22: Driver improvement course | B22: Driver | C22: Florida | D22: Permitted; discount up to 10% presumed appropriate (2003 text) | E22: Up to 10% | F22: Florida Statutes 627.06501 - Driver improvement course discount (2003 text) | G22: https://flsenate.gov/Laws/Statutes/2003/627.06501 | H22: 46295 | I22: Florida | J22: Statute text | K22: Primary source | L22: 46295 | M22: Old-year text; confirm current.
A23: Safety course (sections 627.0652) | B23: Driver | C23: Florida | D23: Required reduction for approved course; lasts 3 years; insurer may condition on no at-fault accident or moving violation | E23: Not stated | F23: Florida Statutes 627.0652 - Safety course discount (2012 text) | G23: https://www.flsenate.gov/laws/statutes/2012/627.0652 | H23: 46295 | I23: Florida | J23: Statute text | K23: Primary source | L23: 46295 | M23: 2012 text; course aimed at drivers 55+ per the text; confirm current.
A24: Specified equipment discounts | B24: Vehicle | C24: Florida | D24: Section 627.0653 exists (specified motor vehicle equipment) | E24: Not read | F24: Florida Statutes Chapter 627 (2025) - table of contents | G24: https://www.flsenate.gov/Laws/Statutes/2025/Chapter627/All | H24: 46295 | I24: Florida | J24: Statute text | K24: Secondary - unverified | L24: 46295 | M24: Only the section title was seen; read the statute.
A25: Senior / mature driver course | B25: Driver | C25: Varies by state | D25: Mandated in some states; otherwise carrier-optional | E25: Typically 5%-15% for 2-3 years (course providers) | F25: SafeDriver.com - Defensive driving discount 2026 | G25: https://www.safedriver.com/news/defensive-driving-for-insurance-discount-2026-how-much-you-can-really-save | H25: 46295 | I25: Multi-state | J25: Reference data (secondary source) | K25: Conflicting | L25: 46295 | M25: Sources disagree on how many states mandate it ('most' vs 'many'); age threshold varies (often 55). Provider is a course seller.
... A28: Safe driver / good driver | B28: Driver | C28: All states (carrier-defined) | D28: Carrier-optional | E28: Up to 30% (Insurance.com) | F28: Insurance.com - Auto insurance discounts guide | G28: https://www.insurance.com/auto-insurance/car-insurance-discounts.html | H28: 46295 | I28: Multi-state | J28: Reference data (secondary source) | K28: Secondary - unverified | L28: 46295 | M28: Definition varies by insurer.
A29: Group / affinity membership | B29: Policy | C29: All states (carrier-defined) | D29: Carrier-optional | E29: Up to 25% (Insurance.com) | F29: Insurance.com - Auto insurance discounts guide | G29: https://www.insurance.com/auto-insurance/car-insurance-discounts.html | H29: 46295 | I29: Multi-state | J29: Reference data (secondary source) | K29: Secondary - unverified | L29: 46295
A30: Driver education under age 21 | B30: Driver | C30: Varies by state (State Farm) | D30: Carrier-optional | E30: Not stated | F30: State Farm - Auto insurance discounts | G30: https://www.statefarm.com/insurance/auto/discounts | H30: 46295 | I30: Multi-state | J30: Carrier-published | K30: Primary source | L30: 46295 | M30: State Farm states discounts vary by state.
A31: Telematics / usage-based | B31: Usage | C31: Varies by carrier and state | D31: Carrier-optional | E31: See Telematics tab | F31: Insurify - Telematics car insurance programs | G31: https://insurify.com/car-insurance/coverage/telematics/ | H31: 46295 | I31: Multi-state | J31: Reference data (secondary source) | K31: Secondary - unverified | L31: 46295 | M31: States have their own laws on how telematics data may be used in rating.
A32: Required hurricane-mitigation discount (shutters, windows, doors) | B32: Property / Mitigation | C32: New York | D32: Mandated: insurers must provide discounts for hurricane-resistant shutters and hurricane-resistant windows and doors | E32: Amount not stated | F32: NY Dept of Financial Services - Ways to Save on Homeowners Insurance | G32: https://www.dfs.ny.gov/system/files/documents/2026/02/Ways-to-Save-Homeowners-Insurance.pdf | H32: 46296 | I32: New York | J32: Regulator-published | K32: Primary source | L32: 46296 | M32: Home insurance discount; distinct from NY's existing auto discount list.

Sheet Telematics
A1: Carrier | B1: Program | C1: Type | D1: State Availability | E1: Max / Reported Discount | F1: Enrollment Discount | G1: Surcharge Possible? | H1: Source | I1: Source URL | J1: Date Collected | K1: Geographic Scope | L1: Data Type | M1: Verification Status | N1: Last Updated | O1: Notes
A2: Progressive | B2: Snapshot | C2: App or plug-in device | D2: All states except California (Bankrate) | E2: Progressive: average $322 savings at renewal (reported) | F2: Not stated | G2: Yes - in some states (Progressive terms); ~20% of users see an increase at renewal (InsureMojo) | H2: Bankrate - Are telematics programs worth the discount | I2: https://www.bankrate.com/insurance/car/are-telematics-programs-worth-the-discount/ | J2: 46295 | K2: US (not CA) | L2: Reference data (secondary source) | M2: Conflicting | N2: 46295 | O2: Surcharge details differ by source; confirm in state filing. Widely available (47+ states per Insurify).
A3: State Farm | B3: Drive Safe & Save | C3: App / mileage-based | D3: At least 47 states (Insurify) | E3: Up to 30% | F3: 10% enrollment (InsureMojo) | G3: State Farm says no surcharge; Insurify says some programs can raise rates | H3: Insurify - Telematics car insurance programs | I3: https://insurify.com/car-insurance/coverage/telematics/ | J3: 46295 | K3: US (47+ states) | L3: Reference data (secondary source) | M3: Conflicting | N3: 46295 | O3: Conflict on surcharge; idarb also notes program can change prior low-mileage discount.
A4: Nationwide | B4: SmartRide | C4: Device / app | D4: At least 47 states (Insurify) | E4: Up to 40% | F4: 10% enrollment (InsureMojo) | G4: Not stated | H4: InsureMojo - Telematics discount programs compared | I4: https://www.insuremojo.com/telematics-insurance-discount-programs/ | J4: 46295 | K4: US (47+ states) | L4: Reference data (secondary source) | M4: Secondary - unverified | N4: 46295 | O4: InsureMojo says SmartRide does not track phone use.
A5: GEICO | B5: DriveEasy | C5: App | D5: Not captured | E5: Not stated | F5: Not stated | G5: Insurify says can raise rates | H5: Insurify - Telematics car insurance programs | I5: https://insurify.com/car-insurance/coverage/telematics/ | J5: 46295 | K5: Multi-state | L5: Reference data (secondary source) | M5: Secondary - unverified | N5: 46295 | O5: Uses driver scores to set safe-driver discounts.
A6: Allstate | B6: Drivewise | C6: App / device | D6: All states except Alaska and California (Bankrate) | E6: Not stated | F6: Not stated | G6: Not stated | H6: Bankrate - Are telematics programs worth the discount | I6: https://www.bankrate.com/insurance/car/are-telematics-programs-worth-the-discount/ | J6: 46295 | K6: US (not AK, CA) | L6: Reference data (secondary source) | M6: Secondary - unverified | N6: 46295 | O6: Based on three factors: speeding, hard braking, late-night driving.
A7: Allstate | B7: Milewise | C7: Pay-per-mile | D7: Not captured | E7: Not stated | F7: Not stated | G7: Not stated | H7: Bankrate - Are telematics programs worth the discount | I7: https://www.bankrate.com/insurance/car/are-telematics-programs-worth-the-discount/ | J7: 46295 | K7: Multi-state | L7: Reference data (secondary source) | M7: Secondary - unverified | N7: 46295 | O7: Designed for low-mileage drivers.
A8: Nationwide | B8: SmartMiles | C8: Pay-per-mile | D8: Not captured | E8: Not stated | F8: Not stated | G8: Not stated | H8: Bankrate - Are telematics programs worth the discount | I8: https://www.bankrate.com/insurance/car/are-telematics-programs-worth-the-discount/ | J8: 46295 | K8: Multi-state | L8: Reference data (secondary source) | M8: Secondary - unverified | N8: 46295
A9: Liberty Mutual / USAA / Travelers | B9: RightTrack / SafePilot / IntelliDrive | C9: Various | D9: Not captured | E9: Not captured | F9: Not captured | G9: Not captured | H9: QuoteYeti - Telematics tradeoffs | I9: https://www.quoteyeti.com/blog/telematics-tradeoffs/ | J9: 46295 | K9: Multi-state | L9: Reference data (secondary source) | M9: Not researched | N9: 46295 | O9: Named as existing programs only; terms not researched.
A10: All carriers | B10: New York rule | C10: Any telematics program | D10: New York | E10: Insurer-determined | F10: Insurer-determined | G10: Not stated | H10: NY Dept of Financial Services - Auto Insurance Information for Consumers | I10: https://www.dfs.ny.gov/consumers/auto_insurance/Auto_resource_center | J10: 46295 | K10: New York | L10: Regulator-published | M10: Primary source | N10: 46295 | O10: DFS says discounts may use GPS location, miles, time of day, acceleration and braking data.
A11: All carriers | B11: Texas note | C11: Any telematics program | D11: Texas | E11: Not stated | F11: Not stated | G11: Not stated | H11: Texas Dept of Insurance - Auto insurance guide (CB020) | I11: https://www.tdi.texas.gov/pubs/consumer/cb020.html | J11: 46295 | K11: Texas | L11: Regulator-published | M11: Not researched | N11: 46295 | O11: TDI links a page on how driving can lower premiums; not read.

Sheet Coverage Details
A1: Coverage | B1: Item | C1: Value | D1: Unit / Detail | E1: Source | F1: Source URL | G1: Date Collected | H1: Geographic Scope | I1: Data Type | J1: Verification Status | K1: Last Updated | L1: Notes
A2: Auto (all) | B2: 'Full coverage' is not a real policy type | C2: - | D2: NAIC says there is no such thing as 'full coverage'; use specific coverages (liability, collision, comprehensive). | E2: NAIC Consumer Shopping Tool for Auto Insurance | F2: https://content.naic.org/sites/default/files/consumer-auto-shopping-tool.pdf | G2: 46295 | H2: US | I2: Regulator-published | J2: Primary source | K2: 46295 | L2: Use in UI wording.
A3: Flood - NFIP | B3: Residential building limit (1-4 family) | C3: 250000 | D3: USD | E3: Lenders Network - Flood insurance mortgage requirements 2026 | F3: https://thelendersnetwork.com/flood-insurance-mortgage-requirements/ | G3: 46295 | H3: US | I3: Reference data (secondary source) | J3: Secondary - unverified | K3: 46295 | L3: Widely reported across sources; confirm on FEMA/FloodSmart.
A4: Flood - NFIP | B4: Residential contents limit | C4: 100000 | D4: USD | E4: Lenders Network - Flood insurance mortgage requirements 2026 | F4: https://thelendersnetwork.com/flood-insurance-mortgage-requirements/ | G4: 46295 | H4: US | I4: Reference data (secondary source) | J4: Secondary - unverified | K4: 46295 | L4: Contents paid on actual-cash-value basis (per Atesa).
A5: Flood - NFIP | B5: Waiting period | C5: 30 | D5: days; waived when bought with a mortgage closing | E5: Lenders Network - Flood insurance mortgage requirements 2026 | F5: https://thelendersnetwork.com/flood-insurance-mortgage-requirements/ | G5: 46295 | H5: US | I5: Reference data (secondary source) | J5: Secondary - unverified | K5: 46295
A6: Flood - NFIP | B6: Average annual premium | C6: $900-$1,100 | D6: USD/year | E6: Lenders Network - Flood insurance mortgage requirements 2026 | F6: https://thelendersnetwork.com/flood-insurance-mortgage-requirements/ | G6: 46295 | H6: US | I6: Estimate | J6: Secondary - unverified | K6: 46295 | L6: WalletGrower cites $926; Cover Forge about $900.
A7: Flood - NFIP | B7: Annual premium increase cap under Risk Rating 2.0 | C7: 18% | D7: per year (WalletGrower citing federal law) | E7: WalletGrower - Flood insurance 2026 | F7: https://walletgrower.com/insurance/homeowners-insurance/flood-insurance | G7: 46295 | H7: US | I7: Reference data (secondary source) | J7: Secondary - unverified | K7: 46295 | L7: Affiliate-linked source; verify with FEMA.
A8: Flood - NFIP | B8: Share of claims from outside high-risk zones | C8: 20% to 40%+ | D8: varies by source | E8: Atesa Risk Advisors - Private flood vs NFIP (Florida) | F8: https://atesariskadvisors.com/blog/florida-private-flood-insurance-vs-nfip-2026 | G8: 46295 | H8: US | I8: Estimate | J8: Conflicting | K8: 46295 | L8: Cover Forge says ~20%; Atesa says over 40%. Find FEMA figure.
A9: Flood - NFIP | B9: Authorization status | C9: Authorized through Dec 11, 2026 | D9: Continuing Appropriations Act, 2027 (P.L. 119-103, Div. A) section 139 | E9: CRS - Overview of Continuing Appropriations for FY2027 (P.L. 119-103, Div. A) | F9: https://www.congress.gov/crs-product/R49353 | G9: 46295 | H9: US | I9: Regulator-published | J9: Primary source | K9: 46295 | L9: Resolved: the Sept 30, 2026 deadline was extended to Dec 11, 2026. Prior lapses stalled new and renewed NFIP policies; private flood is unaffected. Check again before Dec 11, 2026.
A10: Flood - Private | B10: Building limits | C10: Often above $1,000,000 | D10: USD | E10: WalletGrower - Flood insurance 2026 | F10: https://walletgrower.com/insurance/homeowners-insurance/flood-insurance | G10: 46295 | H10: US | I10: Reference data (secondary source) | J10: Secondary - unverified | K10: 46295
A11: Flood - Private | B11: Waiting period | C11: 10-14 | D11: days (some shorter) | E11: WalletGrower - Flood insurance 2026 | F11: https://walletgrower.com/insurance/homeowners-insurance/flood-insurance | G11: 46295 | H11: US | I11: Reference data (secondary source) | J11: Secondary - unverified | K11: 46295
A12: Earthquake - CEA | B12: Deductible options | C12: 5%, 10%, 15%, 20%, 25% | D12: of dwelling coverage | E12: California Earthquake Authority - Homeowners policies | F12: https://www.earthquakeauthority.com/california-earthquake-insurance-policies/homeowners | G12: 46295 | H12: California | I12: Regulator-published | J12: Primary source | K12: 46295 | L12: Homes over $1M dwelling limit, or pre-1980 raised-foundation homes without verified retrofit, only 15%-25%.
A13: Earthquake - CEA | B13: Standard deductible | C13: 15% | D13: of dwelling coverage | E13: Express Financial - Earthquake insurance in California | F13: https://expressfinancial.net/p/earthquake-insurance-california | G13: 46295 | H13: California | I13: Reference data (secondary source) | J13: Secondary - unverified | K13: 46295
A14: Earthquake - CEA | B14: Retrofit premium discount | C14: Up to 25% | D14: of premium | E14: California Earthquake Authority - Homeowners policies | F14: https://www.earthquakeauthority.com/california-earthquake-insurance-policies/homeowners | G14: 46295 | H14: California | I14: Regulator-published | J14: Primary source | K14: 46295
A15: Earthquake - CEA | B15: Loss of use deductible | C15: None | D15: - | E15: California Earthquake Authority - Homeowners policies | F15: https://www.earthquakeauthority.com/california-earthquake-insurance-policies/homeowners | G15: 46295 | H15: California | I15: Regulator-published | J15: Primary source | K15: 46295
A16: Earthquake - CA law | B16: Insurers must offer earthquake coverage | C16: Re-offer every other year if declined | D16: Insurance Code chapter 8.5 (per source) | E16: Express Financial - Earthquake insurance in California | F16: https://expressfinancial.net/p/earthquake-insurance-california | G16: 46295 | H16: California | I16: Reference data (secondary source) | J16: Secondary - unverified | K16: 46295 | L16: Confirm statute with CDI.
A17: Earthquake - CEA | B17: Typical annual premium | C17: $800-$5,000+ | D17: USD/year | E17: EarthquakeNearMe - CA earthquake insurance cost | F17: https://www.earthquakenearme.com/en/blog/earthquake-insurance-california | G17: 46295 | H17: California | I17: Estimate | J17: Secondary - unverified | K17: 46295 | L17: Low-reliability source; get CEA premium calculator quotes.
A18: Earthquake - CA | B18: Share of homeowners carrying coverage | C18: About 13% | D18: of CA homeowners | E18: EarthquakeNearMe - CA earthquake insurance cost | F18: https://www.earthquakenearme.com/en/blog/earthquake-insurance-california | G18: 46295 | H18: California | I18: Estimate | J18: Secondary - unverified | K18: 46295 | L18: Low-reliability source.
A19: Earthquake | B19: Standard homeowners policies | C19: Exclude earthquake damage | D19: - | E19: Express Financial - Earthquake insurance in California | F19: https://expressfinancial.net/p/earthquake-insurance-california | G19: 46295 | H19: US | I19: Reference data (secondary source) | J19: Secondary - unverified | K19: 46295 | L19: HOA master policies also commonly exclude it (same source).
A20: Umbrella | B20: $1M personal umbrella annual cost | C20: $200-$500 typical; over $1,000 possible | D20: USD/year | E20: NerdWallet - Umbrella insurance guide | F20: https://www.nerdwallet.com/insurance/homeowners/learn/umbrella-insurance | G20: 46295 | H20: US | I20: Estimate | J20: Secondary - unverified | K20: 46295 | L20: Kiplinger/Trusted Choice: average about $380 for $1-2M.
A21: Umbrella | B21: Cost of each additional $1M | C21: $50-$150 | D21: USD/year | E21: Real Cost Report - Umbrella insurance cost 2026 | F21: https://www.realcostreport.com/insurance/home-insurance/umbrella-insurance-cost/ | G21: 46295 | H21: US | I21: Estimate | J21: Conflicting | K21: 46295 | L21: Real Cost Report says $50-$75; UseCalcPro says $75-$150.
A22: Umbrella | B22: Typical required underlying auto limits | C22: 250/500/100 | D22: BI per person / per accident / PD | E22: UseCalcPro - Umbrella quote calculator | F22: https://usecalcpro.com/finance/umbrella-insurance-quote-calculator | G22: 46295 | H22: US | I22: Reference data (secondary source) | J22: Secondary - unverified | K22: 46295 | L22: Kiplinger cites $250,000 auto and $300,000 home liability. One source says CA/NY/FL often require 500/500/100.
A23: Umbrella | B23: Typical required underlying home liability | C23: 300000 | D23: USD | E23: Kiplinger - How much umbrella insurance do I need | F23: https://www.kiplinger.com/personal-finance/insurance/umbrella-insurance/603237/how-much-umbrella-insurance-do-i-need | G23: 46295 | H23: US | I23: Reference data (secondary source) | J23: Secondary - unverified | K23: 46295
A24: Umbrella | B24: Extra cost to raise underlying auto limits | C24: $100-$200 | D24: USD/year | E24: Real Cost Report - Umbrella insurance cost 2026 | F24: https://www.realcostreport.com/insurance/home-insurance/umbrella-insurance-cost/ | G24: 46295 | H24: US | I24: Estimate | J24: Secondary - unverified | K24: 46295 | L24: Include in total-cost quote.

Sheet Price Benchmarks
A1: Line | B1: Metric | C1: Value ($/yr) | D1: Comparable Group | E1: Methodology / Definition | F1: Source | G1: Source URL | H1: Date Collected | I1: Geographic Scope | J1: Data Type | K1: Verification Status | L1: Last Updated | M1: Notes
A2: Auto | B2: National average | C2: 1820 | D2: Auto full coverage annual | E2: 35-yr-old, clean record, 12k miles, 100/300/100, $500 deductibles | F2: InsurTool - Average car insurance cost 2026 | G2: https://insurtool.com/tools/average-car-insurance-cost/ | H2: 46295 | I2: US | J2: Estimate | K2: Secondary - unverified | L2: 46295 | M2: Methodology not independently verified.
A3: Auto | B3: National average | C3: 2237 | D3: Auto full coverage annual | E3: Insurify, first half 2026 | F3: Insurify - Car insurance report (H1 2026) | G3: https://insurify.com/car-insurance/report/ | H3: 46295 | I3: US | J3: Estimate | K3: Secondary - unverified | L3: 46295 | M3: Insurify projects $2,242 by year-end.
A4: Auto | B4: National average | C4: 2496 | D4: Auto full coverage annual | E4: ValuePenguin 2026 ($208/month) | F4: ValuePenguin - State of Auto Insurance 2026 | G4: https://www.valuepenguin.com/state-of-auto-insurance-2026 | H4: 46295 | I4: US | J4: Estimate | K4: Secondary - unverified | L4: 46295 | M4: InsuredBetter reports the same figure.
A5: Auto | B5: National average | C5: 2670 | D5: Auto full coverage annual | E5: Cinco Auto Insurance ($223/month) | F5: Cinco Auto Insurance - Average cost | G5: https://cincoautoinsurance.com/auto-insurance/cost/ | H5: 46295 | I5: US | J5: Estimate | K5: Secondary - unverified | L5: 46295 | M5: Agency blog; lower reliability.
A6: Auto | B6: National average | C6: 2922 | D6: Auto full coverage annual | E6: Experian, Aug 2026 (marketplace policies) | F6: Experian - Average cost of car insurance | G6: https://www.experian.com/blogs/ask-experian/average-cost-car-insurance/ | H6: 46295 | I6: US | J6: Estimate | K6: Secondary - unverified | L6: 46295
A7: Auto | B7: National average | C7: 773 | D7: Auto minimum coverage annual | E7: Cinco Auto Insurance | F7: Cinco Auto Insurance - Average cost | G7: https://cincoautoinsurance.com/auto-insurance/cost/ | H7: 46295 | I7: US | J7: Estimate | K7: Secondary - unverified | L7: 46295
A8: Auto | B8: National average | C8: 912 | D8: Auto minimum coverage annual | E8: InsuredBetter / Trusted Choice ($76/month) | F8: InsuredBetter / Trusted Choice - Car insurance cost 2026 | G8: https://www.insuredbetter.com/car-insurance/compare-auto-coverage/rate-cost/ | H8: 46295 | I8: US | J8: Estimate | K8: Secondary - unverified | L8: 46295
A9: Auto | B9: National average | C9: 1580 | D9: Auto minimum coverage annual | E9: Experian, Aug 2026 | F9: Experian - Average cost of car insurance | G9: https://www.experian.com/blogs/ask-experian/average-cost-car-insurance/ | H9: 46295 | I9: US | J9: Estimate | K9: Secondary - unverified | L9: 46295
A10: Auto | B10: National average | C10: 2262 | D10: Auto - all coverage levels (not in spread) | E10: Experian overall average | F10: Experian - Average cost of car insurance | G10: https://www.experian.com/blogs/ask-experian/average-cost-car-insurance/ | H10: 46295 | I10: US | J10: Estimate | K10: Secondary - unverified | L10: 46295 | M10: Not comparable to full-coverage rows.
A11: Auto | B11: National average | C11: 2510 | D11: Auto - coverage level unspecified (not in spread) | E11: U.S. News, Aug 2026 | F11: U.S. News - Average cost of car insurance (Aug 2026) | G11: https://www.usnews.com/insurance/auto/average-cost-of-car-insurance | H11: 46295 | I11: US | J11: Estimate | K11: Secondary - unverified | L11: 46295 | M11: Coverage level unspecified.
A12: Home | B12: National average | C12: 2490 | D12: Home national average annual | E12: NerdWallet analysis of 100+ insurers | F12: NerdWallet - Average homeowners insurance cost | G12: https://www.nerdwallet.com/insurance/homeowners/learn/average-homeowners-insurance-cost | H12: 46295 | I12: US | J12: Estimate | K12: Secondary - unverified | L12: 46295
A13: Home | B13: National average | C13: 3012 | D13: Home national average annual | E13: Insurify, mid-2026 | F13: Insurify - Home insurance rates H1 2026 | G13: https://insurify.com/homeowners-insurance/insights/rates-increase-first-half-2026/ | H13: 46295 | I13: US | J13: Estimate | K13: Secondary - unverified | L13: 46295 | M13: Insurify projected $3,057 for 2026 in March.
A14: Home | B14: Florida average | C14: 8486 | D14: Home - state (not in spread) | E14: Insurify, H1 2026 (most expensive state) | F14: Insurify - Home insurance rates H1 2026 | G14: https://insurify.com/homeowners-insurance/insights/rates-increase-first-half-2026/ | H14: 46295 | I14: Florida | J14: Estimate | K14: Secondary - unverified | L14: 46295
A17: Spread summary (formulas)
A18: Group | B18: Low ($/yr) | C18: High ($/yr) | D18: High vs Low
A19: Auto full coverage annual | B19: =MIN(C2:C6) | C19: =MAX(C2:C6) | D19: =C19/B19-1
A20: Auto minimum coverage annual | B20: =MIN(C7:C9) | C20: =MAX(C7:C9) | D20: =C20/B20-1
A21: Home national average annual | B21: =MIN(C12:C13) | C21: =MAX(C12:C13) | D21: =C21/B21-1
A23: Note: ranges above are computed from the rows in the table; if you add or remove rows, update the range references. Do not show one national average as a verdict on a user's premium.

Sheet Regulatory Watch
A1: Item | B1: Jurisdiction | C1: Status (as reported) | D1: Why It Matters | E1: Source | F1: Source URL | G1: Date Collected | H1: Geographic Scope | I1: Data Type | J1: Verification Status | K1: Last Updated | L1: Notes
A2: NAIC AI Model Bulletin | B2: US states | C2: 24 states + DC adopted as of Apr 1, 2026; CA, CO, NY, TX use own frameworks | D2: Governs insurers' AI use; not brokers. Does not create new liability or a private right of action (per sources). | E2: Tech Savvy Insurance - States that adopted NAIC AI bulletin | F2: https://techsavvyinsurance.com/answers/which-states-adopted-naic-ai-model-bulletin/ | G2: 46295 | H2: US | I2: Reference data (secondary source) | J2: Secondary - unverified | K2: 46295 | L2: Relevant if you later sell tools to carriers.
A3: Colorado Regulation 10-1-1 | B3: Colorado | C3: Amended Oct 15, 2025; extends to private passenger auto from Jul 1, 2026 | D3: Governance for insurers using external consumer data and models. | E3: Meilynx - NAIC AI Model Bulletin explained | F3: https://www.meilynx.com/reference/naic-ai-model-bulletin | G3: 46295 | H3: Colorado | I3: Reference data (secondary source) | J3: Secondary - unverified | K3: 46295
A4: Federal AI preemption | B4: US | C4: Executive order created DOJ AI Litigation Task Force (Jan 10, 2026) to challenge state AI laws | D4: Could change state AI insurance rules. | E4: actuary.info - AI regulation in insurance 2026 | F4: https://actuary.info/insights/ai-regulation-insurance-naic-2026 | G4: 46295 | H4: US | I4: Reference data (secondary source) | J4: Secondary - unverified | K4: 46295 | L4: Situation still evolving.
A5: TCPA one-to-one consent rule | B5: US (federal) | C5: Vacated by 11th Circuit on Jan 24, 2025 | D5: State 'mini-TCPA' laws (FL, OK, WA, TX) still apply; many lead buyers still require seller-specific consent. | E5: Lead Distro AI - One-to-one consent 2026 | F5: https://www.leaddistro.ai/blog/one-to-one-consent | G5: 46295 | H5: US | I5: Reference data (secondary source) | J5: Secondary - unverified | K5: 46295 | L5: Build to one-to-one anyway; get counsel.
A6: TCPA penalties | B6: US (federal) | C6: $500-$1,500 per call reported | D6: - | E6: InsureLeads - TCPA/one-to-one status 2026 | F6: https://www.getinsureleads.com/blog/fcc-one-to-one-consent-rule-status-update-2026 | G6: 46295 | H6: US | I6: Estimate | J6: Secondary - unverified | K6: 46295 | L6: Lead-gen vendor source.
A7: NFIP authorization | B7: US (federal) | C7: Authorized through Dec 11, 2026 (extended from Sept 30, 2026) | D7: Next lapse risk is Dec 12, 2026 unless Congress acts. | E7: CRS Insight - What Happens If the NFIP Lapses? | F7: https://www.congress.gov/crs-product/IN10835 | G7: 46295 | H7: US | I7: Regulator-published | J7: Primary source | K7: 46295 | L7: CRS Insight and NAHB agree.
A8: California Sustainable Insurance Strategy | B8: California | C8: Catastrophe models and reinsurance costs allowed in rates if insurers commit to write 85% of statewide market share in wildfire-distressed areas; FAIR Plan 29.1% average increase approved effective Oct 15, 2026 (news reports) | D8: Availability drives whether a home comparison can show any quotes; FAIR Plan plus a DIC policy is a common outcome. | E8: CA Dept of Insurance - Sustainable Insurance Strategy updates | F8: https://www.insurance.ca.gov/01-consumers/180-climate-change/SustainableInsuranceStrategy.cfm | G8: 46295 | H8: California | I8: Regulator-published | J8: Secondary - unverified | K8: 46295 | L8: Regulator source for the strategy; FAIR Plan decision is from news reports.
A9: California 2026 home insurance laws | B9: California | C9: AB 1, AB 226, AB 888, SB 429, SB 495, SB 547 effective Jan 1, 2026 | D9: Changes discounts review, FAIR Plan financing, wildfire claims payouts and non-renewal protections. | E9: CDI press release - New laws take effect January 1, 2026 (Dec 30, 2025) | F9: https://www.insurance.ca.gov/0400-news/0100-press-releases/2025/release079-2025.cfm | G9: 46295 | H9: California | I9: Regulator-published | J9: Primary source | K9: 46295 | L9: From CDI press release.
A10: Florida PIP repeal attempts | B10: Florida | C10: SB 522 and HB 769 died in committee on Mar 13, 2026; PIP remains required; next regular session convenes Mar 2, 2027 (per law firms) | D10: A repeal would replace PIP with mandatory bodily injury liability (proposed 25/50); would change minimums and comparison logic. | E10: Viles & Beckman - Did Florida repeal no-fault? (Jul 2026) | F10: https://www.vilesandbeckman.com/blog/did-florida-repeal-no-fault-insurance-the-pip-myths-and-the-facts-for-2026/ | G10: 46295 | H10: Florida | I10: Reference data (secondary source) | J10: Secondary - unverified | K10: 46295 | L10: Verify bill status on flsenate.gov.
A11: Texas nonrenewal notice period | B11: Texas | C11: 60 days' notice if policy bought or renewed in 2024; 30 days for 2023 or earlier (TDI wording) | D11: Check whether the 60-day rule applies to all later policies. | E11: Texas Dept of Insurance - Auto insurance guide (CB020) | F11: https://www.tdi.texas.gov/pubs/consumer/cb020.html | G11: 46295 | H11: Texas | I11: Regulator-published | J11: Primary source | K11: 46295 | L11: TDI page wording is date-specific; ask TDI.
A12: Citizens flood requirement expands | B12: Florida | C12: All remaining Citizens wind policies must carry flood coverage from Jan 1, 2027 (per secondary sources) | D12: Affects Florida home comparisons: flood coverage becomes a condition of keeping the state-backed policy. | E12: Coverage Classroom - Citizens flood requirement phase-in | F12: https://coverageclassroom.com/learn/citizens-flood-insurance-requirement | G12: 46295 | H12: Florida | I12: Reference data (secondary source) | J12: Secondary - unverified | K12: 46295 | L12: Confirm on Citizens' site.
A13: Telematics privacy bills | B13: 5 states (incl. MD SB 984, NC) | C13: Introduced in 2025-2026 sessions | D13: Distinguishes opt-in programs from connected-car data sharing. | E13: InsureMojo - Telematics privacy bills 2026 | F13: https://www.insuremojo.com/telematics-insurance-data-privacy-bills-2026/ | G13: 46295 | H13: Multi-state | I13: Reference data (secondary source) | J13: Secondary - unverified | K13: 46295 | L13: Track bill status individually.
A14: Minimum liability limit increases | B14: CA, NC, UT, VA (2025); NJ (2026) | C14: See State Min Limits tab | D14: Limits change; keep versioned with effective dates. | E14: CarInsurance.com - Minimum liability by state (Apr 2026) | F14: https://www.carinsurance.com/Articles/minimum-liability-car-insurance-requirements-by-state.aspx | G14: 46295 | H14: Multi-state | I14: Reference data (secondary source) | J14: Secondary - unverified | K14: 46295 | L14: Virginia and NJ conflict; see Conflicts Log.
A15: Washington credit ban | B15: Washington | C15: Court struck down three-year ban in 2021 | D15: - | E15: MoneyGeek - Insurers that don't check credit | F15: https://www.moneygeek.com/insurance/auto/which-insurance-companies-dont-check-credit-score/ | G15: 46295 | H15: Washington | I15: Reference data (secondary source) | J15: Secondary - unverified | K15: 46295

Sheet Quote Source Options
A1: Option | B1: What it is | C1: Licensing / legal implication | D1: Data type you can show | E1: Evidence found | F1: Source URL | G1: Verification Status | H1: Open questions
A2: A. Become a licensed agency and integrate carriers directly | B2: Operate like The Zebra / Insurify: hold producer licenses, connect to carriers, show real-time quotes | C2: Agents and brokers must be state licensed (CDI). Needs licenses in each state, plus E&O insurance (my note) | D2: Actual carrier quotes | E2: The Zebra says it has in-house licensed agents and direct carrier partnerships; Insurify says it integrates with 120+ carriers and has an in-house agency | F2: https://www.thezebra.com/ | G2: Secondary - unverified | H2: Which states first? Carrier onboarding requirements and timelines?
A3: B. Partner with an existing licensed marketplace | B3: Send users to a licensed partner that returns real quotes; earn a referral fee | C3: Depends on the partner's license and your referral flow; needs counsel | D3: Partner-provided quotes | E3: Insurify says it earns a commission on purchases; The Zebra says it earns money from carriers | F3: https://insurify.com/car-insurance/ | G3: Secondary - unverified | H3: Do partners offer white-label or API access to a new site? Not found publicly.
A4: C. Lead-generation model | B4: Collect user details and hand them to agents or carriers; no live quotes | C4: Consent rules (TCPA, state laws); possible producer licensing questions | D4: No quotes; only referrals | E4: Compare.com describes EverQuote as lead-gen without real-time quotes | F4: https://www.compare.com/auto-insurance/compare-insurance-companies/best-car-insurance-comparison-sites | G4: Secondary - unverified | H4: Consent language; which states treat this as solicitation?
A5: D. Buy rate-filing data for estimates | B5: License ZIP-level rate filing data to show estimated ranges | C5: Data license terms; must label as Estimate, never as quote | D5: Estimates only | E5: The Zebra says its rating tool uses ZIP-level filings from Quadrant Information Services and S&P Global; Insurify also cites Quadrant | F5: https://www.thezebra.com/auto-insurance/ | G5: Secondary - unverified | H5: Pricing and public-display rights for this data not found.
A6: E. Education and tools only (recommended first) | B6: No quotes; explainers, calculators, checklists, questions to ask insurers | C6: Lowest licensing exposure, but still needs disclaimers and privacy compliance; confirm with counsel | D6: Educational content and user-entered numbers | E6: Consistent with CDI's own guide, which tells consumers to obtain written quotes from insurers | F6: https://www.insurance.ca.gov/01-consumers/105-type/95-guides/01-auto/auto101.cfm | G6: Primary source | H6: None blocking.
A8: I found no publicly documented, self-serve quote API for a new entrant. These integrations appear to be negotiated business partnerships (my inference).

Sheet Legal Review Checklist
A1: # | B1: Topic | C1: Question for insurance-regulatory counsel | D1: Why it matters (from the research) | E1: Priority | F1: Status
A2: 1 | B2: Licensing | C2: Does an education-and-calculator site that collects no contact details need any license in California or other states? | D2: Agents and brokers must be licensed (CDI); the line between education and solicitation varies by state | E2: High | F2: Open
A3: 2 | B3: Licensing | C3: If we later refer users to carriers or agents, what licenses are needed and may we receive referral fees? | D3: Referral or lead-gen revenue is the main planned business model | E3: High | F3: Open
A4: 3 | B4: Advertising | C4: What rules govern comparison claims, 'estimate' labels and any 'lower displayed premium' wording? | D4: Spec requires never presenting an estimate as a quote; states regulate insurance advertising | E4: High | F4: Open
A5: 4 | B5: Consent | C5: What consent language do we need for phone, text and email contact, given the vacated federal one-to-one rule and state mini-TCPA laws? | D5: Penalties can run $500-$1,500 per call; state laws (FL, OK, WA, TX) still apply | E5: High | F5: Open
A6: 5 | B6: Privacy | C6: What CCPA/CPRA and other state privacy duties apply to VINs, driver data, and uploaded policy documents? Retention and breach obligations? | D6: Site will hold sensitive personal and financial data | E6: High | F6: Open
A7: 6 | B7: AI / advice | C7: Does the policy-document analyzer or 'coverage gap' output risk being treated as insurance advice? What disclaimers and human-review steps are appropriate? | D7: No case law found on consumer comparison-site AI; hallucination risks in document extraction | E7: High | F7: Open
A8: 7 | B8: AI regulation | C8: Do the NAIC AI bulletin or Colorado Reg 10-1-1 apply to us if we sell tools to carriers or agents? | D8: Bulletin governs insurers; Colorado rule extends to private passenger auto from Jul 1, 2026 | E8: Medium | F8: Open
A9: 8 | B9: Disclosure | C9: How must we disclose carrier payments and ensure ordering is not influenced by them? | D9: Neutral labels and commercial-relationship disclosure are core to the concept | E9: High | F9: Open
A10: 9 | B10: Third-party data | C10: May we display NAIC materials and licensed rate-filing data publicly, and on what terms? | D10: NAIC tool has copyright terms; rate data comes from commercial providers | E10: Medium | F10: Open
A11: 10 | B11: Telematics content | C11: Are there restrictions on how we describe telematics programs, especially in California? | D11: CA regulation limits devices to mileage collection; state privacy bills pending | E11: Medium | F11: Open
A12: 11 | B12: California rules | C12: Please confirm our reading of 10 CCR 2632.5 (approved rating factors) and Advisory Notice 2005-02 (no paid-in-full discount; six-month premium equals half of annual). | D12: We derived 'credit, gender and age not permitted' from the regulation text | E12: High | F12: Open
A13: 12 | B13: Terms | C13: Terms of service, limitation of liability, arbitration and E&O insurance for the site? | D13: Standard protections for a consumer advice product | E13: Medium | F13: Open
... A21: 20 | B21: Accessibility | C21: What ADA/WCAG obligations apply? | D21: Spec requires an accessible site | E21: Low | F21: Open
A23: This is a list of questions to bring to counsel. It is not legal advice and does not replace a lawyer's review.

Sheet Refresh Schedule
A1: Data Set | B1: Primary Source to Check | C1: Owner (assign) | D1: Review Every (days) | E1: Trigger Events | F1: Last Verified | G1: Next Review Due | H1: Status
A2: California auto - minimum limits and coverages | B2: CA DMV and CDI pages; Insurance Code 11580.1 | D2: 90 | E2: New legislation; Jan 1 effective dates; CDI bulletins | F2: 46295 | G2: =IF(F2="","Verify now",F2+D2) | H2: =IF(F2="","Never verified",IF(TODAY()>F2+D2,"Overdue","OK"))
A3: California auto - rating factors and discounts | B3: 10 CCR 2632.5, 2632.12; Ins. Code 1861.02, 11628.3; CDI advisory notices | D3: 180 | E3: CDI regulation changes; new advisory notices | F3: 46295 | G3: =IF(F3="","Verify now",F3+D3) | H3: =IF(F3="","Never verified",IF(TODAY()>F3+D3,"Overdue","OK"))
A4: California home - coverage rules and consumer rights | B4: CDI Form 401; CDI earthquake and flood pages; Insurance Code | D4: 180 | E4: New CDI guide revision; new legislation (Jan 1 effective dates) | F4: 46295 | G4: =IF(F4="","Verify now",F4+D4) | H4: =IF(F4="","Never verified",IF(TODAY()>F4+D4,"Overdue","OK"))
A5: California home - FAIR Plan, SIS, wildfire discounts | B5: CDI press releases and orders; FAIR Plan site; 10 CCR 2644.9 | D5: 30 | E5: FAIR Plan rate orders; Safer from Wildfires updates under AB 1; market exits or entries | F5: 46295 | G5: =IF(F5="","Verify now",F5+D5) | H5: =IF(F5="","Never verified",IF(TODAY()>F5+D5,"Overdue","OK"))
A6: Texas, Florida, New York - auto rules | B6: TDI; FLHSMV and Florida Statutes; NY DFS and Insurance Law | D6: 90 | E6: Legislative sessions (FL Mar 2027); regulator guide revisions | F6: 46295 | G6: =IF(F6="","Verify now",F6+D6) | H6: =IF(F6="","Never verified",IF(TODAY()>F6+D6,"Overdue","OK"))
A7: Texas and Florida home rules | B7: TDI; TWIA; Florida DFS and OIR; Citizens; Florida Statutes 627.351, 627.701 | D7: 30 | E7: Citizens flood phase-in; hurricane season; TWIA limit changes | F7: 46295 | G7: =IF(F7="","Verify now",F7+D7) | H7: =IF(F7="","Never verified",IF(TODAY()>F7+D7,"Overdue","OK"))
A8: Other states - minimum liability limits | B8: Each state DOI / DMV site | D8: 90 | E8: Legislative sessions; Jan 1 and Jul 1 effective dates | G8: =IF(F8="","Verify now",F8+D8) | H8: =IF(F8="","Never verified",IF(TODAY()>F8+D8,"Overdue","OK"))
A9: Rating factor rules by state | B9: State statutes and DOI pages | D9: 180 | E9: New bills on credit, gender or age use | G9: =IF(F9="","Verify now",F9+D9) | H9: =IF(F9="","Never verified",IF(TODAY()>F9+D9,"Overdue","OK"))
A10: Discount availability by state | B10: State DOI pages; carrier filings | D10: 180 | E10: Carrier filing changes | G10: =IF(F10="","Verify now",F10+D10) | H10: =IF(F10="","Never verified",IF(TODAY()>F10+D10,"Overdue","OK"))
A11: Telematics programs | B11: Carrier sites and state filings | D11: 90 | E11: New program launches; privacy bills | G11: =IF(F11="","Verify now",F11+D11) | H11: =IF(F11="","Never verified",IF(TODAY()>F11+D11,"Overdue","OK"))
A12: NFIP authorization status | B12: FEMA; Congress.gov | D12: 30 | E12: Funding deadlines; shutdown risk (next: Dec 11, 2026) | F12: 46295 | G12: =IF(F12="","Verify now",F12+D12) | H12: =IF(F12="","Never verified",IF(TODAY()>F12+D12,"Overdue","OK"))
A13: CEA earthquake terms | B13: earthquakeauthority.com | D13: 180 | E13: CEA rate or product changes | G13: =IF(F13="","Verify now",F13+D13) | H13: =IF(F13="","Never verified",IF(TODAY()>F13+D13,"Overdue","OK"))
A14: Price benchmarks | B14: Source publishers; NAIC database reports | D14: 90 | E14: New annual reports; rate filings | G14: =IF(F14="","Verify now",F14+D14) | H14: =IF(F14="","Never verified",IF(TODAY()>F14+D14,"Overdue","OK"))
A15: Regulatory Watch items | B15: NAIC, state DOIs, Congress.gov | D15: 30 | E15: Any new bulletin or law | G15: =IF(F15="","Verify now",F15+D15) | H15: =IF(F15="","Never verified",IF(TODAY()>F15+D15,"Overdue","OK"))
A16: Conflicts Log | B16: Primary sources listed in the log | D16: 30 | E16: When a conflict is resolved | G16: =IF(F16="","Verify now",F16+D16) | H16: =IF(F16="","Never verified",IF(TODAY()>F16+D16,"Overdue","OK"))
A17: Source URLs (link check) | B17: Sources tab | D17: 90 | E17: Broken links | G17: =IF(F17="","Verify now",F17+D17) | H17: =IF(F17="","Never verified",IF(TODAY()>F17+D17,"Overdue","OK"))
A18: Disclosures and legal language | B18: Counsel | D18: 180 | E18: Law changes; new business model | G18: =IF(F18="","Verify now",F18+D18) | H18: =IF(F18="","Never verified",IF(TODAY()>F18+D18,"Overdue","OK"))
A20: Yellow cells: assign an owner. Blue cells: edit the review interval and Last Verified date after each check. Next Review Due and Status are formulas. Review intervals are suggestions, not researched requirements.

Sheet Conflicts Log
A1: Item | B1: Source A says | C1: Source B says | D1: What to verify | E1: Where to verify | F1: Resolved? | G1: Resolution
A2: Virginia minimum liability | B2: 50/100/25 (CarInsurance.com, LiabilityVsFullCoverage) | C2: 30/60/20 (Coverage Criteria) | D2: Current statutory minimum and effective date | E2: VA DMV / VA Bureau of Insurance | F2: Yes | G2: Not actually conflicting. VA DMV confirms current minimums are 50/100/25, effective Jan 1, 2025. The 30/60/20 figure (Coverage Criteria) was the prior minimum, in effect Jan 1, 2022 - Dec 31, 2024.
A3: Hawaii minimum liability | B3: 40/80/20 in 2026 (Beach Insurance) | C3: 20/40/10 (implied prior limit) | D3: Whether the 2026 increase is enacted | E3: Hawaii Insurance Division | F3: No
A4: New Jersey minimum liability | B4: 35/70/25 effective Jan 1, 2026 (3 sources) | C4: Older two-tier structure listed (Coverage Criteria, Feb 2026) | D4: Current Basic and Standard policy limits | E4: NJ Dept of Banking and Insurance | F4: No
A5: Number of PIP-required states | B5: 13 (CarInsurance.com) | C5: 14 (Coverage Criteria) or 16 + DC (ChooseFI) | D5: Which states require PIP | E5: State statutes / NAIC | F5: No
A6: Michigan credit use for auto | B6: Banned (most sources) | C6: Allowed with limitations (The Zebra); limited not banned (Firstcard) | D6: Current Insurance Code language | E6: Michigan DIFS | F6: No
A7: California allowed rating factors | B7: ZIP and marital status allowed with limits (The Zebra) | C7: Limited to driving record, mileage, experience (Firstcard) | D7: Prop 103 regulations | E7: CA Dept of Insurance | F7: Yes | G7: Resolved from primary text (10 CCR 2632.5): three mandatory factors plus an approved optional list that includes ZIP-based claims bands and marital status. Neither source was fully right.
A8: Progressive / State Farm telematics surcharge | B8: Progressive can surcharge in some states; State Farm says no surcharge | C8: Insurify: some programs can raise rates | D8: State-by-state filing terms | E8: Carrier filings / state DOI | F8: No
A9: Share of NFIP claims outside high-risk zones | B9: About 20% (Cover Forge) | C9: Over 40% (Atesa) | D9: FEMA claims data | E9: FEMA / FloodSmart | F9: No
A10: NFIP authorization after Sept 30, 2026 | B10: Expires Sept 30, 2026 (FEMA, NAR) | C10: CRS item references Dec 11, 2026 | D10: Whether an extension passed | E10: FEMA, Congress.gov | F10: Yes | G10: Resolved: authorized through Dec 11, 2026 (CRS; NAHB).
A11: U.S. auto average premium | B11: $1,820 (InsurTool) full coverage | C11: $2,922 (Experian) full coverage | D11: Methodology of each; use ranges, not one number | E11: Source methodologies / NAIC | F11: No
A12: Umbrella cost per additional $1M | B12: $50-$75 (Real Cost Report) | C12: $75-$150 (UseCalcPro) | D12: Carrier rate quotes | E12: Carrier quotes | F12: No
A13: Senior driver course discount mandates | B13: 'Most states' (Insurance.com) | C13: 'Many states' (SafeDriver.com) | D13: Which states mandate it and age thresholds | E13: State DOIs | F13: No
A14: Florida Citizens policy count | B14: Over 1.2 million (Louis Law Group, Apr 2026) | C14: Under 400,000 (Lewis Insurance, Jan 2026) | D14: Current Citizens policy count and date | E14: Citizens Property Insurance Corporation; OIR | F14: No
A15: Texas TWIA dwelling limit | B15: About $1.8 million (agency blogs) | C15: Commissioner disapproved a proposed increase to $1,809,000 (TDI Order 2025-9540, per an agency blog) | D15: Current TWIA maximum limits | E15: TWIA; TDI order | F15: No
A16: Florida auto cancellation / nonrenewal notice rules | B16: 627.728: 45 days for cancellation (10 for nonpayment); appeal right to OIR | C16: 626.9201: 45 days for nonrenewal, but it sits in the surplus lines part of the code | D16: Which section governs nonrenewal of private passenger auto in Florida | E16: Florida Statutes 627.728 and related; OIR / DFS | F16: No
A17: Texas PIP minimum amount | B17: TDI: PIP included unless rejected; amount not stated | C17: Law-firm blog: insurers must offer $2,500 PIP | D17: Statutory PIP amount | E17: Texas Insurance Code 1952 subchapter D | F17: No
A18: California homeowners credit use | B18: Experian (2025): CA insurers do not use credit for home rates | C18: Older reports: some insurers used credit in underwriting; no explicit statute found | D18: Whether credit may be used in CA homeowners underwriting or rating | E18: CDI; Insurance Code; CDI homeowners rate filing rules | F18: No
A19: Safer from Wildfires legal citation | B19: Insurance Code 2644.9 (several secondary sites) | C19: Title 10 California Code of Regulations section 2644.9 (CDI framing; RFF paper) | D19: Correct citation | E19: CDI regulation text | F19: Yes | G19: It is a Title 10 regulation (10 CCR 2644.9), not an Insurance Code section. Use the regulation citation.
A20: California FAIR Plan policy count | B20: 668,600 at end-2025 (InsuranceNewsNet) | C20: About 697,000 in June 2026 (CalMatters); 550,000+ (Coverage Cat, looks stale) | D20: Current policy count and date | E20: California FAIR Plan / CDI data | F20: No
A21: California cash deposit / surety bond amount | B21: $35,000 (CDI Form 101, rev. Feb 5, 2025) | C21: $75,000 (DMV page, modified Jul 10, 2025) | D21: Current statutory amount | E21: DMV Insurance Unit; Vehicle Code financial responsibility sections | F21: Yes | G21: Resolved: $75,000 under SB 1107 and the DMV page; CDI Form 101 is out of date.

Sheet Sources
A1: Source | B1: Publisher Type | C1: URL | D1: Reliability / Commercial Note | E1: Date Accessed
A2: GEICO - Defensive driving discounts by state | B2: Carrier-published | C2: https://www.geico.com/save/discounts/defensive-driver-discounts/ | D2: Carrier's own statement; applies to GEICO only. | E2: 46295
A3: State Farm - Auto insurance discounts | B3: Carrier-published | C3: https://www.statefarm.com/insurance/auto/discounts | D3: States that discounts vary by state. | E3: 46295
A4: Insurify - Car insurance report (H1 2026) | B4: Comparison marketplace (earns referral fees) | C4: https://insurify.com/car-insurance/report/ | D4: Comparison marketplace data. | E4: 46295
A5: Insurify - Home insurance rates H1 2026 | B5: Comparison marketplace (earns referral fees) | C5: https://insurify.com/homeowners-insurance/insights/rates-increase-first-half-2026/ | D5: Comparison marketplace data. | E5: 46295
A6: Insurify - Telematics car insurance programs | B6: Comparison marketplace (earns referral fees) | C6: https://insurify.com/car-insurance/coverage/telematics/ | D6: Comparison marketplace. | E6: 46295
A7: The Zebra - Car insurance rating factors by state | B7: Comparison marketplace (earns referral fees) | C7: https://www.thezebra.com/resources/research/car-insurance-rating-factors-by-state/ | D7: Dated Oct 2025; verify against state law. | E7: 46295
A8: AutoInsurance.org - Requirements by state | B8: Publisher / media | C8: https://www.autoinsurance.org/car-insurance-requirements/ | E8: 46295
A9: Bankrate - Are telematics programs worth the discount | B9: Publisher / media | C9: https://www.bankrate.com/insurance/car/are-telematics-programs-worth-the-discount/ | E9: 46295
A10: CNBC - Insurance rates based on credit history draw scrutiny | B10: Publisher / media | C10: https://www.cnbc.com/2026/04/26/insurance-rates-credit-history.html | E10: 46295
A11: CNBC Select - State minimum requirements | B11: Publisher / media | C11: https://www.cnbc.com/select/state-minimum-car-insurance-requirements/ | D11: Dated Dec 2025. | E11: 46295
A12: CarInsurance.com - Minimum liability by state (Apr 2026) | B12: Publisher / media | C12: https://www.carinsurance.com/Articles/minimum-liability-car-insurance-requirements-by-state.aspx | E12: 46295
A13: Experian - Average cost of car insurance | B13: Publisher / media | C13: https://www.experian.com/blogs/ask-experian/average-cost-car-insurance/ | D13: Based on policies sold through Experian's marketplace. | E13: 46295
A14: Experian - States that restrict credit-based insurance scores | B14: Publisher / media | C14: https://www.experian.com/blogs/ask-experian/which-states-prohibit-or-restrict-the-use-of-credit-based-insurance-scores/ | D14: Dated Mar 2025. | E14: 46295
A15: Insurance.com - Auto insurance discounts guide | B15: Publisher / media | C15: https://www.insurance.com/auto-insurance/car-insurance-discounts.html | E15: 46295
A16: InsuranceNewsNet - FAIR Plan rates going up 29.1% (May 2026) | B16: Publisher / media | C16: https://insurancenewsnet.com/oarticle/california-fair-plan-rates-going-up-29-1-in-late-2026 | D16: News report. | E16: 46295
A17: KQED - FAIR Plan announces 29.1% rate hike (Aug 2026) | B17: Publisher / media | C17: https://www.kqed.org/news/12094860/california-fair-plan-announces-29-1-rate-hike-for-homeowners-this-fall | D17: News report; not the CDI decision document. | E17: 46295
A18: Kiplinger - How much umbrella insurance do I need | B18: Publisher / media | C18: https://www.kiplinger.com/personal-finance/insurance/umbrella-insurance/603237/how-much-umbrella-insurance-do-i-need | D18: Cites Trusted Choice. | E18: 46295
A19: MoneyGeek - Defensive driver discounts | B19: Publisher / media | C19: https://www.moneygeek.com/insurance/auto/defensive-driver-courses/ | E19: 46295
A20: MoneyGeek - Insurers that don't check credit | B20: Publisher / media | C20: https://www.moneygeek.com/insurance/auto/which-insurance-companies-dont-check-credit-score/ | D20: Notes Washington credit ban struck down in 2021. | E20: 46295
A21: NerdWallet - Average homeowners insurance cost | B21: Publisher / media | C21: https://www.nerdwallet.com/insurance/homeowners/learn/average-homeowners-insurance-cost | D21: Analysis of 100+ insurers' pricing data. | E21: 46295
A22: NerdWallet - Umbrella insurance guide | B22: Publisher / media | C22: https://www.nerdwallet.com/insurance/homeowners/learn/umbrella-insurance | E22: 46295
A23: Newsweek - Where your credit score can/can't raise insurance costs | B23: Publisher / media | C23: https://www.newsweek.com/where-your-credit-score-can-cant-raise-insurance-costs-11885672 | E23: 46295
A24: Resources for the Future - Insurance discounts for wildfire mitigation (WP 25-30) | B24: Publisher / media | C24: https://media.rff.org/documents/WP_25-30.pdf | D24: Research paper describing 10 CCR 2644.9 disclosure and appeal rights. | E24: 46295
A25: U.S. News - Average cost of car insurance (Aug 2026) | B25: Publisher / media | C25: https://www.usnews.com/insurance/auto/average-cost-of-car-insurance | D25: Coverage level not specified in snippet. | E25: 46295
A26: United Policyholders - Should states ban credit-based insurance scoring? (2013) | B26: Publisher / media | C26: https://uphelp.org/should-states-ban-credit-based-insurance-scoring/ | D26: Quotes a CDI-side view that homeowners rate filings depending on credit are not approved. Old. | E26: 46295
A27: ValuePenguin - State of Auto Insurance 2026 | B27: Publisher / media | C27: https://www.valuepenguin.com/state-of-auto-insurance-2026 | E27: 46295
A28: 10 CCR section 2632.12 - Good Driver Discount (text via Cornell LII) | B28: Regulator / government | C28: https://www.law.cornell.edu/regulations/california/10-CCR-2632.12 | D28: Regulation text; confirm against official source. | E28: 46295
A29: 10 CCR section 2632.5 - Rating Factors (text via Cornell LII) | B29: Regulator / government | C29: https://www.law.cornell.edu/regulations/california/10-CCR-2632.5 | D29: Regulation text; confirm against the official California Code of Regulations. | E29: 46295
A30: CA DMV - Auto Insurance Requirements (modified Jul 10, 2025) | B30: Regulator / government | C30: https://www.dmv.ca.gov/portal/vehicle-registration/insurance-requirements/ | D30: Primary source; cites Insurance Code section 11580.1(b). | E30: 46295
A31: CA Dept of Insurance - Earthquake Insurance | B31: Regulator / government | C31: https://www.insurance.ca.gov/01-consumers/105-type/95-guides/03-res/eq-ins.cfm | D31: Regulator page; primary source. | E31: 46295
A32: CA Dept of Insurance - Flood Insurance Resources | B32: Regulator / government | C32: https://www.insurance.ca.gov/01-consumers/140-catastrophes/FloodFacts.cfm | D32: Regulator page; says CDI does not regulate the NFIP. | E32: 46295
A33: CA Dept of Insurance - Homeowners Insurance flyer (Dec 2024) | B33: Regulator / government | C33: https://www.insurance.ca.gov/01-consumers/105-type/95-guides/upload/Homeowners-Insurance-Updated-121924.pdf | D33: Regulator flyer; primary source. | E33: 46295
A34: CA Dept of Insurance - Introduction to Auto Insurance (Form 101, rev. Feb 5, 2025) | B34: Regulator / government | C34: https://www.insurance.ca.gov/01-consumers/105-type/95-guides/01-auto/auto101.cfm | D34: Regulator consumer guide; primary source. Its $35,000 deposit/bond figure conflicts with DMV's $75,000. | E34: 46295
A35: CA Dept of Insurance - Low Cost Auto consumer alert (Jul 23, 2024) | B35: Regulator / government | C35: https://www.insurance.ca.gov/0400-news/0102-alerts/2024/California-s-Low-Cost-Auto-Insurance.cfm | D35: Confirms SB 1107 limit increase beginning 2025; CLCA limits unchanged. | E35: 46295
A36: CA Dept of Insurance - Residential Insurance: Homeowners and Renters (Form 401, rev. Jan 2026) | B36: Regulator / government | C36: https://www.insurance.ca.gov/01-consumers/105-type/95-guides/03-res/res-ins-guide.cfm | D36: Regulator consumer guide; primary source. | E36: 46295
A37: CA Dept of Insurance - Safer from Wildfires | B37: Regulator / government | C37: https://www.insurance.ca.gov/01-consumers/200-wrr/Safer-from-Wildfires.cfm | D37: Regulator page; links to the full regulation text. | E37: 46295
A38: CA Dept of Insurance - Sustainable Insurance Strategy updates | B38: Regulator / government | C38: https://www.insurance.ca.gov/01-consumers/180-climate-change/SustainableInsuranceStrategy.cfm | D38: Regulator page on the 85 percent commitment. | E38: 46295
A39: CA Insurance Code section 10083 - Earthquake offer timing (Justia) | B39: Regulator / government | C39: https://law.justia.com/codes/california/code-ins/division-2/part-1/chapter-8-5/section-10083/ | D39: Statute text via Justia. | E39: 46295
... A78: InsurTool - Average car insurance cost 2026 | B78: Vendor / agency blog | C78: https://insurtool.com/tools/average-car-insurance-cost/ | D78: Baseline: 35-yr-old, clean record, 12k miles, 100/300/100 with $500 deductibles. Methodology not independently verified. | E78: 46295
A79: Insurance Geek - Minimum limits by state (Apr 2026) | B79: Vendor / agency blog | C79: https://www.insurancegeek.com/auto-insurance/state-minimum-car-insurance-limits/ | E79: 46295
A80: InsureLeads - TCPA/one-to-one status 2026 | B80: Vendor / agency blog | C80: https://www.getinsureleads.com/blog/fcc-one-to-one-consent-rule-status-update-2026 | D80: Lead-gen vendor. | E80: 46295
A81: InsureMojo - Telematics discount programs compared | B81: Vendor / agency blog | C81: https://www.insuremojo.com/telematics-insurance-discount-programs/ | E81: 46295
A82: InsureMojo - Telematics privacy bills 2026 | B82: Vendor / agency blog | C82: https://www.insuremojo.com/telematics-insurance-data-privacy-bills-2026/ | E82: 46295
A83: InsuredBetter / Trusted Choice - Car insurance cost 2026 | B83: Vendor / agency blog | C83: https://www.insuredbetter.com/car-insurance/compare-auto-coverage/rate-cost/ | E83: 46295
A84: Latent Insurance - TWIA coverage, limits and cost (Aug 2026) | B84: Vendor / agency blog | C84: https://www.latentinsure.com/texas-homeowners-insurance/twia | D84: Agency blog; cites TDI Order 2025-9540. | E84: 46295
A85: Lead Distro AI - One-to-one consent 2026 | B85: Vendor / agency blog | C85: https://www.leaddistro.ai/blog/one-to-one-consent | D85: Reports rule vacated Jan 24, 2025. | E85: 46295
A86: Lenders Network - Flood insurance mortgage requirements 2026 | B86: Vendor / agency blog | C86: https://thelendersnetwork.com/flood-insurance-mortgage-requirements/ | E86: 46295
A87: Meilynx - NAIC AI Model Bulletin explained | B87: Vendor / agency blog | C87: https://www.meilynx.com/reference/naic-ai-model-bulletin | D87: Includes Colorado Reg 10-1-1 dates. | E87: 46295
A88: QuoteYeti - Telematics tradeoffs | B88: Vendor / agency blog | C88: https://www.quoteyeti.com/blog/telematics-tradeoffs/ | E88: 46295
A89: Real Cost Report - Umbrella insurance cost 2026 | B89: Vendor / agency blog | C89: https://www.realcostreport.com/insurance/home-insurance/umbrella-insurance-cost/ | D89: Cites III/IRMI; treat as directional. | E89: 46295
A90: SafeDriver.com - Defensive driving discount 2026 | B90: Vendor / agency blog | C90: https://www.safedriver.com/news/defensive-driving-for-insurance-discount-2026-how-much-you-can-really-save | D90: Course provider; commercial interest. | E90: 46295
A91: Tech Savvy Insurance - States that adopted NAIC AI bulletin | B91: Vendor / agency blog | C91: https://techsavvyinsurance.com/answers/which-states-adopted-naic-ai-model-bulletin/ | D91: Cites NAIC map as of Apr 1, 2026. | E91: 46295
A92: UseCalcPro - Umbrella quote calculator | B92: Vendor / agency blog | C92: https://usecalcpro.com/finance/umbrella-insurance-quote-calculator | D92: Calculator site; low reliability. | E92: 46295
A93: Viles & Beckman - Did Florida repeal no-fault? (Jul 2026) | B93: Vendor / agency blog | C93: https://www.vilesandbeckman.com/blog/did-florida-repeal-no-fault-insurance-the-pip-myths-and-the-facts-for-2026/ | D93: Law firm blog; several firms agree. Verify on flsenate.gov. | E93: 46295
A94: WalletGrower - Flood insurance 2026 | B94: Vendor / agency blog | C94: https://walletgrower.com/insurance/homeowners-insurance/flood-insurance | D94: Contains affiliate links; treat private-vs-NFIP savings claims cautiously. | E94: 46295
A95: actuary.info - AI regulation in insurance 2026 | B95: Vendor / agency blog | C95: https://actuary.info/insights/ai-regulation-insurance-naic-2026 | D95: Federal preemption discussion. | E95: 46295
A96: NY Dept of Financial Services - Homeowners Insurance: Basic Coverage and Adding Coverage | B96: Regulator-published | C96: https://www.dfs.ny.gov/consumers/help_for_homeowners/insurance/basic_coverage | D96: NY DFS consumer guide page. | E96: 46296
A97: NY Dept of Financial Services - Homeowners Insurance: Problems Obtaining Insurance (NYPIUA) | B97: Regulator-published | C97: https://www.dfs.ny.gov/consumers/help_for_homeowners/insurance/problems_obtaining_insurance | D97: NY DFS consumer guide page describing NYPIUA, the state residual-market insurer. | E97: 46296
A98: NY Dept of Financial Services - Ways to Save on Homeowners Insurance | B98: Regulator-published | C98: https://www.dfs.ny.gov/system/files/documents/2026/02/Ways-to-Save-Homeowners-Insurance.pdf | D98: NY DFS consumer brochure (PDF). | E98: 46296
A99: NY Dept of Financial Services - Homeowners Insurance: Cancellations and Non-Renewals | B99: Regulator-published | C99: https://www.dfs.ny.gov/consumers/help_for_homeowners/insurance/cancellations_and_nonrenewals | D99: NY DFS consumer guide page; cites 'present law in New York State' and 'the Insurance Law' without a specific section number. | E99: 46296
A100: Illinois Dept of Insurance - Auto Insurance Shopping Guide | B100: Regulator-published | C100: https://idoi.illinois.gov/consumers/consumerinsurance/auto-insurance-shopping-guide.html | D100: IDOI consumer guide page. | E100: 46296
... A114: Virginia Property Insurance Association (VPIA) - Frequently Asked Questions | B114: Regulator-published | C114: https://www.vpia.com/frequently-asked-questions/ | D114: Official site of the plan's own administrator (Virginia's FAIR Plan). | E114: 46296

Sheet NY Home Verified
A1: Topic | B1: Fact | C1: Value | D1: Legal Citation | E1: Source | F1: Source URL | G1: Date Collected | H1: Geographic Scope | I1: Data Type | J1: Verification Status | K1: Last Updated | L1: Notes
A2: Coverage | B2: Other structures (garages, sheds) | C2: Typically 10% of the dwelling coverage limit under a Special Form Policy | D2: DFS homeowners guide | E2: NY Dept of Financial Services - Homeowners Insurance: Basic Coverage and Adding Coverage | F2: https://www.dfs.ny.gov/consumers/help_for_homeowners/insurance/basic_coverage | G2: 46296 | H2: New York | I2: Regulator-published | J2: Primary source | K2: 46296
A3: Coverage | B3: Personal property on premises | C3: Typically 50% of the dwelling coverage limit | D3: DFS homeowners guide | E3: NY Dept of Financial Services - Homeowners Insurance: Basic Coverage and Adding Coverage | F3: https://www.dfs.ny.gov/consumers/help_for_homeowners/insurance/basic_coverage | G3: 46296 | H3: New York | I3: Regulator-published | J3: Primary source | K3: 46296
A4: Coverage | B4: Personal property off premises | C4: Typically 10% of the dwelling coverage limit | D4: DFS homeowners guide | E4: NY Dept of Financial Services - Homeowners Insurance: Basic Coverage and Adding Coverage | F4: https://www.dfs.ny.gov/consumers/help_for_homeowners/insurance/basic_coverage | G4: 46296 | H4: New York | I4: Regulator-published | J4: Primary source | K4: 46296
A5: Coverage | B5: Additional living expenses (loss of use) | C5: Typically 20% of the dwelling coverage limit | D5: DFS homeowners guide | E5: NY Dept of Financial Services - Homeowners Insurance: Basic Coverage and Adding Coverage | F5: https://www.dfs.ny.gov/consumers/help_for_homeowners/insurance/basic_coverage | G5: 46296 | H5: New York | I5: Regulator-published | J5: Primary source | K5: 46296
A6: Coverage | B6: Special limits on specific property | C6: Typical per-loss maximums under a standard policy: money/bullion $200; securities/deeds/letters of credit $1,500; watercraft (incl. trailers) $1,500; jewelry/watches/furs theft $1,500; silverware/goldware theft $2,500; firearms theft $2,500; business property on premises $2,500, away from premises $500; electronic apparatus in motor vehicles $1,500 | D6: DFS homeowners guide | E6: NY Dept of Financial Services - Homeowners Insurance: Basic Coverage and Adding Coverage | F6: https://www.dfs.ny.gov/consumers/help_for_homeowners/insurance/basic_coverage | G6: 46296 | H6: New York | I6: Regulator-published | J6: Primary source | K6: 46296
A7: Liability | B7: Typical liability and medical payments limits | C7: Personal liability limits of $25,000 per occurrence and medical payments limits of $1,000 per person are typical; guest medical expense coverage is generally up to $500 or $1,000 | D7: DFS homeowners guide | E7: NY Dept of Financial Services - Homeowners Insurance: Basic Coverage and Adding Coverage | F7: https://www.dfs.ny.gov/consumers/help_for_homeowners/insurance/basic_coverage | G7: 46296 | H7: New York | I7: Regulator-published | J7: Primary source | K7: 46296
A8: Deductibles | B8: Standard deductible | C8: Standard deductibles typically start at $250, with options for $500 and $1,000 | D8: DFS homeowners guide | E8: NY Dept of Financial Services - Homeowners Insurance: Basic Coverage and Adding Coverage | F8: https://www.dfs.ny.gov/consumers/help_for_homeowners/insurance/basic_coverage | G8: 46296 | H8: New York | I8: Regulator-published | J8: Primary source | K8: 46296
A9: Deductibles | B9: Windstorm/hurricane deductible | C9: Windstorm and hurricane deductibles commonly range from 1% to 5% of the dwelling value or insured amount | D9: DFS homeowners guide | E9: NY Dept of Financial Services - Homeowners Insurance: Basic Coverage and Adding Coverage | F9: https://www.dfs.ny.gov/consumers/help_for_homeowners/insurance/basic_coverage | G9: 46296 | H9: New York | I9: Regulator-published | J9: Primary source | K9: 46296
A10: Coverage | B10: Flood exclusion | C10: Flood and mudslide losses are not provided in standard homeowners policies | D10: DFS homeowners guide | E10: NY Dept of Financial Services - Homeowners Insurance: Basic Coverage and Adding Coverage | F10: https://www.dfs.ny.gov/consumers/help_for_homeowners/insurance/basic_coverage | G10: 46296 | H10: New York | I10: Regulator-published | J10: Primary source | K10: 46296
A11: Coverage | B11: Earthquake exclusion | C11: Earthquakes are not covered under standard homeowners policies | D11: DFS homeowners guide | E11: NY Dept of Financial Services - Homeowners Insurance: Basic Coverage and Adding Coverage | F11: https://www.dfs.ny.gov/consumers/help_for_homeowners/insurance/basic_coverage | G11: 46296 | H11: New York | I11: Regulator-published | J11: Primary source | K11: 46296
A12: NYPIUA | B12: What it is | C12: New York's residual-market insurer for homeowners who cannot obtain coverage in the voluntary market | D12: DFS homeowners guide (NYPIUA) | E12: NY Dept of Financial Services - Homeowners Insurance: Problems Obtaining Insurance (NYPIUA) | F12: https://www.dfs.ny.gov/consumers/help_for_homeowners/insurance/problems_obtaining_insurance | G12: 46296 | H12: New York | I12: Regulator-published | J12: Primary source | K12: 46296
A13: NYPIUA | B13: What it covers | C13: Basic Form generally covers fire and extended-coverage perils: wind (including hurricane), hail, explosion (except steam boilers), riot, civil commotion, aircraft, vehicles, smoke, vandalism and malicious mischief; a Broad Form option adds more perils | D13: DFS homeowners guide (NYPIUA) | E13: NY Dept of Financial Services - Homeowners Insurance: Problems Obtaining Insurance (NYPIUA) | F13: https://www.dfs.ny.gov/consumers/help_for_homeowners/insurance/problems_obtaining_insurance | G13: 46296 | H13: New York | I13: Regulator-published | J13: Primary source | K13: 46296
... A21: Discounts | B21: Required hurricane-mitigation discount | C21: Insurers must provide discounts for hurricane-resistant shutters and hurricane-resistant windows and doors | D21: DFS consumer guide (Ways to Save on Homeowners Insurance) | E21: NY Dept of Financial Services - Ways to Save on Homeowners Insurance | F21: https://www.dfs.ny.gov/system/files/documents/2026/02/Ways-to-Save-Homeowners-Insurance.pdf | G21: 46296 | H21: New York | I21: Regulator-published | J21: Primary source | K21: 46296

Sheet IL Auto Verified
A1: Topic | B1: Fact | C1: Value | D1: Legal Citation | E1: Source | F1: Source URL | G1: Date Collected | H1: Geographic Scope | I1: Data Type | J1: Verification Status | K1: Last Updated | L1: Notes
A2: Minimum liability | B2: Bodily injury per person | C2: $25,000 | D2: IDOI auto shopping guide | E2: Illinois Dept of Insurance - Auto Insurance Shopping Guide | F2: https://idoi.illinois.gov/consumers/consumerinsurance/auto-insurance-shopping-guide.html | G2: 46296 | H2: Illinois | I2: Regulator-published | J2: Primary source | K2: 46296
A3: Minimum liability | B3: Bodily injury per accident | C3: $50,000 | D3: IDOI auto shopping guide | E3: Illinois Dept of Insurance - Auto Insurance Shopping Guide | F3: https://idoi.illinois.gov/consumers/consumerinsurance/auto-insurance-shopping-guide.html | G3: 46296 | H3: Illinois | I3: Regulator-published | J3: Primary source | K3: 46296
A4: Minimum liability | B4: Property damage | C4: $20,000 | D4: IDOI auto shopping guide | E4: Illinois Dept of Insurance - Auto Insurance Shopping Guide | F4: https://idoi.illinois.gov/consumers/consumerinsurance/auto-insurance-shopping-guide.html | G4: 46296 | H4: Illinois | I4: Regulator-published | J4: Primary source | K4: 46296
A5: Coverage | B5: Uninsured motorist bodily injury | C5: Required by law; minimum limits of $25,000 per person and $50,000 per accident, the same as the liability minimums | D5: IDOI auto shopping guide | E5: Illinois Dept of Insurance - Auto Insurance Shopping Guide | F5: https://idoi.illinois.gov/consumers/consumerinsurance/auto-insurance-shopping-guide.html | G5: 46296 | H5: Illinois | I5: Regulator-published | J5: Primary source | K5: 46296
A6: Coverage | B6: Underinsured motorist (UIM) | C6: Mandatory when the policyholder purchases higher uninsured-motorist limits; pays the difference between the UIM limit and an at-fault driver's insufficient liability coverage | D6: IDOI auto shopping guide | E6: Illinois Dept of Insurance - Auto Insurance Shopping Guide | F6: https://idoi.illinois.gov/consumers/consumerinsurance/auto-insurance-shopping-guide.html | G6: 46296 | H6: Illinois | I6: Regulator-published | J6: Primary source | K6: 46296
A7: Coverage | B7: Uninsured motorist property damage (UMPD) | C7: Optional; the company must offer this coverage with a maximum $250 deductible | D7: IDOI auto shopping guide | E7: Illinois Dept of Insurance - Auto Insurance Shopping Guide | F7: https://idoi.illinois.gov/consumers/consumerinsurance/auto-insurance-shopping-guide.html | G7: 46296 | H7: Illinois | I7: Regulator-published | J7: Primary source | K7: 46296
A8: Coverage | B8: Physical damage (collision/comprehensive) | C8: Not required by state law, but lenders typically require it for financed vehicles; deductibles range from $0 to $1,000 | D8: IDOI auto shopping guide | E8: Illinois Dept of Insurance - Auto Insurance Shopping Guide | F8: https://idoi.illinois.gov/consumers/consumerinsurance/auto-insurance-shopping-guide.html | G8: 46296 | H8: Illinois | I8: Regulator-published | J8: Primary source | K8: 46296
A9: Coverage | B9: Medical payments | C9: Optional coverage available for medical and funeral expenses (Illinois does not require PIP/no-fault coverage) | D9: IDOI auto shopping guide | E9: Illinois Dept of Insurance - Auto Insurance Shopping Guide | F9: https://idoi.illinois.gov/consumers/consumerinsurance/auto-insurance-shopping-guide.html | G9: 46296 | H9: Illinois | I9: Regulator-published | J9: Primary source | K9: 46296
A10: Discounts | B10: Notable discounts available | C10: Good student (B average or better), defensive driver (age 55+), multiple vehicles, safety devices, low mileage, and bundled policies | D10: IDOI auto shopping guide | E10: Illinois Dept of Insurance - Auto Insurance Shopping Guide | F10: https://idoi.illinois.gov/consumers/consumerinsurance/auto-insurance-shopping-guide.html | G10: 46296 | H10: Illinois | I10: Regulator-published | J10: Primary source | K10: 46296
A11: Rating factors | B11: Credit-based insurance score restrictions | C11: Credit-based insurance scores used for auto and home insurance may not consider race, color, national origin, religion, gender, marital status, age, income, occupation or employment history, location of residence, any interest rate being charged, child/family support obligations or rental agreements, or certain credit inquiries (account review, employment, promotional) or credit counseling participation; insurers cannot base renewal rates solely on credit information; an insurer must use a credit report or score obtained within 90 days of writing or renewing a policy to take an adverse action; consumers may request premium reconsideration after an extraordinary life circumstance such as a catastrophic event, job loss, or serious illness | D11: 215 ILCS 157 (Use of Credit Information in Personal Insurance Act) | E11: Illinois Dept of Insurance - Credit: How Insurers Use It | F11: https://idoi.illinois.gov/consumers/consumerinsurance/credit.html | G11: 46296 | H11: Illinois | I11: Regulator-published | J11: Primary source | K11: 46296

Sheet IL Home Verified
A1: Topic | B1: Fact | C1: Value | D1: Legal Citation | E1: Source | F1: Source URL | G1: Date Collected | H1: Geographic Scope | I1: Data Type | J1: Verification Status | K1: Last Updated | L1: Notes
A2: Coverage | B2: Dwelling coverage | C2: Covers damage to the house; the face amount of the policy (for example $100,000) is the most you will receive if the house is totally destroyed | D2: IDOI homeowner/renter shopping tips | E2: Illinois Dept of Insurance - Homeowner/Renter Shopping Tips and Information | F2: https://idoi.illinois.gov/consumers/consumerinsurance/homeownerrenter/shopping-tips-and-information.html | G2: 46296 | H2: Illinois | I2: Regulator-published | J2: Primary source | K2: 46296
A3: Coverage | B3: Other structures | C3: Covers damage to other structures such as a detached garage, work shed, or fencing | D3: IDOI homeowner/renter shopping tips | E3: Illinois Dept of Insurance - Homeowner/Renter Shopping Tips and Information | F3: https://idoi.illinois.gov/consumers/consumerinsurance/homeownerrenter/shopping-tips-and-information.html | G3: 46296 | H3: Illinois | I3: Regulator-published | J3: Primary source | K3: 46296
A4: Coverage | B4: Personal property | C4: Covers damage to or loss of household contents and other personal belongings used, owned, or worn by you and your family | D4: IDOI homeowner/renter shopping tips | E4: Illinois Dept of Insurance - Homeowner/Renter Shopping Tips and Information | F4: https://idoi.illinois.gov/consumers/consumerinsurance/homeownerrenter/shopping-tips-and-information.html | G4: 46296 | H4: Illinois | I4: Regulator-published | J4: Primary source | K4: 46296
A5: Coverage | B5: Additional living expense | C5: Covers necessary living costs when the home cannot be occupied due to a covered loss | D5: IDOI homeowner/renter shopping tips | E5: Illinois Dept of Insurance - Homeowner/Renter Shopping Tips and Information | F5: https://idoi.illinois.gov/consumers/consumerinsurance/homeownerrenter/shopping-tips-and-information.html | G5: 46296 | H5: Illinois | I5: Regulator-published | J5: Primary source | K5: 46296
A6: Liability | B6: Comprehensive personal liability | C6: Protects against claims arising from accidents to others on property you own or rent | D6: IDOI homeowner/renter shopping tips | E6: Illinois Dept of Insurance - Homeowner/Renter Shopping Tips and Information | F6: https://idoi.illinois.gov/consumers/consumerinsurance/homeownerrenter/shopping-tips-and-information.html | G6: 46296 | H6: Illinois | I6: Regulator-published | J6: Primary source | K6: 46296
A7: Liability | B7: Medical expense coverage | C7: Limited to an amount per person and per accident for injuries occurring on your premises | D7: IDOI homeowner/renter shopping tips | E7: Illinois Dept of Insurance - Homeowner/Renter Shopping Tips and Information | F7: https://idoi.illinois.gov/consumers/consumerinsurance/homeownerrenter/shopping-tips-and-information.html | G7: 46296 | H7: Illinois | I7: Regulator-published | J7: Primary source | K7: 46296
A8: Settlement | B8: Replacement cost vs actual cash value | C8: Replacement cost rebuilds without a depreciation deduction; actual cash value applies depreciation; it is recommended to insure the home for at least 80% of its replacement value | D8: IDOI homeowner/renter shopping tips | E8: Illinois Dept of Insurance - Homeowner/Renter Shopping Tips and Information | F8: https://idoi.illinois.gov/consumers/consumerinsurance/homeownerrenter/shopping-tips-and-information.html | G8: 46296 | H8: Illinois | I8: Regulator-published | J8: Primary source | K8: 46296
A9: Coverage | B9: Flood and earthquake exclusion | C9: Flood and earthquake damage are explicitly not covered by standard homeowners policies | D9: IDOI homeowner/renter shopping tips | E9: Illinois Dept of Insurance - Homeowner/Renter Shopping Tips and Information | F9: https://idoi.illinois.gov/consumers/consumerinsurance/homeownerrenter/shopping-tips-and-information.html | G9: 46296 | H9: Illinois | I9: Regulator-published | J9: Primary source | K9: 46296
A10: Deductibles | B10: Typical deductible range | C10: Typically $100 to $250 or more | D10: IDOI homeowner/renter shopping tips | E10: Illinois Dept of Insurance - Homeowner/Renter Shopping Tips and Information | F10: https://idoi.illinois.gov/consumers/consumerinsurance/homeownerrenter/shopping-tips-and-information.html | G10: 46296 | H10: Illinois | I10: Regulator-published | J10: Primary source | K10: 46296
A11: Discounts | B11: Available discounts | C11: Insurers may offer discounts for bundling auto coverage, home security systems, or disaster-proofing measures | D11: IDOI homeowner/renter shopping tips | E11: Illinois Dept of Insurance - Homeowner/Renter Shopping Tips and Information | F11: https://idoi.illinois.gov/consumers/consumerinsurance/homeownerrenter/shopping-tips-and-information.html | G11: 46296 | H11: Illinois | I11: Regulator-published | J11: Primary source | K11: 46296
A12: Illinois FAIR Plan | B12: What it is | C12: The Illinois FAIR Plan Association's mission is to make basic property insurance available to qualified applicants who have not been able to obtain property insurance; it offers Dwelling Property and Homeowners policies | D12: Illinois FAIR Plan - Important Insurance Information | E12: Illinois FAIR Plan Association - Important Insurance Information | F12: https://www.illinoisfairplan.com/important-insurance-information.html | G12: 46296 | H12: Illinois | I12: Regulator-published | J12: Primary source | K12: 46296
A13: Illinois FAIR Plan | B13: What it covers | C13: Fire, lightning, wind, hail, explosion, smoke, vehicles, aircraft, and vandalism and malicious mischief; homeowners policies additionally provide burglary, theft and personal liability coverage | D13: Illinois FAIR Plan - Consumers page | E13: Illinois FAIR Plan Association - Consumers | F13: https://www.illinoisfairplan.com/consumers.html | G13: 46296 | H13: Illinois | I13: Regulator-published | J13: Primary source | K13: 46296 | L13: Unlike California's FAIR Plan or New York's NYPIUA, Illinois's FAIR Plan homeowners form includes theft and liability coverage.
A14: Illinois FAIR Plan | B14: Earthquake endorsement | C14: Earthquake coverage is available, upon request, as an endorsement to the Dwelling Property and Homeowners policy, with a standard 5% deductible; not available for Commercial Property | D14: Illinois FAIR Plan - Consumers page | E14: Illinois FAIR Plan Association - Consumers | F14: https://www.illinoisfairplan.com/consumers.html | G14: 46296 | H14: Illinois | I14: Regulator-published | J14: Primary source | K14: 46296
A15: Illinois FAIR Plan | B15: Eligibility | C15: The applicant must be unable to buy insurance through the standard market for reasons beyond their control, and the property must meet reasonable safety standards verified by a representative inspection | D15: Illinois FAIR Plan - Consumers page | E15: Illinois FAIR Plan Association - Consumers | F15: https://www.illinoisfairplan.com/consumers.html | G15: 46296 | H15: Illinois | I15: Regulator-published | J15: Primary source | K15: 46296
A16: Non-renewal | B16: Notice period for policies active less than 5 years | C16: At least 30 days before the nonrenewal date | D16: IDOI non-renewal guide | E16: Illinois Dept of Insurance - If Your Homeowners Insurance Policy is Non-Renewed | F16: https://idoi.illinois.gov/consumers/consumerinsurance/homeownerrenter/if-your-homeowners-insurance-policy-is-non-renewed.html | G16: 46296 | H16: Illinois | I16: Regulator-published | J16: Primary source | K16: 46296
A17: Non-renewal | B17: Prohibited reasons | C17: A company cannot nonrenew based on the age or location of the property, or the age, gender, race, color, ancestry, marital status, or occupation of the occupants, or solely on credit report information | D17: IDOI non-renewal guide | E17: Illinois Dept of Insurance - If Your Homeowners Insurance Policy is Non-Renewed | F17: https://idoi.illinois.gov/consumers/consumerinsurance/homeownerrenter/if-your-homeowners-insurance-policy-is-non-renewed.html | G17: 46296 | H17: Illinois | I17: Regulator-published | J17: Primary source | K17: 46296
